Workbook

Sheet Income Statement
A1: Company Fundamentals - Income Statement
A2: Company Name | B2: Wesfarmers Ltd (WES.AX)
A3: Country of Exchange | B3: Australia
A4: Country of Headquarters | B4: Australia
A5: TRBC Industry Group | B5: Diversified Retail
A6: CF Template | B6: IND
A7: Consolidation Basis | B7: Consolidated
A8: Scaling | B8: Millions
A9: Period | B9: Annual
A10: Export Date | B10: 46164.123
A11: Statement Data | B11: 2025 | C11: 2024 | D11: 2023 | E11: 2022 | F11: 2021
A12: Period End Date | B12: 45838 | C12: 45473 | D12: 45107 | E12: 44742 | F12: 44377
A13: Statement Date | B13: 45838 | C13: 45473 | D13: 45107 | E13: 44742 | F13: 44377
A14: Standardized Currency | B14: AUD | C14: AUD | D14: AUD | E14: AUD | F14: AUD
A15: Template Type | B15: Industrial - Operating | C15: Industrial - Operating | D15: Industrial - Operating | E15: Industrial - Operating | F15: Industrial - Operating
A17: Income Statement - Standardized (Currency: Standardized)
A18: Field Name | B18: 30-06-2025 | C18: 30-06-2024 | D18: 30-06-2023 | E18: 30-06-2022 | F18: 30-06-2021 | G18: % Rev 2025 | H18: Avg % Rev | I18: Formula Description | J18: Excel Formula | K18: F2026 | L18: F2027 | M18: F2028 | N18: F2029 | O18: F2030 | P18: % Rev 2024 | Q18: % Rev 2023 | R18: % Rev 2022 | S18: % Rev 2021
A19: Revenues
A20: Revenue from Goods & Services | B20: 45576 | C20: 44047 | D20: 43417 | E20: 36679 | F20: 33797 | G20: =IFERROR(B20/B25,"") -> 0.99728665 | H20: =IFERROR(AVERAGE(G20,P20,Q20,R20,S20),"") -> 0.99649207 | I20: Avg % of total revenue | J20: H20*K25 | K20: =ROUND(H20*K25,0) -> 49928 | L20: =ROUND(H20*L25,0) -> 53004 | M20: =ROUND(H20*M25,0) -> 56081 | N20: =ROUND(H20*N25,0) -> 59157 | O20: =ROUND(H20*O25,0) -> 62233 | P20: =IFERROR(C20/C25,"") -> 0.99678653 | Q20: =IFERROR(D20/D25,"") -> 0.99694604 | R20: =IFERROR(E20/E25,"") -> 0.9956838 | S20: =IFERROR(F20/F25,"") -> 0.99575734
A21: Sales of Goods & Services - Net - Unclassified | B21: 45576 | C21: 44047 | D21: 43417 | E21: 36679 | F21: 33797 | G21: =IFERROR(B21/B25,"") -> 0.99728665 | H21: =IFERROR(AVERAGE(G21,P21,Q21,R21,S21),"") -> 0.99649207 | I21: row 20 (same item, different classification) | J21: K20 | K21: =K20 -> 49928 | L21: =L20 -> 53004 | M21: =M20 -> 56081 | N21: =N20 -> 59157 | O21: =O20 -> 62233 | P21: =IFERROR(C21/C25,"") -> 0.99678653 | Q21: =IFERROR(D21/D25,"") -> 0.99694604 | R21: =IFERROR(E21/E25,"") -> 0.9956838 | S21: =IFERROR(F21/F25,"") -> 0.99575734
A22: Revenue from Financing-Related Operations | B22: 38 | C22: 47 | D22: 41 | E22: 59 | F22: 51 | G22: =IFERROR(B22/B25,"") -> 0.00083150985 | H22: =IFERROR(AVERAGE(G22,P22,Q22,R22,S22),"") -> 0.0011881568 | I22: Avg % of total revenue | J22: H22*K25 | K22: =ROUND(H22*K25,0) -> 60 | L22: =ROUND(H22*L25,0) -> 63 | M22: =ROUND(H22*M25,0) -> 67 | N22: =ROUND(H22*N25,0) -> 71 | O22: =ROUND(H22*O25,0) -> 74 | P22: =IFERROR(C22/C25,"") -> 0.0010636131 | Q22: =IFERROR(D22/D25,"") -> 0.00094144661 | R22: =IFERROR(E22/E25,"") -> 0.001601607 | S22: =IFERROR(F22/F25,"") -> 0.0015026075
A23: Business-Related Financing Revenue - Other | B23: 38 | C23: 47 | D23: 41 | E23: 59 | F23: 51 | G23: =IFERROR(B23/B25,"") -> 0.00083150985 | H23: =IFERROR(AVERAGE(G23,P23,Q23,R23,S23),"") -> 0.0011881568 | I23: row 22 (same item, different classification) | J23: K22 | K23: =K22 -> 60 | L23: =L22 -> 63 | M23: =M22 -> 67 | N23: =N22 -> 71 | O23: =O22 -> 74 | P23: =IFERROR(C23/C25,"") -> 0.0010636131 | Q23: =IFERROR(D23/D25,"") -> 0.00094144661 | R23: =IFERROR(E23/E25,"") -> 0.001601607 | S23: =IFERROR(F23/F25,"") -> 0.0015026075
A24: Revenue from Business-Related Activities - Other - Total | B24: 86 | C24: 95 | D24: 92 | E24: 100 | F24: 93 | G24: =IFERROR(B24/B25,"") -> 0.0018818381 | H24: =IFERROR(AVERAGE(G24,P24,Q24,R24,S24),"") -> 0.0023197692 | I24: Avg % of total revenue | J24: H24*K25 | K24: =ROUND(H24*K25,0) -> 116 | L24: =ROUND(H24*L25,0) -> 123 | M24: =ROUND(H24*M25,0) -> 131 | N24: =ROUND(H24*N25,0) -> 138 | O24: =ROUND(H24*O25,0) -> 145 | P24: =IFERROR(C24/C25,"") -> 0.0021498563 | Q24: =IFERROR(D24/D25,"") -> 0.0021125144 | R24: =IFERROR(E24/E25,"") -> 0.0027145882 | S24: =IFERROR(F24/F25,"") -> 0.0027400489
A25: Revenue from Business Activities - Total | B25: =B20+B22+B24 -> 45700 | C25: =C20+C22+C24 -> 44189 | D25: =D20+D22+D24 -> 43550 | E25: =E20+E22+E24 -> 36838 | F25: =F20+F22+F24 -> 33941 | G25: =IFERROR(B25/B25,"") -> 1 | H25: =IFERROR(AVERAGE(G25,P25,Q25,R25,S25),"") -> 1 | I25: Regression on Year (OLS, see Analysis sheet) | J25: alpha + slope*year [R²=0.9007] | K25: 50104 | L25: 53191 | M25: 56278 | N25: 59365 | O25: 62452 | P25: =IFERROR(C25/C25,"") -> 1 | Q25: =IFERROR(D25/D25,"") -> 1 | R25: =IFERROR(E25/E25,"") -> 1 | S25: =IFERROR(F25/F25,"") -> 1
A26: Operating Expenses
A27: Cost of Operating Revenue | B27: 31772 | C27: 30628 | D27: 30606 | E27: 25013 | F27: 22386 | G27: =IFERROR(B27/B25,"") -> 0.69522976 | H27: =IFERROR(AVERAGE(G27,P27,Q27,R27,S27),"") -> 0.68593562 | I27: Avg % of total revenue | J27: H27*K25 | K27: =ROUND(H27*K25,0) -> 34368 | L27: =ROUND(H27*L25,0) -> 36486 | M27: =ROUND(H27*M25,0) -> 38603 | N27: =ROUND(H27*N25,0) -> 40721 | O27: =ROUND(H27*O25,0) -> 42838 | P27: =IFERROR(C27/C25,"") -> 0.69311367 | Q27: =IFERROR(D27/D25,"") -> 0.70277842 | R27: =IFERROR(E27/E25,"") -> 0.67899995 | S27: =IFERROR(F27/F25,"") -> 0.65955629
A28: Cost of Revenues - Total | B28: =B27 -> 31772 | C28: =C27 -> 30628 | D28: =D27 -> 30606 | E28: =E27 -> 25013 | F28: =F27 -> 22386 | G28: =IFERROR(B28/B25,"") -> 0.69522976 | H28: =IFERROR(AVERAGE(G28,P28,Q28,R28,S28),"") -> 0.68593562 | I28: row 27 (same item, different classification) | J28: K27 | K28: =K27 -> 34368 | L28: =L27 -> 36486 | M28: =M27 -> 38603 | N28: =N27 -> 40721 | O28: =O27 -> 42838 | P28: =IFERROR(C28/C25,"") -> 0.69311367 | Q28: =IFERROR(D28/D25,"") -> 0.70277842 | R28: =IFERROR(E28/E25,"") -> 0.67899995 | S28: =IFERROR(F28/F25,"") -> 0.65955629
A29: Amortization in Cost of Revenues | B29: 125 | C29: 128 | D29: 191 | E29: 158 | F29: 144 | G29: =IFERROR(B29/B25,"") -> 0.0027352298 | H29: =IFERROR(AVERAGE(G29,P29,Q29,R29,S29),"") -> 0.0037098695 | I29: Avg % of total revenue | J29: H29*K25 | K29: =ROUND(H29*K25,0) -> 186 | L29: =ROUND(H29*L25,0) -> 197 | M29: =ROUND(H29*M25,0) -> 209 | N29: =ROUND(H29*N25,0) -> 220 | O29: =ROUND(H29*O25,0) -> 232 | P29: =IFERROR(C29/C25,"") -> 0.0028966485 | Q29: =IFERROR(D29/D25,"") -> 0.0043857635 | R29: =IFERROR(E29/E25,"") -> 0.0042890494 | S29: =IFERROR(F29/F25,"") -> 0.0042426564
A30: Depreciation in Cost of Revenues | B30: 1708 | C30: 1672 | D30: 1510 | E30: 1417 | F30: 1365 | G30: =IFERROR(B30/B25,"") -> 0.037374179 | H30: =IFERROR(AVERAGE(G30,P30,Q30,R30,S30),"") -> 0.0377134 | I30: Avg dep rate × PPE_net_{t-1} (from BS) | J30: 0.1453×PPE_net_{t-1} (Balance Sheet row 41) | K30: =ROUND(0.1453*'Balance Sheet'!G41,0) -> 1604 | L30: =ROUND(0.1453*'Balance Sheet'!T41,0) -> 1671 | M30: =ROUND(0.1453*'Balance Sheet'!U41,0) -> 1747 | N30: =ROUND(0.1453*'Balance Sheet'!V41,0) -> 1830 | O30: =ROUND(0.1453*'Balance Sheet'!W41,0) -> 1919 | P30: =IFERROR(C30/C25,"") -> 0.037837471 | Q30: =IFERROR(D30/D25,"") -> 0.03467279 | R30: =IFERROR(E30/E25,"") -> 0.038465715 | S30: =IFERROR(F30/F25,"") -> 0.040216847
A31: Material Expenses | B31: 29939 | C31: 28828 | D31: 28905 | E31: 23438 | F31: 20877 | G31: =IFERROR(B31/B25,"") -> 0.65512035 | H31: =IFERROR(AVERAGE(G31,P31,Q31,R31,S31),"") -> 0.64451235 | I31: Avg % of total revenue | J31: H31*K25 | K31: =ROUND(H31*K25,0) -> 32293 | L31: =ROUND(H31*L25,0) -> 34282 | M31: =ROUND(H31*M25,0) -> 36272 | N31: =ROUND(H31*N25,0) -> 38261 | O31: =ROUND(H31*O25,0) -> 40251 | P31: =IFERROR(C31/C25,"") -> 0.65237955 | Q31: =IFERROR(D31/D25,"") -> 0.66371986 | R31: =IFERROR(E31/E25,"") -> 0.63624518 | S31: =IFERROR(F31/F25,"") -> 0.61509679
A32: Material Expenses - Materials, Inventory, Own Work & Utility - Unclassified | B32: 29939 | C32: 28828 | D32: 28905 | E32: 23438 | F32: 20877 | G32: =IFERROR(B32/B25,"") -> 0.65512035 | H32: =IFERROR(AVERAGE(G32,P32,Q32,R32,S32),"") -> 0.64451235 | I32: row 31 (same item, different classification) | J32: K31 | K32: =K31 -> 32293 | L32: =L31 -> 34282 | M32: =M31 -> 36272 | N32: =N31 -> 38261 | O32: =O31 -> 40251 | P32: =IFERROR(C32/C25,"") -> 0.65237955 | Q32: =IFERROR(D32/D25,"") -> 0.66371986 | R32: =IFERROR(E32/E25,"") -> 0.63624518 | S32: =IFERROR(F32/F25,"") -> 0.61509679
A33: Gross Profit - Industrials/Property - Total | B33: =B25-B28 -> 13928 | C33: =C25-C28 -> 13561 | D33: =D25-D28 -> 12944 | E33: =E25-E28 -> 11825 | F33: =F25-F28 -> 11555 | G33: =IFERROR(B33/B25,"") -> 0.30477024 | H33: =IFERROR(AVERAGE(G33,P33,Q33,R33,S33),"") -> 0.31406438 | I33: Revenue Total – Cost of Revenues | J33: K25-K28 | K33: =K25-K28 -> 15736 | L33: =L25-L28 -> 16705 | M33: =M25-M28 -> 17675 | N33: =N25-N28 -> 18644 | O33: =O25-O28 -> 19614 | P33: =IFERROR(C33/C25,"") -> 0.30688633 | Q33: =IFERROR(D33/D25,"") -> 0.29722158 | R33: =IFERROR(E33/E25,"") -> 0.32100005 | S33: =IFERROR(F33/F25,"") -> 0.34044371
A34: Selling, General & Administrative Expenses - Total | B34: =B35+B36+B37+B38 -> 8886 | C34: =C35+C36+C37+C38 -> 8191 | D34: =D35+D36+D37+D38 -> 7879 | E34: =E35+E36+E37+E38 -> 7230 | F34: =F35+F36+F37+F38 -> 6764 | G34: =IFERROR(B34/B25,"") -> 0.19444201 | H34: =IFERROR(AVERAGE(G34,P34,Q34,R34,S34),"") -> 0.19125502 | I34: Avg % of total revenue | J34: H34*K25 | K34: =ROUND(H34*K25,0) -> 9583 | L34: =ROUND(H34*L25,0) -> 10173 | M34: =ROUND(H34*M25,0) -> 10763 | N34: =ROUND(H34*N25,0) -> 11354 | O34: =ROUND(H34*O25,0) -> 11944 | P34: =IFERROR(C34/C25,"") -> 0.18536287 | Q34: =IFERROR(D34/D25,"") -> 0.18091848 | R34: =IFERROR(E34/E25,"") -> 0.19626473 | S34: =IFERROR(F34/F25,"") -> 0.199287
A35: Selling, General & Administrative Expenses - Unclassified | B35: 840 | C35: 687 | D35: 704 | E35: 668 | F35: 540 | G35: =IFERROR(B35/B25,"") -> 0.018380744 | H35: =IFERROR(AVERAGE(G35,P35,Q35,R35,S35),"") -> 0.016827267 | I35: Avg % of total revenue | J35: H35*K25 | K35: =ROUND(H35*K25,0) -> 843 | L35: =ROUND(H35*L25,0) -> 895 | M35: =ROUND(H35*M25,0) -> 947 | N35: =ROUND(H35*N25,0) -> 999 | O35: =ROUND(H35*O25,0) -> 1051 | P35: =IFERROR(C35/C25,"") -> 0.015546856 | Q35: =IFERROR(D35/D25,"") -> 0.016165327 | R35: =IFERROR(E35/E25,"") -> 0.018133449 | S35: =IFERROR(F35/F25,"") -> 0.015909961
A36: Labor & Related Expenses including Stock-Based Compensation in Selling, General & Administrative Expenses | B36: 6842 | C36: 6639 | D36: 6333 | E36: 5840 | F36: 5500 | G36: =IFERROR(B36/B25,"") -> 0.14971554 | H36: =IFERROR(AVERAGE(G36,P36,Q36,R36,S36),"") -> 0.15319069 | I36: Avg % of total revenue | J36: H36*K25 | K36: =ROUND(H36*K25,0) -> 7675 | L36: =ROUND(H36*L25,0) -> 8148 | M36: =ROUND(H36*M25,0) -> 8621 | N36: =ROUND(H36*N25,0) -> 9094 | O36: =ROUND(H36*O25,0) -> 9567 | P36: =IFERROR(C36/C25,"") -> 0.15024101 | Q36: =IFERROR(D36/D25,"") -> 0.14541906 | R36: =IFERROR(E36/E25,"") -> 0.15853195 | S36: =IFERROR(F36/F25,"") -> 0.1620459
A37: Operations & Maintenance (Utility) | B37: 638 | C37: 319 | D37: 315 | E37: 268 | F37: 247 | G37: =IFERROR(B37/B25,"") -> 0.013960613 | H37: =IFERROR(AVERAGE(G37,P37,Q37,R37,S37),"") -> 0.00859302 | I37: Avg % of total revenue | J37: H37*K25 | K37: =ROUND(H37*K25,0) -> 431 | L37: =ROUND(H37*L25,0) -> 457 | M37: =ROUND(H37*M25,0) -> 484 | N37: =ROUND(H37*N25,0) -> 510 | O37: =ROUND(H37*O25,0) -> 537 | P37: =IFERROR(C37/C25,"") -> 0.0072189912 | Q37: =IFERROR(D37/D25,"") -> 0.0072330654 | R37: =IFERROR(E37/E25,"") -> 0.0072750964 | S37: =IFERROR(F37/F25,"") -> 0.0072773342
A38: Selling, General & Administrative Expenses - Other - Total | B38: 566 | C38: 546 | D38: 527 | E38: 454 | F38: 477 | G38: =IFERROR(B38/B25,"") -> 0.01238512 | H38: =IFERROR(AVERAGE(G38,P38,Q38,R38,S38),"") -> 0.01264404 | I38: Avg % of total revenue | J38: H38*K25 | K38: =ROUND(H38*K25,0) -> 634 | L38: =ROUND(H38*L25,0) -> 673 | M38: =ROUND(H38*M25,0) -> 712 | N38: =ROUND(H38*N25,0) -> 751 | O38: =ROUND(H38*O25,0) -> 790 | P38: =IFERROR(C38/C25,"") -> 0.012356016 | Q38: =IFERROR(D38/D25,"") -> 0.012101033 | R38: =IFERROR(E38/E25,"") -> 0.01232423 | S38: =IFERROR(F38/F25,"") -> 0.014053799
A39: Rental Expense | B39: 48 | C39: 41 | D39: 35 | E39: 58 | G39: =IFERROR(B39/B25,"") -> 0.0010503282 | H39: =IFERROR(AVERAGE(G39,P39,Q39,R39,S39),"") -> 0.00087125921 | I39: Avg % of total revenue | J39: H39*K25 | K39: =ROUND(H39*K25,0) -> 44 | L39: =ROUND(H39*L25,0) -> 46 | M39: =ROUND(H39*M25,0) -> 49 | N39: =ROUND(H39*N25,0) -> 52 | O39: =ROUND(H39*O25,0) -> 54 | P39: =IFERROR(C39/C25,"") -> 0.00092783272 | Q39: =IFERROR(D39/D25,"") -> 0.00080367394 | R39: =IFERROR(E39/E25,"") -> 0.0015744612 | S39: =IFERROR(F39/F25,"") -> 0
A40: Occupancy Expense - Other | B40: 513 | C40: 500 | D40: 470 | E40: 384 | F40: 461 | G40: =IFERROR(B40/B25,"") -> 0.011225383 | H40: =IFERROR(AVERAGE(G40,P40,Q40,R40,S40),"") -> 0.011467804 | I40: Avg % of total revenue | J40: H40*K25 | K40: =ROUND(H40*K25,0) -> 575 | L40: =ROUND(H40*L25,0) -> 610 | M40: =ROUND(H40*M25,0) -> 645 | N40: =ROUND(H40*N25,0) -> 681 | O40: =ROUND(H40*O25,0) -> 716 | P40: =IFERROR(C40/C25,"") -> 0.011315033 | Q40: =IFERROR(D40/D25,"") -> 0.010792193 | R40: =IFERROR(E40/E25,"") -> 0.010424019 | S40: =IFERROR(F40/F25,"") -> 0.013582393
A41: Provision for Doubtful Accounts & Write-off | B41: 5 | C41: 5 | D41: 22 | E41: 12 | F41: 16 | G41: =IFERROR(B41/B25,"") -> 0.00010940919 | H41: =IFERROR(AVERAGE(G41,P41,Q41,R41,S41),"") -> 0.00030497657 | I41: Avg % of total revenue | J41: H41*K25 | K41: =ROUND(H41*K25,0) -> 15 | L41: =ROUND(H41*L25,0) -> 16 | M41: =ROUND(H41*M25,0) -> 17 | N41: =ROUND(H41*N25,0) -> 18 | O41: =ROUND(H41*O25,0) -> 19 | P41: =IFERROR(C41/C25,"") -> 0.00011315033 | Q41: =IFERROR(D41/D25,"") -> 0.00050516648 | R41: =IFERROR(E41/E25,"") -> 0.00032575058 | S41: =IFERROR(F41/F25,"") -> 0.00047140626
A42: Other Operating Expense/(Income) - Net | B42: 971 | C42: 1389 | D42: 1238 | E42: 1172 | F42: 1126 | G42: =IFERROR(B42/B25,"") -> 0.021247265 | H42: =IFERROR(AVERAGE(G42,P42,Q42,R42,S42),"") -> 0.029219542 | I42: Avg % of total revenue | J42: H42*K25 | K42: =ROUND(H42*K25,0) -> 1464 | L42: =ROUND(H42*L25,0) -> 1554 | M42: =ROUND(H42*M25,0) -> 1644 | N42: =ROUND(H42*N25,0) -> 1735 | O42: =ROUND(H42*O25,0) -> 1825 | P42: =IFERROR(C42/C25,"") -> 0.031433162 | Q42: =IFERROR(D42/D25,"") -> 0.028427095 | R42: =IFERROR(E42/E25,"") -> 0.031814974 | S42: =IFERROR(F42/F25,"") -> 0.033175216
A43: Other Operating Income - Total | B43: 125 | C43: 132 | D43: 124 | E43: 109 | F43: 84 | G43: =IFERROR(B43/B25,"") -> 0.0027352298 | H43: =IFERROR(AVERAGE(G43,P43,Q43,R43,S43),"") -> 0.0028006969 | I43: Avg % of total revenue | J43: H43*K25 | K43: =ROUND(H43*K25,0) -> 140 | L43: =ROUND(H43*L25,0) -> 149 | M43: =ROUND(H43*M25,0) -> 158 | N43: =ROUND(H43*N25,0) -> 166 | O43: =ROUND(H43*O25,0) -> 175 | P43: =IFERROR(C43/C25,"") -> 0.0029871688 | Q43: =IFERROR(D43/D25,"") -> 0.002847302 | R43: =IFERROR(E43/E25,"") -> 0.0029589011 | S43: =IFERROR(F43/F25,"") -> 0.0024748829
A44: Other Operating Expense | B44: 1096 | C44: 1521 | D44: 1362 | E44: 1281 | F44: 1210 | G44: =IFERROR(B44/B25,"") -> 0.023982495 | H44: =IFERROR(AVERAGE(G44,P44,Q44,R44,S44),"") -> 0.032020239 | I44: Avg % of total revenue | J44: H44*K25 | K44: =ROUND(H44*K25,0) -> 1604 | L44: =ROUND(H44*L25,0) -> 1703 | M44: =ROUND(H44*M25,0) -> 1802 | N44: =ROUND(H44*N25,0) -> 1901 | O44: =ROUND(H44*O25,0) -> 2000 | P44: =IFERROR(C44/C25,"") -> 0.034420331 | Q44: =IFERROR(D44/D25,"") -> 0.031274397 | R44: =IFERROR(E44/E25,"") -> 0.034773875 | S44: =IFERROR(F44/F25,"") -> 0.035650099
A45: Operating Expenses - Total | B45: =B28+B34+B42 -> 41629 | C45: =C28+C34+C42 -> 40208 | D45: =D28+D34+D42 -> 39723 | E45: =E28+E34+E42 -> 33415 | F45: =F28+F34+F42 -> 30276 | G45: =IFERROR(B45/B25,"") -> 0.91091904 | H45: =IFERROR(AVERAGE(G45,P45,Q45,R45,S45),"") -> 0.90641018 | I45: Sum: Cost of Rev + SGA + Other Op Exp/(Inc) | J45: K28+K34+K42 | K45: =K28+K34+K42 -> 45415 | L45: =L28+L34+L42 -> 48213 | M45: =M28+M34+M42 -> 51010 | N45: =N28+N34+N42 -> 53810 | O45: =O28+O34+O42 -> 56607 | P45: =IFERROR(C45/C25,"") -> 0.90990971 | Q45: =IFERROR(D45/D25,"") -> 0.912124 | R45: =IFERROR(E45/E25,"") -> 0.90707965 | S45: =IFERROR(F45/F25,"") -> 0.8920185
A46: Operating Profit
A47: Operating Profit before Non-Recurring Income/Expense | B47: 4071 | C47: 3981 | D47: 3827 | E47: 3423 | F47: 3665 | G47: =IFERROR(B47/B25,"") -> 0.089080963 | H47: =IFERROR(AVERAGE(G47,P47,Q47,R47,S47),"") -> 0.093589823 | I47: Revenue Total – Operating Expenses | J47: K25-K45 | K47: =K25-K45 -> 4689 | L47: =L25-L45 -> 4978 | M47: =M25-M45 -> 5268 | N47: =N25-N45 -> 5555 | O47: =O25-O45 -> 5845 | P47: =IFERROR(C47/C25,"") -> 0.090090294 | Q47: =IFERROR(D47/D25,"") -> 0.087876005 | R47: =IFERROR(E47/E25,"") -> 0.092920354 | S47: =IFERROR(F47/F25,"") -> 0.1079815
A48: Non-Operating Expenses
A49: Financing Income/(Expense) - Net - Total | B49: -412 | C49: -402 | D49: -354 | E49: -313 | F49: -344 | G49: =IFERROR(B49/B25,"") -> -0.0090153173 | H49: =IFERROR(AVERAGE(G49,P49,Q49,R49,S49),"") -> -0.0089746175 | I49: Interest Expense Net + Non-Interest Financial | J49: -(K50)+K52 | K49: =-(K50)+K52 -> -478 | L49: =-(L50)+L52 -> -402 | M49: =-(M50)+M52 -> -403 | N49: =-(N50)+N52 -> -404 | O49: =-(O50)+O52 -> -405 | P49: =IFERROR(C49/C25,"") -> -0.0090972867 | Q49: =IFERROR(D49/D25,"") -> -0.0081285878 | R49: =IFERROR(E49/E25,"") -> -0.0084966611 | S49: =IFERROR(F49/F25,"") -> -0.010135235
A50: Interest Expense - Net of (Interest Income) | B50: 393 | C50: 379 | D50: 336 | E50: 289 | F50: 316 | G50: =IFERROR(B50/B25,"") -> 0.0085995624 | H50: =IFERROR(AVERAGE(G50,P50,Q50,R50,S50),"") -> 0.0084094122 | I50: Avg int rate × LT debt excl leases_{t-1} (from BS) | J50: 0.098075×LT_debt_excl_leases_{t-1} (Balance Sheet row 116) | K50: =ROUND(0.098075*'Balance Sheet'!G116,0) -> 463 | L50: =ROUND(0.098075*'Balance Sheet'!T116,0) -> 386 | M50: =ROUND(0.098075*'Balance Sheet'!U116,0) -> 386 | N50: =ROUND(0.098075*'Balance Sheet'!V116,0) -> 386 | O50: =ROUND(0.098075*'Balance Sheet'!W116,0) -> 386 | P50: =IFERROR(C50/C25,"") -> 0.0085767951 | Q50: =IFERROR(D50/D25,"") -> 0.0077152698 | R50: =IFERROR(E50/E25,"") -> 0.0078451599 | S50: =IFERROR(F50/F25,"") -> 0.0093102737
A51: Interest Expense - Net of Capitalized Interest | B51: 393 | C51: 379 | D51: 336 | E51: 289 | F51: 316 | G51: =IFERROR(B51/B25,"") -> 0.0085995624 | H51: =IFERROR(AVERAGE(G51,P51,Q51,R51,S51),"") -> 0.0084094122 | I51: row 50 (same item, different classification) | J51: K50 | K51: =K50 -> 463 | L51: =L50 -> 386 | M51: =M50 -> 386 | N51: =N50 -> 386 | O51: =O50 -> 386 | P51: =IFERROR(C51/C25,"") -> 0.0085767951 | Q51: =IFERROR(D51/D25,"") -> 0.0077152698 | R51: =IFERROR(E51/E25,"") -> 0.0078451599 | S51: =IFERROR(F51/F25,"") -> 0.0093102737
A52: Non-Interest Financial Income/(Expense) - Total | B52: =SUM(B53:B54) -> -11 | C52: =SUM(C53:C54) -> -13 | D52: =SUM(D53:D54) -> -10 | E52: =SUM(E53:E54) -> -14 | F52: =SUM(F53:F54) -> -12 | G52: =IFERROR(B52/B25,"") -> -0.00024070022 | H52: =IFERROR(AVERAGE(G52,P52,Q52,R52,S52),"") -> -0.00029962185 | I52: Avg % of total revenue | J52: H52*K25 | K52: =ROUND(H52*K25,0) -> -15 | L52: =ROUND(H52*L25,0) -> -16 | M52: =ROUND(H52*M25,0) -> -17 | N52: =ROUND(H52*N25,0) -> -18 | O52: =ROUND(H52*O25,0) -> -19 | P52: =IFERROR(C52/C25,"") -> -0.00029419086 | Q52: =IFERROR(D52/D25,"") -> -0.00022962113 | R52: =IFERROR(E52/E25,"") -> -0.00038004235 | S52: =IFERROR(F52/F25,"") -> -0.0003535547
A53: Amortization of Deferred Financing Charges | B53: 4 | C53: 5 | D53: 4 | E53: 5 | F53: 8 | G53: =IFERROR(B53/B25,"") -> 8.7527352e-05 | H53: =IFERROR(AVERAGE(G53,P53,Q53,R53,S53),"") -> 0.00013279174 | I53: Avg % of total revenue | J53: H53*K25 | K53: =ROUND(H53*K25,0) -> 7 | L53: =ROUND(H53*L25,0) -> 7 | M53: =ROUND(H53*M25,0) -> 7 | N53: =ROUND(H53*N25,0) -> 8 | O53: =ROUND(H53*O25,0) -> 8 | P53: =IFERROR(C53/C25,"") -> 0.00011315033 | Q53: =IFERROR(D53/D25,"") -> 9.184845e-05 | R53: =IFERROR(E53/E25,"") -> 0.00013572941 | S53: =IFERROR(F53/F25,"") -> 0.00023570313
A54: Non-Interest Financial Income/(Expense) - Other - Net | B54: -15 | C54: -18 | D54: -14 | E54: -19 | F54: -20 | G54: =IFERROR(B54/B25,"") -> -0.00032822757 | H54: =IFERROR(AVERAGE(G54,P54,Q54,R54,S54),"") -> -0.00043241359 | I54: Avg % of total revenue | J54: H54*K25 | K54: =ROUND(H54*K25,0) -> -22 | L54: =ROUND(H54*L25,0) -> -23 | M54: =ROUND(H54*M25,0) -> -24 | N54: =ROUND(H54*N25,0) -> -26 | O54: =ROUND(H54*O25,0) -> -27 | P54: =IFERROR(C54/C25,"") -> -0.00040734119 | Q54: =IFERROR(D54/D25,"") -> -0.00032146958 | R54: =IFERROR(E54/E25,"") -> -0.00051577176 | S54: =IFERROR(F54/F25,"") -> -0.00058925783
A55: Sale of Tangible & Intangible Fixed Assets - Gain/(Loss) | B55: 1 | C55: 12 | D55: 41 | E55: 58 | F55: 3 | G55: =IFERROR(B55/B25,"") -> 2.1881838e-05 | H55: =IFERROR(AVERAGE(G55,P55,Q55,R55,S55),"") -> 0.00057954782 | I55: Avg % of total revenue | J55: H55*K25 | K55: =ROUND(H55*K25,0) -> 29 | L55: =ROUND(H55*L25,0) -> 31 | M55: =ROUND(H55*M25,0) -> 33 | N55: =ROUND(H55*N25,0) -> 34 | O55: =ROUND(H55*O25,0) -> 36 | P55: =IFERROR(C55/C25,"") -> 0.0002715608 | Q55: =IFERROR(D55/D25,"") -> 0.00094144661 | R55: =IFERROR(E55/E25,"") -> 0.0015744612 | S55: =IFERROR(F55/F25,"") -> 8.8388674e-05
A56: Equity Earnings/(Loss) - before Taxes including Non-Recurring | B56: 196 | C56: 35 | D56: 9 | E56: 173 | F56: 103 | G56: =IFERROR(B56/B25,"") -> 0.0042888403 | H56: =IFERROR(AVERAGE(G56,P56,Q56,R56,S56),"") -> 0.0026036934 | I56: Avg % of total revenue | J56: H56*K25 | K56: =ROUND(H56*K25,0) -> 130 | L56: =ROUND(H56*L25,0) -> 138 | M56: =ROUND(H56*M25,0) -> 147 | N56: =ROUND(H56*N25,0) -> 155 | O56: =ROUND(H56*O25,0) -> 163 | P56: =IFERROR(C56/C25,"") -> 0.00079205232 | Q56: =IFERROR(D56/D25,"") -> 0.00020665901 | R56: =IFERROR(E56/E25,"") -> 0.0046962376 | S56: =IFERROR(F56/F25,"") -> 0.0030346778
A57: Other Non-Operating Income/(Expense) - Total | F57: 59 | G57: =IFERROR(B57/B25,"") -> 0 | H57: =IFERROR(AVERAGE(G57,P57,Q57,R57,S57),"") -> 0.00034766212 | I57: Zero balance in FY2025 – not forecast | J57: n/a – not forecast | P57: =IFERROR(C57/C25,"") -> 0 | Q57: =IFERROR(D57/D25,"") -> 0 | R57: =IFERROR(E57/E25,"") -> 0 | S57: =IFERROR(F57/F25,"") -> 0.0017383106
A58: Non-Recurring Adjustments - Non-Operating- Decrease/(Increase) | F58: 59 | G58: =IFERROR(B58/B25,"") -> 0 | H58: =IFERROR(AVERAGE(G58,P58,Q58,R58,S58),"") -> 0.00034766212 | I58: Zero balance in FY2025 – not forecast | J58: n/a – not forecast | P58: =IFERROR(C58/C25,"") -> 0 | Q58: =IFERROR(D58/D25,"") -> 0 | R58: =IFERROR(E58/E25,"") -> 0 | S58: =IFERROR(F58/F25,"") -> 0.0017383106
A59: Normalized Pre-tax Profit | B59: 3856 | C59: 3626 | D59: 3523 | E59: 3341 | F59: 3486 | G59: =IFERROR(B59/B25,"") -> 0.084376368 | H59: =IFERROR(AVERAGE(G59,P59,Q59,R59,S59),"") -> 0.088146108 | I59: Operating Profit + Financing + Sale + Equity | J59: K47+K49+K55+K56 | K59: =K47+K49+K55+K56 -> 4370 | L59: =L47+L49+L55+L56 -> 4745 | M59: =M47+M49+M55+M56 -> 5045 | N59: =N47+N49+N55+N56 -> 5340 | O59: =O47+O49+O55+O56 -> 5639 | P59: =IFERROR(C59/C25,"") -> 0.08205662 | Q59: =IFERROR(D59/D25,"") -> 0.080895522 | R59: =IFERROR(E59/E25,"") -> 0.090694392 | S59: =IFERROR(F59/F25,"") -> 0.10270764
A60: Non-Recurring Income/Expense
A61: Non-Recurring Income/(Expense) - Total | B61: 197 | C61: -39 | D61: -14 | E61: -21 | F61: -113 | G61: =IFERROR(B61/B25,"") -> 0.0043107221 | H61: =IFERROR(AVERAGE(G61,P61,Q61,R61,S61),"") -> -0.00015853806 | I61: Avg % of total revenue | J61: H61*K25 | K61: =ROUND(H61*K25,0) -> -8 | L61: =ROUND(H61*L25,0) -> -8 | M61: =ROUND(H61*M25,0) -> -9 | N61: =ROUND(H61*N25,0) -> -9 | O61: =ROUND(H61*O25,0) -> -10 | P61: =IFERROR(C61/C25,"") -> -0.00088257259 | Q61: =IFERROR(D61/D25,"") -> -0.00032146958 | R61: =IFERROR(E61/E25,"") -> -0.00057006352 | S61: =IFERROR(F61/F25,"") -> -0.0033293067
A62: Impairment - Tangible & Intangible Fixed Assets | B62: 38 | C62: 39 | D62: 14 | E62: 21 | F62: 54 | G62: =IFERROR(B62/B25,"") -> 0.00083150985 | H62: =IFERROR(AVERAGE(G62,P62,Q62,R62,S62),"") -> 0.00083932233 | I62: Avg % of total revenue | J62: H62*K25 | K62: =ROUND(H62*K25,0) -> 42 | L62: =ROUND(H62*L25,0) -> 45 | M62: =ROUND(H62*M25,0) -> 47 | N62: =ROUND(H62*N25,0) -> 50 | O62: =ROUND(H62*O25,0) -> 52 | P62: =IFERROR(C62/C25,"") -> 0.00088257259 | Q62: =IFERROR(D62/D25,"") -> 0.00032146958 | R62: =IFERROR(E62/E25,"") -> 0.00057006352 | S62: =IFERROR(F62/F25,"") -> 0.0015909961
A63: Impairment - Fixed Assets | B63: 34 | C63: 21 | D63: 10 | E63: 21 | F63: 42 | G63: =IFERROR(B63/B25,"") -> 0.00074398249 | H63: =IFERROR(AVERAGE(G63,P63,Q63,R63,S63),"") -> 0.000651268 | I63: Avg % of total revenue | J63: H63*K25 | K63: =ROUND(H63*K25,0) -> 33 | L63: =ROUND(H63*L25,0) -> 35 | M63: =ROUND(H63*M25,0) -> 37 | N63: =ROUND(H63*N25,0) -> 39 | O63: =ROUND(H63*O25,0) -> 41 | P63: =IFERROR(C63/C25,"") -> 0.00047523139 | Q63: =IFERROR(D63/D25,"") -> 0.00022962113 | R63: =IFERROR(E63/E25,"") -> 0.00057006352 | S63: =IFERROR(F63/F25,"") -> 0.0012374414
A64: Impairment - Goodwill | B64: 4 | C64: 18 | D64: 4 | E64: 0 | F64: 0 | G64: =IFERROR(B64/B25,"") -> 8.7527352e-05 | H64: =IFERROR(AVERAGE(G64,P64,Q64,R64,S64),"") -> 0.0001173434 | I64: Avg % of total revenue | J64: H64*K25 | K64: =ROUND(H64*K25,0) -> 6 | L64: =ROUND(H64*L25,0) -> 6 | M64: =ROUND(H64*M25,0) -> 7 | N64: =ROUND(H64*N25,0) -> 7 | O64: =ROUND(H64*O25,0) -> 7 | P64: =IFERROR(C64/C25,"") -> 0.00040734119 | Q64: =IFERROR(D64/D25,"") -> 9.184845e-05 | R64: =IFERROR(E64/E25,"") -> 0 | S64: =IFERROR(F64/F25,"") -> 0
A65: Impairment - Intangibles excluding Goodwill | F65: 12 | G65: =IFERROR(B65/B25,"") -> 0 | H65: =IFERROR(AVERAGE(G65,P65,Q65,R65,S65),"") -> 7.071094e-05 | I65: Zero balance in FY2025 – not forecast | J65: n/a – not forecast | P65: =IFERROR(C65/C25,"") -> 0 | Q65: =IFERROR(D65/D25,"") -> 0 | R65: =IFERROR(E65/E25,"") -> 0 | S65: =IFERROR(F65/F25,"") -> 0.0003535547
A66: Impairment - Financial Investments | B66: 2 | G66: =IFERROR(B66/B25,"") -> 4.3763676e-05 | H66: =IFERROR(AVERAGE(G66,P66,Q66,R66,S66),"") -> 8.7527352e-06 | I66: Avg % of total revenue | J66: H66*K25 | K66: =ROUND(H66*K25,0) -> 0 | L66: =ROUND(H66*L25,0) -> 0 | M66: =ROUND(H66*M25,0) -> 0 | N66: =ROUND(H66*N25,0) -> 1 | O66: =ROUND(H66*O25,0) -> 1 | P66: =IFERROR(C66/C25,"") -> 0 | Q66: =IFERROR(D66/D25,"") -> 0 | R66: =IFERROR(E66/E25,"") -> 0 | S66: =IFERROR(F66/F25,"") -> 0
A67: Restructuring Charges | F67: 59 | G67: =IFERROR(B67/B25,"") -> 0 | H67: =IFERROR(AVERAGE(G67,P67,Q67,R67,S67),"") -> 0.00034766212 | I67: Zero balance in FY2025 – not forecast | J67: n/a – not forecast | P67: =IFERROR(C67/C25,"") -> 0 | Q67: =IFERROR(D67/D25,"") -> 0 | R67: =IFERROR(E67/E25,"") -> 0 | S67: =IFERROR(F67/F25,"") -> 0.0017383106
A68: Sale & Acquisition of Group Companies - Gain/(Loss) | B68: 237 | F68: 0 | G68: =IFERROR(B68/B25,"") -> 0.0051859956 | H68: =IFERROR(AVERAGE(G68,P68,Q68,R68,S68),"") -> 0.0010371991 | I68: Avg % of total revenue | J68: H68*K25 | K68: =ROUND(H68*K25,0) -> 52 | L68: =ROUND(H68*L25,0) -> 55 | M68: =ROUND(H68*M25,0) -> 58 | N68: =ROUND(H68*N25,0) -> 62 | O68: =ROUND(H68*O25,0) -> 65 | P68: =IFERROR(C68/C25,"") -> 0 | Q68: =IFERROR(D68/D25,"") -> 0 | R68: =IFERROR(E68/E25,"") -> 0 | S68: =IFERROR(F68/F25,"") -> 0
A69: Pre-Tax Income
A70: Income before Taxes | B70: 4053 | C70: 3587 | D70: 3509 | E70: 3320 | F70: 3373 | G70: =IFERROR(B70/B25,"") -> 0.08868709 | H70: =IFERROR(AVERAGE(G70,P70,Q70,R70,S70),"") -> 0.08798757 | I70: Normalised PBT + Non-Recurring | J70: K59+K61 | K70: =K59+K61 -> 4362 | L70: =L59+L61 -> 4737 | M70: =M59+M61 -> 5036 | N70: =N59+N61 -> 5331 | O70: =O59+O61 -> 5629 | P70: =IFERROR(C70/C25,"") -> 0.081174048 | Q70: =IFERROR(D70/D25,"") -> 0.080574053 | R70: =IFERROR(E70/E25,"") -> 0.090124328 | S70: =IFERROR(F70/F25,"") -> 0.099378333
A71: Taxes
A72: Income Taxes | B72: =B73+B76 -> 1127 | C72: =C73+C76 -> 1030 | D72: =D73+D76 -> 1044 | E72: =E73+E76 -> 968 | F72: =F73+F76 -> 993 | G72: =IFERROR(B72/B25,"") -> 0.024660832 | H72: =IFERROR(AVERAGE(G72,P72,Q72,R72,S72),"") -> 0.025495222 | I72: Avg effective tax rate × Income before Taxes | J72: 0.28974×Income_before_Taxes (row 70) | K72: =ROUND(0.28974*K70,0) -> 1264 | L72: =ROUND(0.28974*L70,0) -> 1372 | M72: =ROUND(0.28974*M70,0) -> 1459 | N72: =ROUND(0.28974*N70,0) -> 1545 | O72: =ROUND(0.28974*O70,0) -> 1631 | P72: =IFERROR(C72/C25,"") -> 0.023308968 | Q72: =IFERROR(D72/D25,"") -> 0.023972445 | R72: =IFERROR(E72/E25,"") -> 0.026277214 | S72: =IFERROR(F72/F25,"") -> 0.029256651
A73: Income Taxes for the Year - Current | B73: 1094 | C73: 1021 | D73: 991 | E73: 886 | F73: 975 | G73: =IFERROR(B73/B25,"") -> 0.023938731 | H73: =IFERROR(AVERAGE(G73,P73,Q73,R73,S73),"") -> 0.024515411 | I73: row 72 (same item, different classification) | J73: K72 | K73: =K72 -> 1264 | L73: =L72 -> 1372 | M73: =M72 -> 1459 | N73: =N72 -> 1545 | O73: =O72 -> 1631 | P73: =IFERROR(C73/C25,"") -> 0.023105298 | Q73: =IFERROR(D73/D25,"") -> 0.022755454 | R73: =IFERROR(E73/E25,"") -> 0.024051251 | S73: =IFERROR(F73/F25,"") -> 0.028726319
A74: Income Taxes - Domestic - Current | B74: 1110 | C74: 1060 | D74: 994 | E74: 857 | F74: 996 | G74: =IFERROR(B74/B25,"") -> 0.02428884 | H74: =IFERROR(AVERAGE(G74,P74,Q74,R74,S74),"") -> 0.024742022 | I74: Avg % of total revenue | J74: H74*K25 | K74: =ROUND(H74*K25,0) -> 1240 | L74: =ROUND(H74*L25,0) -> 1316 | M74: =ROUND(H74*M25,0) -> 1392 | N74: =ROUND(H74*N25,0) -> 1469 | O74: =ROUND(H74*O25,0) -> 1545 | P74: =IFERROR(C74/C25,"") -> 0.02398787 | Q74: =IFERROR(D74/D25,"") -> 0.02282434 | R74: =IFERROR(E74/E25,"") -> 0.023264021 | S74: =IFERROR(F74/F25,"") -> 0.02934504
A75: Income Taxes - Other (KFAS/NLST) - Current | B75: -16 | C75: -39 | D75: -3 | E75: 29 | F75: -21 | G75: =IFERROR(B75/B25,"") -> -0.00035010941 | H75: =IFERROR(AVERAGE(G75,P75,Q75,R75,S75),"") -> -0.0002266117 | I75: Avg % of total revenue | J75: H75*K25 | K75: =ROUND(H75*K25,0) -> -11 | L75: =ROUND(H75*L25,0) -> -12 | M75: =ROUND(H75*M25,0) -> -13 | N75: =ROUND(H75*N25,0) -> -13 | O75: =ROUND(H75*O25,0) -> -14 | P75: =IFERROR(C75/C25,"") -> -0.00088257259 | Q75: =IFERROR(D75/D25,"") -> -6.8886338e-05 | R75: =IFERROR(E75/E25,"") -> 0.00078723058 | S75: =IFERROR(F75/F25,"") -> -0.00061872072
A76: Income Taxes - Deferred | B76: 33 | C76: 9 | D76: 53 | E76: 82 | F76: 18 | G76: =IFERROR(B76/B25,"") -> 0.00072210066 | H76: =IFERROR(AVERAGE(G76,P76,Q76,R76,S76),"") -> 0.00097981152 | I76: Avg % of total revenue | J76: H76*K25 | K76: =ROUND(H76*K25,0) -> 49 | L76: =ROUND(H76*L25,0) -> 52 | M76: =ROUND(H76*M25,0) -> 55 | N76: =ROUND(H76*N25,0) -> 58 | O76: =ROUND(H76*O25,0) -> 61 | P76: =IFERROR(C76/C25,"") -> 0.0002036706 | Q76: =IFERROR(D76/D25,"") -> 0.001216992 | R76: =IFERROR(E76/E25,"") -> 0.0022259623 | S76: =IFERROR(F76/F25,"") -> 0.00053033205
A77: Income Taxes - Other - Deferred | B77: 33 | C77: 9 | D77: 53 | E77: 82 | F77: 18 | G77: =IFERROR(B77/B25,"") -> 0.00072210066 | H77: =IFERROR(AVERAGE(G77,P77,Q77,R77,S77),"") -> 0.00097981152 | I77: row 76 (same item, different classification) | J77: K76 | K77: =K76 -> 49 | L77: =L76 -> 52 | M77: =M76 -> 55 | N77: =N76 -> 58 | O77: =O76 -> 61 | P77: =IFERROR(C77/C25,"") -> 0.0002036706 | Q77: =IFERROR(D77/D25,"") -> 0.001216992 | R77: =IFERROR(E77/E25,"") -> 0.0022259623 | S77: =IFERROR(F77/F25,"") -> 0.00053033205
A78: Net Income After Tax
A79: Net Income after Tax | B79: 2926 | C79: 2557 | D79: 2465 | E79: 2352 | F79: 2380 | G79: =IFERROR(B79/B25,"") -> 0.064026258 | H79: =IFERROR(AVERAGE(G79,P79,Q79,R79,S79),"") -> 0.062492348 | I79: Income before Taxes – Income Taxes | J79: K70-K72 | K79: =K70-K72 -> 3098 | L79: =L70-L72 -> 3365 | M79: =M70-M72 -> 3577 | N79: =N70-N72 -> 3786 | O79: =O70-O72 -> 3998 | P79: =IFERROR(C79/C25,"") -> 0.05786508 | Q79: =IFERROR(D79/D25,"") -> 0.056601607 | R79: =IFERROR(E79/E25,"") -> 0.063847114 | S79: =IFERROR(F79/F25,"") -> 0.070121682
A80: After Tax Income/Expense
A81: Income before Discontinued Operations & Extraordinary Items | B81: 2926 | C81: 2557 | D81: 2465 | E81: 2352 | F81: 2380 | G81: =IFERROR(B81/B25,"") -> 0.064026258 | H81: =IFERROR(AVERAGE(G81,P81,Q81,R81,S81),"") -> 0.062492348 | I81: row 79 (same item, different classification) | J81: K79 | K81: =K79 -> 3098 | L81: =L79 -> 3365 | M81: =M79 -> 3577 | N81: =N79 -> 3786 | O81: =O79 -> 3998 | P81: =IFERROR(C81/C25,"") -> 0.05786508 | Q81: =IFERROR(D81/D25,"") -> 0.056601607 | R81: =IFERROR(E81/E25,"") -> 0.063847114 | S81: =IFERROR(F81/F25,"") -> 0.070121682
A82: Extraordinary Activities - after Tax - Gain/(Loss) | F82: 0 | G82: =IFERROR(B82/B25,"") -> 0 | H82: =IFERROR(AVERAGE(G82,P82,Q82,R82,S82),"") -> 0 | I82: Zero balance in FY2025 – not forecast | J82: n/a – not forecast | P82: =IFERROR(C82/C25,"") -> 0 | Q82: =IFERROR(D82/D25,"") -> 0 | R82: =IFERROR(E82/E25,"") -> 0 | S82: =IFERROR(F82/F25,"") -> 0
A83: Discontinued Operations - Net of Taxes - Total - Income/(Expense) | F83: 0 | G83: =IFERROR(B83/B25,"") -> 0 | H83: =IFERROR(AVERAGE(G83,P83,Q83,R83,S83),"") -> 0 | I83: Zero balance in FY2025 – not forecast | J83: n/a – not forecast | P83: =IFERROR(C83/C25,"") -> 0 | Q83: =IFERROR(D83/D25,"") -> 0 | R83: =IFERROR(E83/E25,"") -> 0 | S83: =IFERROR(F83/F25,"") -> 0
A84: Net Income before Minority Interest | B84: =B81+B82+B83 -> 2926 | C84: =C81+C82+C83 -> 2557 | D84: =D81+D82+D83 -> 2465 | E84: =E81+E82+E83 -> 2352 | F84: =F81+F82+F83 -> 2380 | G84: =IFERROR(B84/B25,"") -> 0.064026258 | H84: =IFERROR(AVERAGE(G84,P84,Q84,R84,S84),"") -> 0.062492348 | I84: Income before Disc Ops + Extraordinary + Disc Ops | J84: K81+K82+K83 | K84: =K81+K82+K83 -> 3098 | L84: =L81+L82+L83 -> 3365 | M84: =M81+M82+M83 -> 3577 | N84: =N81+N82+N83 -> 3786 | O84: =O81+O82+O83 -> 3998 | P84: =IFERROR(C84/C25,"") -> 0.05786508 | Q84: =IFERROR(D84/D25,"") -> 0.056601607 | R84: =IFERROR(E84/E25,"") -> 0.063847114 | S84: =IFERROR(F84/F25,"") -> 0.070121682
A85: Net Income after Minority Interest | B85: 2926 | C85: 2557 | D85: 2465 | E85: 2352 | F85: 2380 | G85: =IFERROR(B85/B25,"") -> 0.064026258 | H85: =IFERROR(AVERAGE(G85,P85,Q85,R85,S85),"") -> 0.062492348 | I85: row 84 (same item, different classification) | J85: K84 | K85: =K84 -> 3098 | L85: =L84 -> 3365 | M85: =M84 -> 3577 | N85: =N84 -> 3786 | O85: =O84 -> 3998 | P85: =IFERROR(C85/C25,"") -> 0.05786508 | Q85: =IFERROR(D85/D25,"") -> 0.056601607 | R85: =IFERROR(E85/E25,"") -> 0.063847114 | S85: =IFERROR(F85/F25,"") -> 0.070121682
A86: Net Income
A87: Income Available to Common Shares | B87: 2926 | C87: 2557 | D87: 2465 | E87: 2352 | F87: 2380 | G87: =IFERROR(B87/B25,"") -> 0.064026258 | H87: =IFERROR(AVERAGE(G87,P87,Q87,R87,S87),"") -> 0.062492348 | I87: row 79 (same item, different classification) | J87: K79 | K87: =K79 -> 3098 | L87: =L79 -> 3365 | M87: =M79 -> 3577 | N87: =N79 -> 3786 | O87: =O79 -> 3998 | P87: =IFERROR(C87/C25,"") -> 0.05786508 | Q87: =IFERROR(D87/D25,"") -> 0.056601607 | R87: =IFERROR(E87/E25,"") -> 0.063847114 | S87: =IFERROR(F87/F25,"") -> 0.070121682
A88: Other Comprehensive Income
A89: Other Comprehensive Income - Starting Line | B89: 2926 | C89: 2557 | D89: 2465 | E89: 2352 | F89: 2380 | G89: =IFERROR(B89/B25,"") -> 0.064026258 | H89: =IFERROR(AVERAGE(G89,P89,Q89,R89,S89),"") -> 0.062492348 | I89: row 79 (same item, different classification) | J89: K79 | K89: =K79 -> 3098 | L89: =L79 -> 3365 | M89: =M79 -> 3577 | N89: =N79 -> 3786 | O89: =O79 -> 3998 | P89: =IFERROR(C89/C25,"") -> 0.05786508 | Q89: =IFERROR(D89/D25,"") -> 0.056601607 | R89: =IFERROR(E89/E25,"") -> 0.063847114 | S89: =IFERROR(F89/F25,"") -> 0.070121682
A90: Other Comprehensive Income - Foreign Currency | B90: 6 | C90: -4 | D90: 5 | E90: -11 | F90: -8 | G90: =IFERROR(B90/B25,"") -> 0.00013129103 | H90: =IFERROR(AVERAGE(G90,P90,Q90,R90,S90),"") -> -7.5745302e-05 | I90: Avg % of total revenue | J90: H90*K25 | K90: =ROUND(H90*K25,0) -> -4 | L90: =ROUND(H90*L25,0) -> -4 | M90: =ROUND(H90*M25,0) -> -4 | N90: =ROUND(H90*N25,0) -> -4 | O90: =ROUND(H90*O25,0) -> -5 | P90: =IFERROR(C90/C25,"") -> -9.0520265e-05 | Q90: =IFERROR(D90/D25,"") -> 0.00011481056 | R90: =IFERROR(E90/E25,"") -> -0.0002986047 | S90: =IFERROR(F90/F25,"") -> -0.00023570313
A91: Other Comprehensive Income - Unrealized Investment Gain/(Loss) | C91: 0 | D91: 24 | E91: 43 | F91: -3 | G91: =IFERROR(B91/B25,"") -> 0 | H91: =IFERROR(AVERAGE(G91,P91,Q91,R91,S91),"") -> 0.00032599499 | I91: Zero balance in FY2025 – not forecast | J91: n/a – not forecast | P91: =IFERROR(C91/C25,"") -> 0 | Q91: =IFERROR(D91/D25,"") -> 0.0005510907 | R91: =IFERROR(E91/E25,"") -> 0.0011672729 | S91: =IFERROR(F91/F25,"") -> -8.8388674e-05
A92: Other Comprehensive Income - Hedging Gain/(Loss) | B92: 77 | C92: 77 | D92: -99 | E92: 111 | F92: 117 | G92: =IFERROR(B92/B25,"") -> 0.0016849015 | H92: =IFERROR(AVERAGE(G92,P92,Q92,R92,S92),"") -> 0.0015229037 | I92: Avg % of total revenue | J92: H92*K25 | K92: =ROUND(H92*K25,0) -> 76 | L92: =ROUND(H92*L25,0) -> 81 | M92: =ROUND(H92*M25,0) -> 86 | N92: =ROUND(H92*N25,0) -> 90 | O92: =ROUND(H92*O25,0) -> 95 | P92: =IFERROR(C92/C25,"") -> 0.0017425151 | Q92: =IFERROR(D92/D25,"") -> -0.0022732491 | R92: =IFERROR(E92/E25,"") -> 0.0030131929 | S92: =IFERROR(F92/F25,"") -> 0.0034471583
A93: Other Comprehensive Income - Other | E93: 0 | F93: 0 | G93: =IFERROR(B93/B25,"") -> 0 | H93: =IFERROR(AVERAGE(G93,P93,Q93,R93,S93),"") -> 0 | I93: Zero balance in FY2025 – not forecast | J93: n/a – not forecast | P93: =IFERROR(C93/C25,"") -> 0 | Q93: =IFERROR(D93/D25,"") -> 0 | R93: =IFERROR(E93/E25,"") -> 0 | S93: =IFERROR(F93/F25,"") -> 0
A94: Other Comprehensive Income - Discontinued Operations | F94: 0 | G94: =IFERROR(B94/B25,"") -> 0 | H94: =IFERROR(AVERAGE(G94,P94,Q94,R94,S94),"") -> 0 | I94: Zero balance in FY2025 – not forecast | J94: n/a – not forecast | P94: =IFERROR(C94/C25,"") -> 0 | Q94: =IFERROR(D94/D25,"") -> 0 | R94: =IFERROR(E94/E25,"") -> 0 | S94: =IFERROR(F94/F25,"") -> 0
A95: Other Comprehensive Income - Associated Companies | B95: 0 | C95: -2 | D95: 8 | E95: 5 | F95: 5 | G95: =IFERROR(B95/B25,"") -> 0 | H95: =IFERROR(AVERAGE(G95,P95,Q95,R95,S95),"") -> 8.4296127e-05 | I95: Zero balance in FY2025 – not forecast (zero in 2025) | J95: n/a – not forecast | P95: =IFERROR(C95/C25,"") -> -4.5260133e-05 | Q95: =IFERROR(D95/D25,"") -> 0.0001836969 | R95: =IFERROR(E95/E25,"") -> 0.00013572941 | S95: =IFERROR(F95/F25,"") -> 0.00014731446
A96: Other Comprehensive Income - Pension Related | E96: 0 | F96: 0 | G96: =IFERROR(B96/B25,"") -> 0 | H96: =IFERROR(AVERAGE(G96,P96,Q96,R96,S96),"") -> 0 | I96: Zero balance in FY2025 – not forecast | J96: n/a – not forecast | P96: =IFERROR(C96/C25,"") -> 0 | Q96: =IFERROR(D96/D25,"") -> 0 | R96: =IFERROR(E96/E25,"") -> 0 | S96: =IFERROR(F96/F25,"") -> 0
A97: Other Comprehensive Income - Income Tax | B97: -23 | C97: -23 | D97: 22 | E97: -53 | F97: -37 | G97: =IFERROR(B97/B25,"") -> -0.00050328228 | H97: =IFERROR(AVERAGE(G97,P97,Q97,R97,S97),"") -> -0.00060949321 | I97: Avg % of total revenue | J97: H97*K25 | K97: =ROUND(H97*K25,0) -> -31 | L97: =ROUND(H97*L25,0) -> -32 | M97: =ROUND(H97*M25,0) -> -34 | N97: =ROUND(H97*N25,0) -> -36 | O97: =ROUND(H97*O25,0) -> -38 | P97: =IFERROR(C97/C25,"") -> -0.00052049153 | Q97: =IFERROR(D97/D25,"") -> 0.00050516648 | R97: =IFERROR(E97/E25,"") -> -0.0014387317 | S97: =IFERROR(F97/F25,"") -> -0.001090127
A98: Other Comprehensive Income - Net of Tax - Total | B98: =SUM(B90:B97) -> 60 | C98: =SUM(C90:C97) -> 48 | D98: =SUM(D90:D97) -> -40 | E98: =SUM(E90:E97) -> 95 | F98: =SUM(F90:F97) -> 74 | G98: =IFERROR(B98/B25,"") -> 0.0013129103 | H98: =IFERROR(AVERAGE(G98,P98,Q98,R98,S98),"") -> 0.0012479563 | I98: Sum OCI components (rows 90-97) | J98: SUM(K90:K97) | K98: =SUM(K90:K97) -> 41 | L98: =SUM(L90:L97) -> 45 | M98: =SUM(M90:M97) -> 48 | N98: =SUM(N90:N97) -> 50 | O98: =SUM(O90:O97) -> 52 | P98: =IFERROR(C98/C25,"") -> 0.0010862432 | Q98: =IFERROR(D98/D25,"") -> -0.0009184845 | R98: =IFERROR(E98/E25,"") -> 0.0025788588 | S98: =IFERROR(F98/F25,"") -> 0.002180254
A99: Comprehensive Income before Minority Interest - Total | B99: =B87+B98 -> 2986 | C99: =C87+C98 -> 2605 | D99: =D87+D98 -> 2425 | E99: =E87+E98 -> 2447 | F99: =F87+F98 -> 2454 | G99: =IFERROR(B99/B25,"") -> 0.065339168 | H99: =IFERROR(AVERAGE(G99,P99,Q99,R99,S99),"") -> 0.063740305 | I99: Net Income + OCI Net of Tax | J99: K87+K98 | K99: =K87+K98 -> 3139 | L99: =L87+L98 -> 3410 | M99: =M87+M98 -> 3625 | N99: =N87+N98 -> 3836 | O99: =O87+O98 -> 4050 | P99: =IFERROR(C99/C25,"") -> 0.058951323 | Q99: =IFERROR(D99/D25,"") -> 0.055683123 | R99: =IFERROR(E99/E25,"") -> 0.066425973 | S99: =IFERROR(F99/F25,"") -> 0.072301936
A100: Comprehensive Income - Attributable to Parent Company Equity Holders - Total | B100: =B99 -> 2986 | C100: =C99 -> 2605 | D100: =D99 -> 2425 | E100: =E99 -> 2447 | F100: =F99 -> 2454 | G100: =IFERROR(B100/B25,"") -> 0.065339168 | H100: =IFERROR(AVERAGE(G100,P100,Q100,R100,S100),"") -> 0.063740305 | I100: row 99 (same item, different classification) | J100: K99 | K100: =K99 -> 3139 | L100: =L99 -> 3410 | M100: =M99 -> 3625 | N100: =N99 -> 3836 | O100: =O99 -> 4050 | P100: =IFERROR(C100/C25,"") -> 0.058951323 | Q100: =IFERROR(D100/D25,"") -> 0.055683123 | R100: =IFERROR(E100/E25,"") -> 0.066425973 | S100: =IFERROR(F100/F25,"") -> 0.072301936
A101: Dividends | B101: 2291 | C101: 2202 | D101: 2139 | E101: 1927 | G101: =IFERROR(B101/B25,"") -> 0.050131291 | H101: =IFERROR(AVERAGE(G101,P101,Q101,R101,S101),"") -> 0.050347193 | I101: Avg payout ratio × Net Income (row 79); capped 0-100% | J101: 0.8816×Net_Income_row79 | K101: =ROUND(0.8816*K79,0) -> 2731 | L101: =ROUND(0.8816*L79,0) -> 2967 | M101: =ROUND(0.8816*M79,0) -> 3153 | N101: =ROUND(0.8816*N79,0) -> 3338 | O101: =ROUND(0.8816*O79,0) -> 3525 | P101: =IFERROR(C101/C25,"") -> 0.049831406 | Q101: =IFERROR(D101/D25,"") -> 0.049115959 | R101: =IFERROR(E101/E25,"") -> 0.052310115

Sheet FCFE
A1: Free Cash Flow to Equity (FCFE) — Wesfarmers Ltd (WES.AX)
A2: AUD $m | FY2026–FY2030 | All components formula-linked to pro-forma IS and BS
A4: SECTION 1 — FORMULA DEFINITION
A5: FCFE = E + NCC − ΔWCAP − FCInv + Net Borrowing + Δ Other NCL
A6: E = Net Income | IS row 79
A7: NCC = Depreciation (IS r30) + Amortisation (IS r29) — non-cash charges
A8: ΔWCAP = Change in Net Working Capital: (TCA−Cash) − (TCL−STDebt) | BS rows 35,20,113,104
A9: FCInv = Net Capex = PPE_t − PPE_{t−1} + Dep_t | BS row 41 + IS row 30
A10: Net Borrowing = Δ(LT Debt excl. leases + ST Debt) | BS rows 116, 104
A11: Δ Other NCL = Change in other non-current liabilities | BS row 120
A13: SECTION 2 — FCFE CALCULATION (FY2026–FY2030)
A14: Component | B14: 2026 | C14: 2027 | D14: 2028 | E14: 2029 | F14: 2030 | H14: Formula / Source Reference
A16: E — Net Income | B16: ='Income Statement'!K79 -> 3098 | C16: ='Income Statement'!L79 -> 3365 | D16: ='Income Statement'!M79 -> 3577 | E16: ='Income Statement'!N79 -> 3786 | F16: ='Income Statement'!O79 -> 3998 | H16: IS row 79: Net Income after Tax
A17: NCC — Depreciation | B17: ='Income Statement'!K30 -> 1604 | C17: ='Income Statement'!L30 -> 1671 | D17: ='Income Statement'!M30 -> 1747 | E17: ='Income Statement'!N30 -> 1830 | F17: ='Income Statement'!O30 -> 1919 | H17: IS row 30: Depreciation in Cost of Revenues
A18: NCC — Amortisation | B18: ='Income Statement'!K29 -> 186 | C18: ='Income Statement'!L29 -> 197 | D18: ='Income Statement'!M29 -> 209 | E18: ='Income Statement'!N29 -> 220 | F18: ='Income Statement'!O29 -> 232 | H18: IS row 29: Amortisation in Cost of Revenues
A19: NCC Total (Dep + Amort) | B19: =B17+B18 -> 1790 | C19: =C17+C18 -> 1868 | D19: =D17+D18 -> 1956 | E19: =E17+E18 -> 2050 | F19: =F17+F18 -> 2151 | H19: Sum of IS rows 30 and 29
A20: Less: ΔWCAP — Change in Net Working Capital | B20: =('Balance Sheet'!T35-'Balance Sheet'!T20-'Balance Sheet'!T113+'Balance Sheet'!T104)-('Balance Sheet'!G35-'Balance Sheet'!G20-'Balance Sheet'!G113+'Balance Sheet'!G104) -> -316 | C20: =('Balance Sheet'!U35-'Balance Sheet'!U20-'Balance Sheet'!U113+'Balance Sheet'!U104)-('Balance Sheet'!T35-'Balance Sheet'!T20-'Balance Sheet'!T113+'Balance Sheet'!T104) -> 110 | D20: =('Balance Sheet'!V35-'Balance Sheet'!V20-'Balance Sheet'!V113+'Balance Sheet'!V104)-('Balance Sheet'!U35-'Balance Sheet'!U20-'Balance Sheet'!U113+'Balance Sheet'!U104) -> 111 | E20: =('Balance Sheet'!W35-'Balance Sheet'!W20-'Balance Sheet'!W113+'Balance Sheet'!W104)-('Balance Sheet'!V35-'Balance Sheet'!V20-'Balance Sheet'!V113+'Balance Sheet'!V104) -> 111 | F20: =('Balance Sheet'!X35-'Balance Sheet'!X20-'Balance Sheet'!X113+'Balance Sheet'!X104)-('Balance Sheet'!W35-'Balance Sheet'!W20-'Balance Sheet'!W113+'Balance Sheet'!W104) -> 110 | H20: (TCA−Cash−TCL+STD)_t − prior year | BS rows 35,20,113,104
A21: NWC_t (supporting) | B21: ='Balance Sheet'!T35-'Balance Sheet'!T20-'Balance Sheet'!T113+'Balance Sheet'!T104 -> 1800 | C21: ='Balance Sheet'!U35-'Balance Sheet'!U20-'Balance Sheet'!U113+'Balance Sheet'!U104 -> 1910 | D21: ='Balance Sheet'!V35-'Balance Sheet'!V20-'Balance Sheet'!V113+'Balance Sheet'!V104 -> 2021 | E21: ='Balance Sheet'!W35-'Balance Sheet'!W20-'Balance Sheet'!W113+'Balance Sheet'!W104 -> 2132 | F21: ='Balance Sheet'!X35-'Balance Sheet'!X20-'Balance Sheet'!X113+'Balance Sheet'!X104 -> 2242 | H21: Net Working Capital each year (excl. cash and ST debt)
A22: Less: FCInv — Net Capital Expenditure | B22: ='Balance Sheet'!T41-'Balance Sheet'!G41+'Income Statement'!K30 -> 2064 | C22: ='Balance Sheet'!U41-'Balance Sheet'!T41+'Income Statement'!L30 -> 2191 | D22: ='Balance Sheet'!V41-'Balance Sheet'!U41+'Income Statement'!M30 -> 2319 | E22: ='Balance Sheet'!W41-'Balance Sheet'!V41+'Income Statement'!N30 -> 2446 | F22: ='Balance Sheet'!X41-'Balance Sheet'!W41+'Income Statement'!O30 -> 2573 | H22: PPE_t (BS r41) − PPE_{t-1} + Dep_t (IS r30) = Gross Capex
A23: Add: Net Borrowing — Δ(LT Debt + ST Debt) | B23: =('Balance Sheet'!T116+'Balance Sheet'!T104)-('Balance Sheet'!G116+'Balance Sheet'!G104) -> -25 | C23: =('Balance Sheet'!U116+'Balance Sheet'!U104)-('Balance Sheet'!T116+'Balance Sheet'!T104) -> 118 | D23: =('Balance Sheet'!V116+'Balance Sheet'!V104)-('Balance Sheet'!U116+'Balance Sheet'!U104) -> 117 | E23: =('Balance Sheet'!W116+'Balance Sheet'!W104)-('Balance Sheet'!V116+'Balance Sheet'!V104) -> 118 | F23: =('Balance Sheet'!X116+'Balance Sheet'!X104)-('Balance Sheet'!W116+'Balance Sheet'!W104) -> 118 | H23: (LTD+STD)_t − (LTD+STD)_{t-1} | BS rows 116, 104
A24: Add: Δ Other Non-Current Liabilities | B24: ='Balance Sheet'!T120-'Balance Sheet'!G120 -> 38 | C24: ='Balance Sheet'!U120-'Balance Sheet'!T120 -> 29 | D24: ='Balance Sheet'!V120-'Balance Sheet'!U120 -> 30 | E24: ='Balance Sheet'!W120-'Balance Sheet'!V120 -> 30 | F24: ='Balance Sheet'!X120-'Balance Sheet'!W120 -> 29 | H24: BS row 120: Other NCL Total vs prior year
A25: FCFE = E + NCC − ΔWCAP − FCInv + Net Borrowing + Δ Other NCL | B25: =B16+B19-B20-B22+B23+B24 -> 3153 | C25: =C16+C19-C20-C22+C23+C24 -> 3079 | D25: =D16+D19-D20-D22+D23+D24 -> 3250 | E25: =E16+E19-E20-E22+E23+E24 -> 3427 | F25: =F16+F19-F20-F22+F23+F24 -> 3613 | H25: e + ncc − ΔWCAP − FCInv + Net Borrowing + Δ Other NCL
A26: Duality of FCFE = Equity_{t-1} + Net Income − Equity_t | B26: ='Balance Sheet'!G142+'Income Statement'!K79-'Balance Sheet'!T142 -> 2731 | C26: ='Balance Sheet'!T142+'Income Statement'!L79-'Balance Sheet'!U142 -> 2967 | D26: ='Balance Sheet'!U142+'Income Statement'!M79-'Balance Sheet'!V142 -> 3153 | E26: ='Balance Sheet'!V142+'Income Statement'!N79-'Balance Sheet'!W142 -> 3338 | F26: ='Balance Sheet'!W142+'Income Statement'!O79-'Balance Sheet'!X142 -> 3525 | H26: BS Equity_{t-1} (r142) + NI (IS r79) − BS Equity_t | Model consistency check
A28: SECTION 3 — NOTES
A29: 1. All components are formula-linked to the pro-forma IS and BS — no values are hardcoded.
A30: 2. ΔWCAP excludes Cash (plug, BS row 20) and ST Debt (financing item, row 104) to isolate operating working capital.
A31: 3. FCInv = PPE_t − PPE_{t-1} + Dep_t. This equals gross capital expenditure (new investment before depreciation offset).
A32: 4. Net Borrowing uses interest-bearing debt only (LT excl. cap. leases r116 + ST debt r104). Cap. lease obligations excluded (non-cash AASB 16 entries).
A33: 5. Duality check: Equity_{t-1} + NI − Equity_t. Small residuals reflect OCI reserve movements (non-cash items bypassing P&L). This verifies RE accumulation is correct.
A34: 6. FCFE is positive in all forecast years, consistent with Wesfarmers strong earnings generation relative to reinvestment needs.

Sheet Balance Sheet
A1: Company Fundamentals - Balance Sheet
A2: Company Name | B2: Wesfarmers Ltd (WES.AX)
A3: Country of Exchange | B3: Australia
A4: Country of Headquarters | B4: Australia
A5: TRBC Industry Group | B5: Diversified Retail
A6: CF Template | B6: IND
A7: Consolidation Basis | B7: Consolidated
A8: Scaling | B8: Millions
A9: Period | B9: Annual
A10: Export Date | B10: 46164.123
A11: Statement Data | B11: 2025 | C11: 2024 | D11: 2023 | E11: 2022 | F11: 2021
A12: Period End Date | B12: 45838 | C12: 45473 | D12: 45107 | E12: 44742 | F12: 44377
A13: Statement Date | B13: 45838 | C13: 45473 | D13: 45107 | E13: 45107 | F13: 44377
A14: Standardized Currency | B14: AUD | C14: AUD | D14: AUD | E14: AUD | F14: AUD
A15: Template Type | B15: Industrial - Differentiated | C15: Industrial - Differentiated | D15: Industrial - Differentiated | E15: Industrial - Differentiated | F15: Industrial - Differentiated
A17: Balance Sheet - Standardized (Currency: Standardized)
A18: Field Name | B18: 30-06-2025 | C18: 30-06-2024 | D18: 30-06-2023 | E18: 30-06-2022 | F18: 30-06-2021 | G18: ADJ 30-06-2025 | H18: ADJ 30-06-2024 | I18: ADJ 30-06-2023 | J18: ADJ 30-06-2022 | K18: ADJ 30-06-2021 | L18: % Rev 2025adj | M18: % Rev 2024adj | N18: % Rev 2023adj | O18: % Rev 2022adj | P18: % Rev 2021adj | Q18: Avg % Rev | R18: Formula Description | S18: Excel Formula | T18: F2026 | U18: F2027 | V18: F2028 | W18: F2029 | X18: F2030
A19: Current Assets
A20: Cash & Short-Term Investments | B20: 638 | C20: 835 | D20: 673 | E20: 705 | F20: 3023 | G20: =B20 -> 638 | H20: =C20 -> 835 | I20: =D20 -> 673 | J20: =E20 -> 705 | K20: =F20 -> 3023 | L20: =IFERROR(G20/'Income Statement'!B25,"") -> 0.013960613 | M20: =IFERROR(H20/'Income Statement'!C25,"") -> 0.018896105 | N20: =IFERROR(I20/'Income Statement'!D25,"") -> 0.015453502 | O20: =IFERROR(J20/'Income Statement'!E25,"") -> 0.019137847 | P20: =IFERROR(K20/'Income Statement'!F25,"") -> 0.089066321 | Q20: =IFERROR(AVERAGE(L20:P20),"") -> 0.031302878 | R20: PLUG: Total L&E – Total NCA – Non-cash CA | S20: Total L&E - Total NCA - (Deriv+Rec+Inv+OtherCA) | T20: =ROUND(T146-T97-T22-T23-T29-T33,0) -> 2602 | U20: =ROUND(U146-U97-U22-U23-U29-U33,0) -> 2774 | V20: =ROUND(V146-V97-V22-V23-V29-V33,0) -> 2917 | W20: =ROUND(W146-W97-W22-W23-W29-W33,0) -> 3042 | X20: =ROUND(X146-X97-X22-X23-X29-X33,0) -> 3151
A21: Cash & Cash Equivalents | B21: 638 | C21: 835 | D21: 673 | E21: 705 | F21: 3023 | G21: =B21 -> 638 | H21: =C21 -> 835 | I21: =D21 -> 673 | J21: =E21 -> 705 | K21: =F21 -> 3023 | L21: =IFERROR(G21/'Income Statement'!B25,"") -> 0.013960613 | M21: =IFERROR(H21/'Income Statement'!C25,"") -> 0.018896105 | N21: =IFERROR(I21/'Income Statement'!D25,"") -> 0.015453502 | O21: =IFERROR(J21/'Income Statement'!E25,"") -> 0.019137847 | P21: =IFERROR(K21/'Income Statement'!F25,"") -> 0.089066321 | Q21: =IFERROR(AVERAGE(L21:P21),"") -> 0.031302878 | R21: 20 | S21: T20 (Cash Equivalents = Cash) | T21: =T20 -> 2602 | U21: =U20 -> 2774 | V21: =V20 -> 2917 | W21: =W20 -> 3042 | X21: =X20 -> 3151
A22: Derivative Financial Instruments - Hedging - Short-Term | B22: 31 | C22: 19 | D22: 116 | E22: 452 | F22: 152 | G22: =B22 -> 31 | H22: =C22 -> 19 | I22: =D22 -> 116 | J22: =E22 -> 452 | K22: =F22 -> 152 | L22: =IFERROR(G22/'Income Statement'!B25,"") -> 0.00067833698 | M22: =IFERROR(H22/'Income Statement'!C25,"") -> 0.00042997126 | N22: =IFERROR(I22/'Income Statement'!D25,"") -> 0.0026636051 | O22: =IFERROR(J22/'Income Statement'!E25,"") -> 0.012269939 | P22: =IFERROR(K22/'Income Statement'!F25,"") -> 0.0044783595 | Q22: =IFERROR(AVERAGE(L22:P22),"") -> 0.0041040423 | R22: Avg % of adjusted revenue | S22: ROUND(Q22*IS_rev,0) | T22: =ROUND(Q22*'Income Statement'!K25,0) -> 206 | U22: =ROUND(Q22*'Income Statement'!L25,0) -> 218 | V22: =ROUND(Q22*'Income Statement'!M25,0) -> 231 | W22: =ROUND(Q22*'Income Statement'!N25,0) -> 244 | X22: =ROUND(Q22*'Income Statement'!O25,0) -> 256
A23: Loans & Receivables - Net - Short-Term | B23: 2988 | C23: 2210 | D23: 2089 | E23: 2094 | F23: 1247 | G23: =B23 -> 2988 | H23: =C23 -> 2210 | I23: =D23 -> 2089 | J23: =E23 -> 2094 | K23: =F23 -> 1247 | L23: =IFERROR(G23/'Income Statement'!B25,"") -> 0.065382932 | M23: =IFERROR(H23/'Income Statement'!C25,"") -> 0.050012447 | N23: =IFERROR(I23/'Income Statement'!D25,"") -> 0.047967853 | O23: =IFERROR(J23/'Income Statement'!E25,"") -> 0.056843477 | P23: =IFERROR(K23/'Income Statement'!F25,"") -> 0.036740226 | Q23: =IFERROR(AVERAGE(L23:P23),"") -> 0.051389387 | R23: Avg % of adjusted revenue | S23: ROUND(Q23*IS_rev,0) | T23: =ROUND(Q23*'Income Statement'!K25,0) -> 2575 | U23: =ROUND(Q23*'Income Statement'!L25,0) -> 2733 | V23: =ROUND(Q23*'Income Statement'!M25,0) -> 2892 | W23: =ROUND(Q23*'Income Statement'!N25,0) -> 3051 | X23: =ROUND(Q23*'Income Statement'!O25,0) -> 3209
A24: Trade Accounts & Trade Notes Receivable - Net | B24: 2001 | C24: 1995 | D24: 1829 | E24: 1883 | F24: 1037 | G24: =B24 -> 2001 | H24: =C24 -> 1995 | I24: =D24 -> 1829 | J24: =E24 -> 1883 | K24: =F24 -> 1037 | L24: =IFERROR(G24/'Income Statement'!B25,"") -> 0.043785558 | M24: =IFERROR(H24/'Income Statement'!C25,"") -> 0.045146982 | N24: =IFERROR(I24/'Income Statement'!D25,"") -> 0.041997704 | O24: =IFERROR(J24/'Income Statement'!E25,"") -> 0.051115696 | P24: =IFERROR(K24/'Income Statement'!F25,"") -> 0.030553018 | Q24: =IFERROR(AVERAGE(L24:P24),"") -> 0.042519792 | R24: Avg % of adjusted revenue | S24: ROUND(Q24*IS_rev,0) | T24: =ROUND(Q24*'Income Statement'!K25,0) -> 2130 | U24: =ROUND(Q24*'Income Statement'!L25,0) -> 2262 | V24: =ROUND(Q24*'Income Statement'!M25,0) -> 2393 | W24: =ROUND(Q24*'Income Statement'!N25,0) -> 2524 | X24: =ROUND(Q24*'Income Statement'!O25,0) -> 2655
A25: Trade Accounts & Trade Notes Receivable - Gross | B25: 2052 | C25: 2055 | D25: 1892 | E25: 1938 | F25: 1070 | G25: =B25 -> 2052 | H25: =C25 -> 2055 | I25: =D25 -> 1892 | J25: =E25 -> 1938 | K25: =F25 -> 1070 | L25: =IFERROR(G25/'Income Statement'!B25,"") -> 0.044901532 | M25: =IFERROR(H25/'Income Statement'!C25,"") -> 0.046504786 | N25: =IFERROR(I25/'Income Statement'!D25,"") -> 0.043444317 | O25: =IFERROR(J25/'Income Statement'!E25,"") -> 0.052608719 | P25: =IFERROR(K25/'Income Statement'!F25,"") -> 0.031525294 | Q25: =IFERROR(AVERAGE(L25:P25),"") -> 0.04379693 | R25: Avg % of adjusted revenue | S25: ROUND(Q25*IS_rev,0) | T25: =ROUND(Q25*'Income Statement'!K25,0) -> 2194 | U25: =ROUND(Q25*'Income Statement'!L25,0) -> 2330 | V25: =ROUND(Q25*'Income Statement'!M25,0) -> 2465 | W25: =ROUND(Q25*'Income Statement'!N25,0) -> 2600 | X25: =ROUND(Q25*'Income Statement'!O25,0) -> 2735
A26: Provision - Trade Accounts & Trade Notes Receivable | B26: 51 | C26: 60 | D26: 63 | E26: 55 | F26: 33 | G26: =B26 -> 51 | H26: =C26 -> 60 | I26: =D26 -> 63 | J26: =E26 -> 55 | K26: =F26 -> 33 | L26: =IFERROR(G26/'Income Statement'!B25,"") -> 0.0011159737 | M26: =IFERROR(H26/'Income Statement'!C25,"") -> 0.001357804 | N26: =IFERROR(I26/'Income Statement'!D25,"") -> 0.0014466131 | O26: =IFERROR(J26/'Income Statement'!E25,"") -> 0.0014930235 | P26: =IFERROR(K26/'Income Statement'!F25,"") -> 0.00097227542 | Q26: =IFERROR(AVERAGE(L26:P26),"") -> 0.0012771379 | R26: Avg % of adjusted revenue | S26: ROUND(Q26*IS_rev,0) | T26: =ROUND(Q26*'Income Statement'!K25,0) -> 64 | U26: =ROUND(Q26*'Income Statement'!L25,0) -> 68 | V26: =ROUND(Q26*'Income Statement'!M25,0) -> 72 | W26: =ROUND(Q26*'Income Statement'!N25,0) -> 76 | X26: =ROUND(Q26*'Income Statement'!O25,0) -> 80
A27: Income Tax - Receivables - Short-Term | C27: 0 | D27: 43 | H27: =C27 -> 0 | I27: =D27 -> 43 | L27: =IFERROR(G27/'Income Statement'!B25,"") -> 0 | M27: =IFERROR(H27/'Income Statement'!C25,"") -> 0 | N27: =IFERROR(I27/'Income Statement'!D25,"") -> 0.00098737084 | O27: =IFERROR(J27/'Income Statement'!E25,"") -> 0 | P27: =IFERROR(K27/'Income Statement'!F25,"") -> 0 | Q27: =IFERROR(AVERAGE(L27:P27),"") -> 0.00019747417 | R27: Zero/nil in FY2025 – not forecast
A28: Receivables - Other - Total | B28: 987 | C28: 215 | D28: 217 | E28: 211 | F28: 210 | G28: =B28 -> 987 | H28: =C28 -> 215 | I28: =D28 -> 217 | J28: =E28 -> 211 | K28: =F28 -> 210 | L28: =IFERROR(G28/'Income Statement'!B25,"") -> 0.021597374 | M28: =IFERROR(H28/'Income Statement'!C25,"") -> 0.0048654643 | N28: =IFERROR(I28/'Income Statement'!D25,"") -> 0.0049827784 | O28: =IFERROR(J28/'Income Statement'!E25,"") -> 0.0057277811 | P28: =IFERROR(K28/'Income Statement'!F25,"") -> 0.0061872072 | Q28: =IFERROR(AVERAGE(L28:P28),"") -> 0.008672121 | R28: Avg % of adjusted revenue | S28: ROUND(Q28*IS_rev,0) | T28: =ROUND(Q28*'Income Statement'!K25,0) -> 435 | U28: =ROUND(Q28*'Income Statement'!L25,0) -> 461 | V28: =ROUND(Q28*'Income Statement'!M25,0) -> 488 | W28: =ROUND(Q28*'Income Statement'!N25,0) -> 515 | X28: =ROUND(Q28*'Income Statement'!O25,0) -> 542
A29: Inventories - Total | B29: 6038 | C29: 6102 | D29: 6039 | E29: 6084 | F29: 4502 | G29: =B29 -> 6038 | H29: =C29 -> 6102 | I29: =D29 -> 6039 | J29: =E29 -> 6084 | K29: =F29 -> 4502 | L29: =IFERROR(G29/'Income Statement'!B25,"") -> 0.13212254 | M29: =IFERROR(H29/'Income Statement'!C25,"") -> 0.13808866 | N29: =IFERROR(I29/'Income Statement'!D25,"") -> 0.1386682 | O29: =IFERROR(J29/'Income Statement'!E25,"") -> 0.16515555 | P29: =IFERROR(K29/'Income Statement'!F25,"") -> 0.13264194 | Q29: =IFERROR(AVERAGE(L29:P29),"") -> 0.14133538 | R29: Avg % of adjusted revenue | S29: ROUND(Q29*IS_rev,0) | T29: =ROUND(Q29*'Income Statement'!K25,0) -> 7081 | U29: =ROUND(Q29*'Income Statement'!L25,0) -> 7518 | V29: =ROUND(Q29*'Income Statement'!M25,0) -> 7954 | W29: =ROUND(Q29*'Income Statement'!N25,0) -> 8390 | X29: =ROUND(Q29*'Income Statement'!O25,0) -> 8827
A30: Inventories - Raw Materials | B30: 65 | C30: 57 | D30: 34 | E30: 28 | F30: 28 | G30: =B30 -> 65 | H30: =C30 -> 57 | I30: =D30 -> 34 | J30: =E30 -> 28 | K30: =F30 -> 28 | L30: =IFERROR(G30/'Income Statement'!B25,"") -> 0.0014223195 | M30: =IFERROR(H30/'Income Statement'!C25,"") -> 0.0012899138 | N30: =IFERROR(I30/'Income Statement'!D25,"") -> 0.00078071183 | O30: =IFERROR(J30/'Income Statement'!E25,"") -> 0.0007600847 | P30: =IFERROR(K30/'Income Statement'!F25,"") -> 0.00082496096 | Q30: =IFERROR(AVERAGE(L30:P30),"") -> 0.0010155981 | R30: Avg % of adjusted revenue | S30: ROUND(Q30*IS_rev,0) | T30: =ROUND(Q30*'Income Statement'!K25,0) -> 51 | U30: =ROUND(Q30*'Income Statement'!L25,0) -> 54 | V30: =ROUND(Q30*'Income Statement'!M25,0) -> 57 | W30: =ROUND(Q30*'Income Statement'!N25,0) -> 60 | X30: =ROUND(Q30*'Income Statement'!O25,0) -> 63
A31: Inventories - Finished Goods | B31: 5973 | C31: 6038 | D31: 5997 | E31: 6047 | F31: 4465 | G31: =B31 -> 5973 | H31: =C31 -> 6038 | I31: =D31 -> 5997 | J31: =E31 -> 6047 | K31: =F31 -> 4465 | L31: =IFERROR(G31/'Income Statement'!B25,"") -> 0.13070022 | M31: =IFERROR(H31/'Income Statement'!C25,"") -> 0.13664034 | N31: =IFERROR(I31/'Income Statement'!D25,"") -> 0.13770379 | O31: =IFERROR(J31/'Income Statement'!E25,"") -> 0.16415115 | P31: =IFERROR(K31/'Income Statement'!F25,"") -> 0.13155181 | Q31: =IFERROR(AVERAGE(L31:P31),"") -> 0.14014946 | R31: Avg % of adjusted revenue | S31: ROUND(Q31*IS_rev,0) | T31: =ROUND(Q31*'Income Statement'!K25,0) -> 7022 | U31: =ROUND(Q31*'Income Statement'!L25,0) -> 7455 | V31: =ROUND(Q31*'Income Statement'!M25,0) -> 7887 | W31: =ROUND(Q31*'Income Statement'!N25,0) -> 8320 | X31: =ROUND(Q31*'Income Statement'!O25,0) -> 8753
A32: Inventories - Other - Total | C32: 7 | D32: 8 | E32: 9 | F32: 9 | H32: =C32 -> 7 | I32: =D32 -> 8 | J32: =E32 -> 9 | K32: =F32 -> 9 | L32: =IFERROR(G32/'Income Statement'!B25,"") -> 0 | M32: =IFERROR(H32/'Income Statement'!C25,"") -> 0.00015841046 | N32: =IFERROR(I32/'Income Statement'!D25,"") -> 0.0001836969 | O32: =IFERROR(J32/'Income Statement'!E25,"") -> 0.00024431294 | P32: =IFERROR(K32/'Income Statement'!F25,"") -> 0.00026516602 | Q32: =IFERROR(AVERAGE(L32:P32),"") -> 0.00017031727 | R32: Zero/nil in FY2025 – not forecast
A33: Other Current Assets - Total | B33: 238 | C33: 248 | D33: 237 | E33: 264 | F33: 172 | G33: =B33 -> 238 | H33: =C33 -> 248 | I33: =D33 -> 237 | J33: =E33 -> 264 | K33: =F33 -> 172 | L33: =IFERROR(G33/'Income Statement'!B25,"") -> 0.0052078775 | M33: =IFERROR(H33/'Income Statement'!C25,"") -> 0.0056122564 | N33: =IFERROR(I33/'Income Statement'!D25,"") -> 0.0054420207 | O33: =IFERROR(J33/'Income Statement'!E25,"") -> 0.0071665128 | P33: =IFERROR(K33/'Income Statement'!F25,"") -> 0.0050676173 | Q33: =IFERROR(AVERAGE(L33:P33),"") -> 0.0056992569 | R33: Avg % of adjusted revenue | S33: ROUND(Q33*IS_rev,0) | T33: =ROUND(Q33*'Income Statement'!K25,0) -> 286 | U33: =ROUND(Q33*'Income Statement'!L25,0) -> 303 | V33: =ROUND(Q33*'Income Statement'!M25,0) -> 321 | W33: =ROUND(Q33*'Income Statement'!N25,0) -> 338 | X33: =ROUND(Q33*'Income Statement'!O25,0) -> 356
A34: Other Current Assets | B34: 238 | C34: 248 | D34: 237 | E34: 264 | F34: 172 | G34: =B34 -> 238 | H34: =C34 -> 248 | I34: =D34 -> 237 | J34: =E34 -> 264 | K34: =F34 -> 172 | L34: =IFERROR(G34/'Income Statement'!B25,"") -> 0.0052078775 | M34: =IFERROR(H34/'Income Statement'!C25,"") -> 0.0056122564 | N34: =IFERROR(I34/'Income Statement'!D25,"") -> 0.0054420207 | O34: =IFERROR(J34/'Income Statement'!E25,"") -> 0.0071665128 | P34: =IFERROR(K34/'Income Statement'!F25,"") -> 0.0050676173 | Q34: =IFERROR(AVERAGE(L34:P34),"") -> 0.0056992569 | R34: 33 | S34: T33 (sub-item = total) | T34: =T33 -> 286 | U34: =U33 -> 303 | V34: =V33 -> 321 | W34: =W33 -> 338 | X34: =X33 -> 356
A35: Total Current Assets | B35: =B20+B22+B23+B29+B33 -> 9933 | C35: =C20+C22+C23+C29+C33 -> 9414 | D35: =D20+D22+D23+D29+D33 -> 9154 | E35: =E20+E22+E23+E29+E33 -> 9599 | F35: =F20+F22+F23+F29+F33 -> 9096 | G35: =G20+G22+G23+G29+G33 -> 9933 | H35: =H20+H22+H23+H29+H33 -> 9414 | I35: =I20+I22+I23+I29+I33 -> 9154 | ... K35: =K20+K22+K23+K29+K33 -> 9096 | L35: =IFERROR(G35/'Income Statement'!B25,"") -> 0.2173523 | M35: =IFERROR(H35/'Income Statement'!C25,"") -> 0.21303944 | N35: =IFERROR(I35/'Income Statement'!D25,"") -> 0.21019518 | O35: =IFERROR(J35/'Income Statement'!E25,"") -> 0.26057332 | P35: =IFERROR(K35/'Income Statement'!F25,"") -> 0.26799446 | Q35: =IFERROR(AVERAGE(L35:P35),"") -> 0.23383094 | R35: SUM: Cash + Deriv.Hedging + Loans&Rec + Inventories + OtherCA | S35: T20+T22+T23+T29+T33 | T35: =T20+T22+T23+T29+T33 -> 12750 | U35: =U20+U22+U23+U29+U33 -> 13546 | V35: =V20+V22+V23+V29+V33 -> 14315 | W35: =W20+W22+W23+W29+W33 -> 15065 | X35: =X20+X22+X23+X29+X33 -> 15799
A36: Non-Current Assets
A37: Investments - Long-Term | D37: 15 | E37: 677 | F37: 1124 | I37: =D37 -> 15 | J37: =E37 -> 677 | K37: =F37 -> 1124 | L37: =IFERROR(G37/'Income Statement'!B25,"") -> 0 | M37: =IFERROR(H37/'Income Statement'!C25,"") -> 0 | N37: =IFERROR(I37/'Income Statement'!D25,"") -> 0.00034443169 | O37: =IFERROR(J37/'Income Statement'!E25,"") -> 0.018377762 | P37: =IFERROR(K37/'Income Statement'!F25,"") -> 0.03311629 | Q37: =IFERROR(AVERAGE(L37:P37),"") -> 0.010367697 | R37: Zero/nil in FY2025 – not forecast
A38: Investments - Available for Sale/Held to Maturity - Long-Term | D38: 15 | E38: 677 | F38: 1124 | I38: =D38 -> 15 | J38: =E38 -> 677 | K38: =F38 -> 1124 | L38: =IFERROR(G38/'Income Statement'!B25,"") -> 0 | M38: =IFERROR(H38/'Income Statement'!C25,"") -> 0 | N38: =IFERROR(I38/'Income Statement'!D25,"") -> 0.00034443169 | O38: =IFERROR(J38/'Income Statement'!E25,"") -> 0.018377762 | P38: =IFERROR(K38/'Income Statement'!F25,"") -> 0.03311629 | Q38: =IFERROR(AVERAGE(L38:P38),"") -> 0.010367697 | R38: 37 | S38: T37 (sub-item) | T38: =T37 -> 0 | U38: =U37 -> 0 | V38: =V37 -> 0 | W38: =W37 -> 0 | X38: =X37 -> 0
A39: Investments in Associates, Joint Ventures and Unconsolidated Subsidiaries | B39: 1113 | C39: 938 | D39: 943 | E39: 934 | F39: 775 | G39: =B39 -> 1113 | H39: =C39 -> 938 | I39: =D39 -> 943 | J39: =E39 -> 934 | K39: =F39 -> 775 | L39: =IFERROR(G39/'Income Statement'!B25,"") -> 0.024354486 | M39: =IFERROR(H39/'Income Statement'!C25,"") -> 0.021227002 | N39: =IFERROR(I39/'Income Statement'!D25,"") -> 0.021653272 | O39: =IFERROR(J39/'Income Statement'!E25,"") -> 0.025354254 | P39: =IFERROR(K39/'Income Statement'!F25,"") -> 0.022833741 | Q39: =IFERROR(AVERAGE(L39:P39),"") -> 0.023084551 | R39: Avg % of adjusted revenue | S39: ROUND(Q39*IS_rev,0) | T39: =ROUND(Q39*'Income Statement'!K25,0) -> 1157 | U39: =ROUND(Q39*'Income Statement'!L25,0) -> 1228 | V39: =ROUND(Q39*'Income Statement'!M25,0) -> 1299 | W39: =ROUND(Q39*'Income Statement'!N25,0) -> 1370 | X39: =ROUND(Q39*'Income Statement'!O25,0) -> 1442
A40: Derivative Financial Instruments - Hedging - Long-Term | B40: 96 | C40: 22 | D40: 27 | E40: 8 | F40: 282 | G40: =B40 -> 96 | H40: =C40 -> 22 | I40: =D40 -> 27 | J40: =E40 -> 8 | K40: =F40 -> 282 | L40: =IFERROR(G40/'Income Statement'!B25,"") -> 0.0021006565 | M40: =IFERROR(H40/'Income Statement'!C25,"") -> 0.00049786146 | N40: =IFERROR(I40/'Income Statement'!D25,"") -> 0.00061997704 | O40: =IFERROR(J40/'Income Statement'!E25,"") -> 0.00021716706 | P40: =IFERROR(K40/'Income Statement'!F25,"") -> 0.0083085354 | Q40: =IFERROR(AVERAGE(L40:P40),"") -> 0.0023488395 | R40: Avg % of adjusted revenue | S40: ROUND(Q40*IS_rev,0) | T40: =ROUND(Q40*'Income Statement'!K25,0) -> 118 | U40: =ROUND(Q40*'Income Statement'!L25,0) -> 125 | V40: =ROUND(Q40*'Income Statement'!M25,0) -> 132 | W40: =ROUND(Q40*'Income Statement'!N25,0) -> 139 | X40: =ROUND(Q40*'Income Statement'!O25,0) -> 147
A41: Property, Plant & Equipment - Net - Total | B41: 11040 | C41: 11150 | D41: 11041 | E41: 10764 | F41: 10397 | G41: =B41 -> 11040 | H41: =C41 -> 11150 | I41: =D41 -> 11041 | J41: =E41 -> 10764 | K41: =F41 -> 10397 | L41: =IFERROR(G41/'Income Statement'!B25,"") -> 0.24157549 | M41: =IFERROR(H41/'Income Statement'!C25,"") -> 0.25232524 | N41: =IFERROR(I41/'Income Statement'!D25,"") -> 0.25352468 | O41: =IFERROR(J41/'Income Statement'!E25,"") -> 0.29219827 | P41: =IFERROR(K41/'Income Statement'!F25,"") -> 0.30632568 | Q41: =IFERROR(AVERAGE(L41:P41),"") -> 0.26918987 | R41: Prior PPE + Capex (4.12% of rev) – Depreciation (IS row 30) | S41: prior_PPE + 0.0412×IS_rev – IS_Dep_row30 | T41: =ROUND(G41+0.0412*'Income Statement'!K25-'Income Statement'!K30,0) -> 11500 | U41: =ROUND(T41+0.0412*'Income Statement'!L25-'Income Statement'!L30,0) -> 12020 | V41: =ROUND(U41+0.0412*'Income Statement'!M25-'Income Statement'!M30,0) -> 12592 | W41: =ROUND(V41+0.0412*'Income Statement'!N25-'Income Statement'!N30,0) -> 13208 | X41: =ROUND(W41+0.0412*'Income Statement'!O25-'Income Statement'!O30,0) -> 13862
A42: Property, Plant & Equipment - excluding Assets Leased Out - Net - Total | B42: 11040 | C42: 11150 | D42: 11041 | E42: 10764 | F42: 10397 | G42: =B42 -> 11040 | H42: =C42 -> 11150 | I42: =D42 -> 11041 | J42: =E42 -> 10764 | K42: =F42 -> 10397 | L42: =IFERROR(G42/'Income Statement'!B25,"") -> 0.24157549 | M42: =IFERROR(H42/'Income Statement'!C25,"") -> 0.25232524 | N42: =IFERROR(I42/'Income Statement'!D25,"") -> 0.25352468 | O42: =IFERROR(J42/'Income Statement'!E25,"") -> 0.29219827 | P42: =IFERROR(K42/'Income Statement'!F25,"") -> 0.30632568 | Q42: =IFERROR(AVERAGE(L42:P42),"") -> 0.26918987 | R42: 41 | S42: T41 (PPE excl leased = PPE Net Total) | T42: =T41 -> 11500 | U42: =U41 -> 12020 | V42: =V41 -> 12592 | W42: =W41 -> 13208 | X42: =X41 -> 13862
A43: Land & Buildings - Net | B43: 1101 | C43: 1018 | D43: 1007 | E43: 1012 | F43: 1070 | G43: =B43 -> 1101 | H43: =C43 -> 1018 | I43: =D43 -> 1007 | J43: =E43 -> 1012 | K43: =F43 -> 1070 | L43: =IFERROR(G43/'Income Statement'!B25,"") -> 0.024091904 | M43: =IFERROR(H43/'Income Statement'!C25,"") -> 0.023037407 | N43: =IFERROR(I43/'Income Statement'!D25,"") -> 0.023122847 | O43: =IFERROR(J43/'Income Statement'!E25,"") -> 0.027471633 | P43: =IFERROR(K43/'Income Statement'!F25,"") -> 0.031525294 | Q43: =IFERROR(AVERAGE(L43:P43),"") -> 0.025849817 | R43: Avg % of adjusted revenue | S43: ROUND(Q43*IS_rev,0) | T43: =ROUND(Q43*'Income Statement'!K25,0) -> 1295 | U43: =ROUND(Q43*'Income Statement'!L25,0) -> 1375 | V43: =ROUND(Q43*'Income Statement'!M25,0) -> 1455 | W43: =ROUND(Q43*'Income Statement'!N25,0) -> 1535 | X43: =ROUND(Q43*'Income Statement'!O25,0) -> 1614
A44: Land/Improvements - Net | B44: 436 | C44: 383 | D44: 323 | E44: 321 | F44: 369 | G44: =B44 -> 436 | H44: =C44 -> 383 | I44: =D44 -> 323 | J44: =E44 -> 321 | K44: =F44 -> 369 | L44: =IFERROR(G44/'Income Statement'!B25,"") -> 0.0095404814 | M44: =IFERROR(H44/'Income Statement'!C25,"") -> 0.0086673154 | N44: =IFERROR(I44/'Income Statement'!D25,"") -> 0.0074167623 | O44: =IFERROR(J44/'Income Statement'!E25,"") -> 0.0087138281 | P44: =IFERROR(K44/'Income Statement'!F25,"") -> 0.010871807 | Q44: =IFERROR(AVERAGE(L44:P44),"") -> 0.0090420388 | R44: Avg % of adjusted revenue | S44: ROUND(Q44*IS_rev,0) | T44: =ROUND(Q44*'Income Statement'!K25,0) -> 453 | U44: =ROUND(Q44*'Income Statement'!L25,0) -> 481 | V44: =ROUND(Q44*'Income Statement'!M25,0) -> 509 | W44: =ROUND(Q44*'Income Statement'!N25,0) -> 537 | X44: =ROUND(Q44*'Income Statement'!O25,0) -> 565
A45: Buildings - Net | B45: 367 | C45: 321 | D45: 329 | E45: 297 | F45: 324 | G45: =B45 -> 367 | H45: =C45 -> 321 | I45: =D45 -> 329 | J45: =E45 -> 297 | K45: =F45 -> 324 | L45: =IFERROR(G45/'Income Statement'!B25,"") -> 0.0080306346 | M45: =IFERROR(H45/'Income Statement'!C25,"") -> 0.0072642513 | N45: =IFERROR(I45/'Income Statement'!D25,"") -> 0.007554535 | O45: =IFERROR(J45/'Income Statement'!E25,"") -> 0.0080623269 | P45: =IFERROR(K45/'Income Statement'!F25,"") -> 0.0095459768 | Q45: =IFERROR(AVERAGE(L45:P45),"") -> 0.0080915449 | R45: Avg % of adjusted revenue | S45: ROUND(Q45*IS_rev,0) | T45: =ROUND(Q45*'Income Statement'!K25,0) -> 405 | U45: =ROUND(Q45*'Income Statement'!L25,0) -> 430 | V45: =ROUND(Q45*'Income Statement'!M25,0) -> 455 | W45: =ROUND(Q45*'Income Statement'!N25,0) -> 480 | X45: =ROUND(Q45*'Income Statement'!O25,0) -> 505
A46: Leasehold Improvements - Net | B46: 298 | C46: 314 | D46: 355 | E46: 394 | F46: 377 | G46: =B46 -> 298 | H46: =C46 -> 314 | I46: =D46 -> 355 | J46: =E46 -> 394 | K46: =F46 -> 377 | L46: =IFERROR(G46/'Income Statement'!B25,"") -> 0.0065207877 | M46: =IFERROR(H46/'Income Statement'!C25,"") -> 0.0071058408 | N46: =IFERROR(I46/'Income Statement'!D25,"") -> 0.0081515499 | O46: =IFERROR(J46/'Income Statement'!E25,"") -> 0.010695477 | P46: =IFERROR(K46/'Income Statement'!F25,"") -> 0.01110751 | Q46: =IFERROR(AVERAGE(L46:P46),"") -> 0.0087162332 | R46: Avg % of adjusted revenue | S46: ROUND(Q46*IS_rev,0) | T46: =ROUND(Q46*'Income Statement'!K25,0) -> 437 | U46: =ROUND(Q46*'Income Statement'!L25,0) -> 464 | V46: =ROUND(Q46*'Income Statement'!M25,0) -> 491 | W46: =ROUND(Q46*'Income Statement'!N25,0) -> 517 | X46: =ROUND(Q46*'Income Statement'!O25,0) -> 544
A47: Plant, Machinery & Equipment - Net | B47: 3527 | C47: 3685 | D47: 3429 | E47: 2868 | F47: 2426 | G47: =B47 -> 3527 | H47: =C47 -> 3685 | I47: =D47 -> 3429 | J47: =E47 -> 2868 | K47: =F47 -> 2426 | L47: =IFERROR(G47/'Income Statement'!B25,"") -> 0.077177243 | M47: =IFERROR(H47/'Income Statement'!C25,"") -> 0.083391794 | N47: =IFERROR(I47/'Income Statement'!D25,"") -> 0.078737084 | O47: =IFERROR(J47/'Income Statement'!E25,"") -> 0.077854389 | P47: =IFERROR(K47/'Income Statement'!F25,"") -> 0.071476975 | Q47: =IFERROR(AVERAGE(L47:P47),"") -> 0.077727497 | R47: Avg % of adjusted revenue | S47: ROUND(Q47*IS_rev,0) | T47: =ROUND(Q47*'Income Statement'!K25,0) -> 3894 | U47: =ROUND(Q47*'Income Statement'!L25,0) -> 4134 | V47: =ROUND(Q47*'Income Statement'!M25,0) -> 4374 | W47: =ROUND(Q47*'Income Statement'!N25,0) -> 4614 | X47: =ROUND(Q47*'Income Statement'!O25,0) -> 4854
A48: Right of Use Tangible Assets - Total - Net | B48: 5460 | C48: 5497 | D48: 5676 | E48: 6014 | F48: 6035 | G48: =B48 -> 5460 | H48: =C48 -> 5497 | I48: =D48 -> 5676 | J48: =E48 -> 6014 | K48: =F48 -> 6035 | L48: =IFERROR(G48/'Income Statement'!B25,"") -> 0.11947484 | M48: =IFERROR(H48/'Income Statement'!C25,"") -> 0.12439747 | N48: =IFERROR(I48/'Income Statement'!D25,"") -> 0.13033295 | O48: =IFERROR(J48/'Income Statement'!E25,"") -> 0.16325533 | P48: =IFERROR(K48/'Income Statement'!F25,"") -> 0.17780855 | Q48: =IFERROR(AVERAGE(L48:P48),"") -> 0.14305383 | R48: Avg % of adjusted revenue | S48: ROUND(Q48*IS_rev,0) | T48: =ROUND(Q48*'Income Statement'!K25,0) -> 7168 | U48: =ROUND(Q48*'Income Statement'!L25,0) -> 7609 | V48: =ROUND(Q48*'Income Statement'!M25,0) -> 8051 | W48: =ROUND(Q48*'Income Statement'!N25,0) -> 8492 | X48: =ROUND(Q48*'Income Statement'!O25,0) -> 8934
A49: Right of Use Tangible Assets - Capital/Finance Lease - Net | B49: 5460 | C49: 5497 | D49: 5676 | E49: 6014 | F49: 6035 | G49: =B49 -> 5460 | H49: =C49 -> 5497 | I49: =D49 -> 5676 | J49: =E49 -> 6014 | K49: =F49 -> 6035 | L49: =IFERROR(G49/'Income Statement'!B25,"") -> 0.11947484 | M49: =IFERROR(H49/'Income Statement'!C25,"") -> 0.12439747 | N49: =IFERROR(I49/'Income Statement'!D25,"") -> 0.13033295 | O49: =IFERROR(J49/'Income Statement'!E25,"") -> 0.16325533 | P49: =IFERROR(K49/'Income Statement'!F25,"") -> 0.17780855 | Q49: =IFERROR(AVERAGE(L49:P49),"") -> 0.14305383 | R49: 48 | S49: T48 (Finance lease = ROU total) | T49: =T48 -> 7168 | U49: =U48 -> 7609 | V49: =V48 -> 8051 | W49: =W48 -> 8492 | X49: =X48 -> 8934
A50: Property, Plant & Equipment - Other - Net | B50: 952 | C50: 950 | D50: 929 | E50: 870 | F50: 866 | G50: =B50 -> 952 | H50: =C50 -> 950 | I50: =D50 -> 929 | J50: =E50 -> 870 | K50: =F50 -> 866 | L50: =IFERROR(G50/'Income Statement'!B25,"") -> 0.02083151 | M50: =IFERROR(H50/'Income Statement'!C25,"") -> 0.021498563 | N50: =IFERROR(I50/'Income Statement'!D25,"") -> 0.021331803 | O50: =IFERROR(J50/'Income Statement'!E25,"") -> 0.023616917 | P50: =IFERROR(K50/'Income Statement'!F25,"") -> 0.025514864 | Q50: =IFERROR(AVERAGE(L50:P50),"") -> 0.022558731 | R50: Avg % of adjusted revenue | S50: ROUND(Q50*IS_rev,0) | T50: =ROUND(Q50*'Income Statement'!K25,0) -> 1130 | U50: =ROUND(Q50*'Income Statement'!L25,0) -> 1200 | V50: =ROUND(Q50*'Income Statement'!M25,0) -> 1270 | W50: =ROUND(Q50*'Income Statement'!N25,0) -> 1339 | X50: =ROUND(Q50*'Income Statement'!O25,0) -> 1409
A51: Mining/Exploration Specific Assets - Net | B51: 952 | C51: 950 | D51: 929 | E51: 870 | F51: 866 | G51: =B51 -> 952 | H51: =C51 -> 950 | I51: =D51 -> 929 | J51: =E51 -> 870 | K51: =F51 -> 866 | L51: =IFERROR(G51/'Income Statement'!B25,"") -> 0.02083151 | M51: =IFERROR(H51/'Income Statement'!C25,"") -> 0.021498563 | N51: =IFERROR(I51/'Income Statement'!D25,"") -> 0.021331803 | O51: =IFERROR(J51/'Income Statement'!E25,"") -> 0.023616917 | P51: =IFERROR(K51/'Income Statement'!F25,"") -> 0.025514864 | Q51: =IFERROR(AVERAGE(L51:P51),"") -> 0.022558731 | R51: 50 | S51: T50 (Mining assets = PPE Other) | T51: =T50 -> 1130 | U51: =U50 -> 1200 | V51: =V50 -> 1270 | W51: =W50 -> 1339 | X51: =X50 -> 1409
A52: Property, Plant & Equipment - Gross - Total | B52: 23300 | C52: 22519 | D52: 20857 | E52: 19215 | F52: 17618 | G52: =B52 -> 23300 | H52: =C52 -> 22519 | I52: =D52 -> 20857 | J52: =E52 -> 19215 | K52: =F52 -> 17618 | L52: =IFERROR(G52/'Income Statement'!B25,"") -> 0.50984683 | M52: =IFERROR(H52/'Income Statement'!C25,"") -> 0.50960646 | N52: =IFERROR(I52/'Income Statement'!D25,"") -> 0.47892078 | O52: =IFERROR(J52/'Income Statement'!E25,"") -> 0.52160812 | P52: =IFERROR(K52/'Income Statement'!F25,"") -> 0.51907722 | Q52: =IFERROR(AVERAGE(L52:P52),"") -> 0.50781188 | R52: Avg % of adjusted revenue | S52: ROUND(Q52*IS_rev,0) | T52: =ROUND(Q52*'Income Statement'!K25,0) -> 25443 | U52: =ROUND(Q52*'Income Statement'!L25,0) -> 27011 | V52: =ROUND(Q52*'Income Statement'!M25,0) -> 28579 | W52: =ROUND(Q52*'Income Statement'!N25,0) -> 30146 | X52: =ROUND(Q52*'Income Statement'!O25,0) -> 31714
A53: Property, Plant & Equipment - excluding Assets Leased Out - Gross | B53: 23300 | C53: 22519 | D53: 20857 | E53: 19215 | F53: 17618 | G53: =B53 -> 23300 | H53: =C53 -> 22519 | I53: =D53 -> 20857 | J53: =E53 -> 19215 | K53: =F53 -> 17618 | L53: =IFERROR(G53/'Income Statement'!B25,"") -> 0.50984683 | M53: =IFERROR(H53/'Income Statement'!C25,"") -> 0.50960646 | N53: =IFERROR(I53/'Income Statement'!D25,"") -> 0.47892078 | O53: =IFERROR(J53/'Income Statement'!E25,"") -> 0.52160812 | P53: =IFERROR(K53/'Income Statement'!F25,"") -> 0.51907722 | Q53: =IFERROR(AVERAGE(L53:P53),"") -> 0.50781188 | R53: 52 | S53: T52 (PPE Gross excl leased = PPE Gross) | T53: =T52 -> 25443 | U53: =U52 -> 27011 | V53: =V52 -> 28579 | W53: =W52 -> 30146 | X53: =X52 -> 31714
A54: Land & Buildings - Gross | B54: 2050 | C54: 1910 | D54: 1812 | E54: 1744 | F54: 1745 | G54: =B54 -> 2050 | H54: =C54 -> 1910 | I54: =D54 -> 1812 | J54: =E54 -> 1744 | K54: =F54 -> 1745 | L54: =IFERROR(G54/'Income Statement'!B25,"") -> 0.044857768 | M54: =IFERROR(H54/'Income Statement'!C25,"") -> 0.043223427 | N54: =IFERROR(I54/'Income Statement'!D25,"") -> 0.041607348 | O54: =IFERROR(J54/'Income Statement'!E25,"") -> 0.047342418 | P54: =IFERROR(K54/'Income Statement'!F25,"") -> 0.051412746 | Q54: =IFERROR(AVERAGE(L54:P54),"") -> 0.045688741 | R54: Avg % of adjusted revenue | S54: ROUND(Q54*IS_rev,0) | T54: =ROUND(Q54*'Income Statement'!K25,0) -> 2289 | U54: =ROUND(Q54*'Income Statement'!L25,0) -> 2430 | V54: =ROUND(Q54*'Income Statement'!M25,0) -> 2571 | W54: =ROUND(Q54*'Income Statement'!N25,0) -> 2712 | X54: =ROUND(Q54*'Income Statement'!O25,0) -> 2853
A55: Land/Improvements - Gross | B55: 436 | C55: 383 | D55: 323 | E55: 321 | F55: 369 | G55: =B55 -> 436 | H55: =C55 -> 383 | I55: =D55 -> 323 | J55: =E55 -> 321 | K55: =F55 -> 369 | L55: =IFERROR(G55/'Income Statement'!B25,"") -> 0.0095404814 | M55: =IFERROR(H55/'Income Statement'!C25,"") -> 0.0086673154 | N55: =IFERROR(I55/'Income Statement'!D25,"") -> 0.0074167623 | O55: =IFERROR(J55/'Income Statement'!E25,"") -> 0.0087138281 | P55: =IFERROR(K55/'Income Statement'!F25,"") -> 0.010871807 | Q55: =IFERROR(AVERAGE(L55:P55),"") -> 0.0090420388 | R55: Avg % of adjusted revenue | S55: ROUND(Q55*IS_rev,0) | T55: =ROUND(Q55*'Income Statement'!K25,0) -> 453 | U55: =ROUND(Q55*'Income Statement'!L25,0) -> 481 | V55: =ROUND(Q55*'Income Statement'!M25,0) -> 509 | W55: =ROUND(Q55*'Income Statement'!N25,0) -> 537 | X55: =ROUND(Q55*'Income Statement'!O25,0) -> 565
A56: Buildings - Gross | B56: 588 | C56: 541 | D56: 535 | E56: 489 | F56: 506 | G56: =B56 -> 588 | H56: =C56 -> 541 | I56: =D56 -> 535 | J56: =E56 -> 489 | K56: =F56 -> 506 | L56: =IFERROR(G56/'Income Statement'!B25,"") -> 0.012866521 | M56: =IFERROR(H56/'Income Statement'!C25,"") -> 0.012242866 | N56: =IFERROR(I56/'Income Statement'!D25,"") -> 0.01228473 | O56: =IFERROR(J56/'Income Statement'!E25,"") -> 0.013274336 | P56: =IFERROR(K56/'Income Statement'!F25,"") -> 0.014908223 | Q56: =IFERROR(AVERAGE(L56:P56),"") -> 0.013115335 | R56: Avg % of adjusted revenue | S56: ROUND(Q56*IS_rev,0) | T56: =ROUND(Q56*'Income Statement'!K25,0) -> 657 | U56: =ROUND(Q56*'Income Statement'!L25,0) -> 698 | V56: =ROUND(Q56*'Income Statement'!M25,0) -> 738 | W56: =ROUND(Q56*'Income Statement'!N25,0) -> 779 | X56: =ROUND(Q56*'Income Statement'!O25,0) -> 819
A57: Leasehold Improvements - Gross | B57: 1026 | C57: 986 | D57: 954 | E57: 934 | F57: 870 | G57: =B57 -> 1026 | H57: =C57 -> 986 | I57: =D57 -> 954 | J57: =E57 -> 934 | K57: =F57 -> 870 | L57: =IFERROR(G57/'Income Statement'!B25,"") -> 0.022450766 | M57: =IFERROR(H57/'Income Statement'!C25,"") -> 0.022313245 | N57: =IFERROR(I57/'Income Statement'!D25,"") -> 0.021905855 | O57: =IFERROR(J57/'Income Statement'!E25,"") -> 0.025354254 | P57: =IFERROR(K57/'Income Statement'!F25,"") -> 0.025632716 | Q57: =IFERROR(AVERAGE(L57:P57),"") -> 0.023531367 | R57: Avg % of adjusted revenue | S57: ROUND(Q57*IS_rev,0) | T57: =ROUND(Q57*'Income Statement'!K25,0) -> 1179 | U57: =ROUND(Q57*'Income Statement'!L25,0) -> 1252 | V57: =ROUND(Q57*'Income Statement'!M25,0) -> 1324 | W57: =ROUND(Q57*'Income Statement'!N25,0) -> 1397 | X57: =ROUND(Q57*'Income Statement'!O25,0) -> 1470
A58: Plant, Machinery & Equipment - Gross | B58: 8787 | C58: 9151 | D58: 8490 | E58: 7648 | F58: 6985 | G58: =B58 -> 8787 | H58: =C58 -> 9151 | I58: =D58 -> 8490 | J58: =E58 -> 7648 | K58: =F58 -> 6985 | L58: =IFERROR(G58/'Income Statement'!B25,"") -> 0.19227571 | M58: =IFERROR(H58/'Income Statement'!C25,"") -> 0.20708774 | N58: =IFERROR(I58/'Income Statement'!D25,"") -> 0.19494834 | O58: =IFERROR(J58/'Income Statement'!E25,"") -> 0.20761171 | P58: =IFERROR(K58/'Income Statement'!F25,"") -> 0.2057983 | Q58: =IFERROR(AVERAGE(L58:P58),"") -> 0.20154436 | R58: Avg % of adjusted revenue | S58: ROUND(Q58*IS_rev,0) | T58: =ROUND(Q58*'Income Statement'!K25,0) -> 10098 | U58: =ROUND(Q58*'Income Statement'!L25,0) -> 10720 | V58: =ROUND(Q58*'Income Statement'!M25,0) -> 11343 | W58: =ROUND(Q58*'Income Statement'!N25,0) -> 11965 | X58: =ROUND(Q58*'Income Statement'!O25,0) -> 12587
A59: Right of Use Tangible Assets - Total - Gross | B59: 11472 | C59: 10493 | D59: 9626 | E59: 8953 | F59: 8022 | G59: =B59 -> 11472 | H59: =C59 -> 10493 | I59: =D59 -> 9626 | J59: =E59 -> 8953 | K59: =F59 -> 8022 | L59: =IFERROR(G59/'Income Statement'!B25,"") -> 0.25102845 | M59: =IFERROR(H59/'Income Statement'!C25,"") -> 0.23745729 | N59: =IFERROR(I59/'Income Statement'!D25,"") -> 0.2210333 | O59: =IFERROR(J59/'Income Statement'!E25,"") -> 0.24303708 | P59: =IFERROR(K59/'Income Statement'!F25,"") -> 0.23635132 | Q59: =IFERROR(AVERAGE(L59:P59),"") -> 0.23778148 | R59: Avg % of adjusted revenue | S59: ROUND(Q59*IS_rev,0) | T59: =ROUND(Q59*'Income Statement'!K25,0) -> 11914 | U59: =ROUND(Q59*'Income Statement'!L25,0) -> 12648 | V59: =ROUND(Q59*'Income Statement'!M25,0) -> 13382 | W59: =ROUND(Q59*'Income Statement'!N25,0) -> 14116 | X59: =ROUND(Q59*'Income Statement'!O25,0) -> 14850
A60: Right of Use Tangible Assets - Capital/Finance Lease - Gross | B60: 11472 | C60: 10493 | D60: 9626 | E60: 8953 | F60: 8022 | G60: =B60 -> 11472 | H60: =C60 -> 10493 | I60: =D60 -> 9626 | J60: =E60 -> 8953 | K60: =F60 -> 8022 | L60: =IFERROR(G60/'Income Statement'!B25,"") -> 0.25102845 | M60: =IFERROR(H60/'Income Statement'!C25,"") -> 0.23745729 | N60: =IFERROR(I60/'Income Statement'!D25,"") -> 0.2210333 | O60: =IFERROR(J60/'Income Statement'!E25,"") -> 0.24303708 | P60: =IFERROR(K60/'Income Statement'!F25,"") -> 0.23635132 | Q60: =IFERROR(AVERAGE(L60:P60),"") -> 0.23778148 | R60: 59 | S60: T59 (Finance lease gross = ROU gross) | T60: =T59 -> 11914 | U60: =U59 -> 12648 | V60: =V59 -> 13382 | W60: =W59 -> 14116 | X60: =X59 -> 14850
A61: Property, Plant & Equipment - Other - Gross | B61: 991 | C61: 965 | D61: 929 | E61: 870 | F61: 866 | G61: =B61 -> 991 | H61: =C61 -> 965 | I61: =D61 -> 929 | J61: =E61 -> 870 | K61: =F61 -> 866 | L61: =IFERROR(G61/'Income Statement'!B25,"") -> 0.021684902 | M61: =IFERROR(H61/'Income Statement'!C25,"") -> 0.021838014 | N61: =IFERROR(I61/'Income Statement'!D25,"") -> 0.021331803 | O61: =IFERROR(J61/'Income Statement'!E25,"") -> 0.023616917 | P61: =IFERROR(K61/'Income Statement'!F25,"") -> 0.025514864 | Q61: =IFERROR(AVERAGE(L61:P61),"") -> 0.0227973 | R61: Avg % of adjusted revenue | S61: ROUND(Q61*IS_rev,0) | T61: =ROUND(Q61*'Income Statement'!K25,0) -> 1142 | U61: =ROUND(Q61*'Income Statement'!L25,0) -> 1213 | V61: =ROUND(Q61*'Income Statement'!M25,0) -> 1283 | W61: =ROUND(Q61*'Income Statement'!N25,0) -> 1353 | X61: =ROUND(Q61*'Income Statement'!O25,0) -> 1424
A62: Mining/Exploration Specific Assets - Gross | B62: 991 | C62: 965 | D62: 929 | E62: 870 | F62: 866 | G62: =B62 -> 991 | H62: =C62 -> 965 | I62: =D62 -> 929 | J62: =E62 -> 870 | K62: =F62 -> 866 | L62: =IFERROR(G62/'Income Statement'!B25,"") -> 0.021684902 | M62: =IFERROR(H62/'Income Statement'!C25,"") -> 0.021838014 | N62: =IFERROR(I62/'Income Statement'!D25,"") -> 0.021331803 | O62: =IFERROR(J62/'Income Statement'!E25,"") -> 0.023616917 | P62: =IFERROR(K62/'Income Statement'!F25,"") -> 0.025514864 | Q62: =IFERROR(AVERAGE(L62:P62),"") -> 0.0227973 | R62: 61 | S62: T61 (Mining gross = PPE Other gross) | T62: =T61 -> 1142 | U62: =U61 -> 1213 | V62: =V61 -> 1283 | W62: =W61 -> 1353 | X62: =X61 -> 1424
A63: Property, Plant & Equipment - Accumulated Depreciation & Impairment - Total | B63: 12260 | C63: 11369 | D63: 9816 | E63: 8451 | F63: 7221 | G63: =B63 -> 12260 | H63: =C63 -> 11369 | I63: =D63 -> 9816 | J63: =E63 -> 8451 | K63: =F63 -> 7221 | L63: =IFERROR(G63/'Income Statement'!B25,"") -> 0.26827133 | M63: =IFERROR(H63/'Income Statement'!C25,"") -> 0.25728122 | N63: =IFERROR(I63/'Income Statement'!D25,"") -> 0.2253961 | O63: =IFERROR(J63/'Income Statement'!E25,"") -> 0.22940985 | P63: =IFERROR(K63/'Income Statement'!F25,"") -> 0.21275154 | Q63: =IFERROR(AVERAGE(L63:P63),"") -> 0.23862201 | R63: Avg % of adjusted revenue | S63: ROUND(Q63*IS_rev,0) | T63: =ROUND(Q63*'Income Statement'!K25,0) -> 11956 | U63: =ROUND(Q63*'Income Statement'!L25,0) -> 12693 | V63: =ROUND(Q63*'Income Statement'!M25,0) -> 13429 | W63: =ROUND(Q63*'Income Statement'!N25,0) -> 14166 | X63: =ROUND(Q63*'Income Statement'!O25,0) -> 14902
A64: Property, Plant & Equipment - excluding Assets Leased Out - Accumulated Depreciation & Impairment - Total | B64: 12260 | C64: 11369 | D64: 9816 | E64: 8451 | F64: 7221 | G64: =B64 -> 12260 | H64: =C64 -> 11369 | I64: =D64 -> 9816 | J64: =E64 -> 8451 | K64: =F64 -> 7221 | L64: =IFERROR(G64/'Income Statement'!B25,"") -> 0.26827133 | M64: =IFERROR(H64/'Income Statement'!C25,"") -> 0.25728122 | N64: =IFERROR(I64/'Income Statement'!D25,"") -> 0.2253961 | O64: =IFERROR(J64/'Income Statement'!E25,"") -> 0.22940985 | P64: =IFERROR(K64/'Income Statement'!F25,"") -> 0.21275154 | Q64: =IFERROR(AVERAGE(L64:P64),"") -> 0.23862201 | R64: 63 | S64: T63 (excl leased accum dep = total accum dep) | T64: =T63 -> 11956 | U64: =U63 -> 12693 | V64: =V63 -> 13429 | W64: =W63 -> 14166 | X64: =X63 -> 14902
A65: Land & Buildings - Accumulated Depreciation & Impairment | B65: 949 | C65: 892 | D65: 805 | E65: 732 | F65: 675 | G65: =B65 -> 949 | H65: =C65 -> 892 | I65: =D65 -> 805 | J65: =E65 -> 732 | K65: =F65 -> 675 | L65: =IFERROR(G65/'Income Statement'!B25,"") -> 0.020765864 | M65: =IFERROR(H65/'Income Statement'!C25,"") -> 0.020186019 | N65: =IFERROR(I65/'Income Statement'!D25,"") -> 0.018484501 | O65: =IFERROR(J65/'Income Statement'!E25,"") -> 0.019870786 | P65: =IFERROR(K65/'Income Statement'!F25,"") -> 0.019887452 | Q65: =IFERROR(AVERAGE(L65:P65),"") -> 0.019838924 | R65: Avg % of adjusted revenue | S65: ROUND(Q65*IS_rev,0) | T65: =ROUND(Q65*'Income Statement'!K25,0) -> 994 | U65: =ROUND(Q65*'Income Statement'!L25,0) -> 1055 | V65: =ROUND(Q65*'Income Statement'!M25,0) -> 1116 | W65: =ROUND(Q65*'Income Statement'!N25,0) -> 1178 | X65: =ROUND(Q65*'Income Statement'!O25,0) -> 1239
A66: Buildings - Accumulated Depreciation & Impairment | B66: 221 | C66: 220 | D66: 206 | E66: 192 | F66: 182 | G66: =B66 -> 221 | H66: =C66 -> 220 | I66: =D66 -> 206 | J66: =E66 -> 192 | K66: =F66 -> 182 | L66: =IFERROR(G66/'Income Statement'!B25,"") -> 0.0048358862 | M66: =IFERROR(H66/'Income Statement'!C25,"") -> 0.0049786146 | N66: =IFERROR(I66/'Income Statement'!D25,"") -> 0.0047301952 | O66: =IFERROR(J66/'Income Statement'!E25,"") -> 0.0052120093 | P66: =IFERROR(K66/'Income Statement'!F25,"") -> 0.0053622463 | Q66: =IFERROR(AVERAGE(L66:P66),"") -> 0.0050237903 | R66: Avg % of adjusted revenue | S66: ROUND(Q66*IS_rev,0) | T66: =ROUND(Q66*'Income Statement'!K25,0) -> 252 | U66: =ROUND(Q66*'Income Statement'!L25,0) -> 267 | V66: =ROUND(Q66*'Income Statement'!M25,0) -> 283 | W66: =ROUND(Q66*'Income Statement'!N25,0) -> 298 | X66: =ROUND(Q66*'Income Statement'!O25,0) -> 314
A67: Leasehold Improvements - Accumulated Depreciation & Impairment | B67: 728 | C67: 672 | D67: 599 | E67: 540 | F67: 493 | G67: =B67 -> 728 | H67: =C67 -> 672 | I67: =D67 -> 599 | J67: =E67 -> 540 | K67: =F67 -> 493 | L67: =IFERROR(G67/'Income Statement'!B25,"") -> 0.015929978 | M67: =IFERROR(H67/'Income Statement'!C25,"") -> 0.015207405 | N67: =IFERROR(I67/'Income Statement'!D25,"") -> 0.013754305 | O67: =IFERROR(J67/'Income Statement'!E25,"") -> 0.014658776 | P67: =IFERROR(K67/'Income Statement'!F25,"") -> 0.014525206 | Q67: =IFERROR(AVERAGE(L67:P67),"") -> 0.014815134 | R67: Avg % of adjusted revenue | S67: ROUND(Q67*IS_rev,0) | T67: =ROUND(Q67*'Income Statement'!K25,0) -> 742 | U67: =ROUND(Q67*'Income Statement'!L25,0) -> 788 | V67: =ROUND(Q67*'Income Statement'!M25,0) -> 834 | W67: =ROUND(Q67*'Income Statement'!N25,0) -> 880 | X67: =ROUND(Q67*'Income Statement'!O25,0) -> 925
A68: Plant, Machinery & Equipment - Accumulated Depreciation & Impairment | B68: 5260 | C68: 5466 | D68: 5061 | E68: 4780 | F68: 4559 | G68: =B68 -> 5260 | H68: =C68 -> 5466 | I68: =D68 -> 5061 | J68: =E68 -> 4780 | K68: =F68 -> 4559 | L68: =IFERROR(G68/'Income Statement'!B25,"") -> 0.11509847 | M68: =IFERROR(H68/'Income Statement'!C25,"") -> 0.12369594 | N68: =IFERROR(I68/'Income Statement'!D25,"") -> 0.11621125 | O68: =IFERROR(J68/'Income Statement'!E25,"") -> 0.12975732 | P68: =IFERROR(K68/'Income Statement'!F25,"") -> 0.13432132 | Q68: =IFERROR(AVERAGE(L68:P68),"") -> 0.12381686 | R68: Avg % of adjusted revenue | S68: ROUND(Q68*IS_rev,0) | T68: =ROUND(Q68*'Income Statement'!K25,0) -> 6204 | U68: =ROUND(Q68*'Income Statement'!L25,0) -> 6586 | V68: =ROUND(Q68*'Income Statement'!M25,0) -> 6968 | W68: =ROUND(Q68*'Income Statement'!N25,0) -> 7350 | X68: =ROUND(Q68*'Income Statement'!O25,0) -> 7733
A69: Right of Use Tangible Assets - Total/Unspecified - Accumulated Depreciation | B69: 6012 | C69: 4996 | D69: 3950 | E69: 2939 | F69: 1987 | G69: =B69 -> 6012 | H69: =C69 -> 4996 | I69: =D69 -> 3950 | J69: =E69 -> 2939 | K69: =F69 -> 1987 | L69: =IFERROR(G69/'Income Statement'!B25,"") -> 0.13155361 | M69: =IFERROR(H69/'Income Statement'!C25,"") -> 0.11305981 | N69: =IFERROR(I69/'Income Statement'!D25,"") -> 0.090700344 | O69: =IFERROR(J69/'Income Statement'!E25,"") -> 0.079781747 | P69: =IFERROR(K69/'Income Statement'!F25,"") -> 0.058542765 | Q69: =IFERROR(AVERAGE(L69:P69),"") -> 0.094727656 | R69: Avg % of adjusted revenue | S69: ROUND(Q69*IS_rev,0) | T69: =ROUND(Q69*'Income Statement'!K25,0) -> 4746 | U69: =ROUND(Q69*'Income Statement'!L25,0) -> 5039 | V69: =ROUND(Q69*'Income Statement'!M25,0) -> 5331 | W69: =ROUND(Q69*'Income Statement'!N25,0) -> 5624 | X69: =ROUND(Q69*'Income Statement'!O25,0) -> 5916
A70: Right of Use Tangible Assets - Capital/Finance Lease - Accumulated Depreciation | B70: 6012 | C70: 4996 | D70: 3950 | E70: 2939 | F70: 1987 | G70: =B70 -> 6012 | H70: =C70 -> 4996 | I70: =D70 -> 3950 | J70: =E70 -> 2939 | K70: =F70 -> 1987 | L70: =IFERROR(G70/'Income Statement'!B25,"") -> 0.13155361 | M70: =IFERROR(H70/'Income Statement'!C25,"") -> 0.11305981 | N70: =IFERROR(I70/'Income Statement'!D25,"") -> 0.090700344 | O70: =IFERROR(J70/'Income Statement'!E25,"") -> 0.079781747 | P70: =IFERROR(K70/'Income Statement'!F25,"") -> 0.058542765 | Q70: =IFERROR(AVERAGE(L70:P70),"") -> 0.094727656 | R70: 69 | S70: T69 (finance lease accum dep = ROU accum dep) | T70: =T69 -> 4746 | U70: =U69 -> 5039 | V70: =V69 -> 5331 | W70: =W69 -> 5624 | X70: =X69 -> 5916
A71: Property, Plant & Equipment - Other - Accumulated Depreciation & Impairment | B71: 39 | C71: 15 | D71: 0 | E71: 0 | G71: =B71 -> 39 | H71: =C71 -> 15 | I71: =D71 -> 0 | J71: =E71 -> 0 | L71: =IFERROR(G71/'Income Statement'!B25,"") -> 0.00085339168 | M71: =IFERROR(H71/'Income Statement'!C25,"") -> 0.00033945099 | N71: =IFERROR(I71/'Income Statement'!D25,"") -> 0 | O71: =IFERROR(J71/'Income Statement'!E25,"") -> 0 | P71: =IFERROR(K71/'Income Statement'!F25,"") -> 0 | Q71: =IFERROR(AVERAGE(L71:P71),"") -> 0.00023856854 | R71: Avg % of adjusted revenue | S71: ROUND(Q71*IS_rev,0) | T71: =ROUND(Q71*'Income Statement'!K25,0) -> 12 | U71: =ROUND(Q71*'Income Statement'!L25,0) -> 13 | V71: =ROUND(Q71*'Income Statement'!M25,0) -> 13 | W71: =ROUND(Q71*'Income Statement'!N25,0) -> 14 | X71: =ROUND(Q71*'Income Statement'!O25,0) -> 15
A72: Mining/Exploration Specific Assets - Accumulated Depreciation & Impairment | B72: 39 | C72: 15 | D72: 0 | E72: 0 | G72: =B72 -> 39 | H72: =C72 -> 15 | I72: =D72 -> 0 | J72: =E72 -> 0 | L72: =IFERROR(G72/'Income Statement'!B25,"") -> 0.00085339168 | M72: =IFERROR(H72/'Income Statement'!C25,"") -> 0.00033945099 | N72: =IFERROR(I72/'Income Statement'!D25,"") -> 0 | O72: =IFERROR(J72/'Income Statement'!E25,"") -> 0 | P72: =IFERROR(K72/'Income Statement'!F25,"") -> 0 | Q72: =IFERROR(AVERAGE(L72:P72),"") -> 0.00023856854 | R72: 71 | S72: T71 (mining accum dep = PPE Other accum dep) | T72: =T71 -> 12 | U72: =U71 -> 13 | V72: =V71 -> 13 | W72: =W71 -> 14 | X72: =X71 -> 15
A73: Other Non-Current Assets - Total | B73: 842 | C73: 734 | D73: 674 | E73: 620 | F73: 638 | G73: =G74+G75+G76 -> 211 | H73: =H74+H75+H76 -> 93 | I73: =I74+I75+I76 -> 50 | J73: =J74+J75+J76 -> 39 | K73: =K74+K75+K76 -> 25 | L73: =IFERROR(G73/'Income Statement'!B25,"") -> 0.0046170678 | M73: =IFERROR(H73/'Income Statement'!C25,"") -> 0.0021045962 | N73: =IFERROR(I73/'Income Statement'!D25,"") -> 0.0011481056 | O73: =IFERROR(J73/'Income Statement'!E25,"") -> 0.0010586894 | P73: =IFERROR(K73/'Income Statement'!F25,"") -> 0.00073657229 | Q73: =IFERROR(AVERAGE(L73:P73),"") -> 0.0019330063 | R73: SUM: DTA(0) + LT Inv + Other NCA | S73: T74+T75+T76 | T73: =T74+T75+T76 -> 97 | U73: =U74+U75+U76 -> 102 | V73: =V74+V75+V76 -> 109 | W73: =W74+W75+W76 -> 115 | X73: =X74+X75+X76 -> 121
A74: Deferred Tax - Asset - Long-Term | B74: 631 | C74: 641 | D74: 624 | E74: 581 | F74: 613 | G74: 0 | H74: 0 | I74: 0 | J74: 0 | K74: 0 | L74: =IFERROR(G74/'Income Statement'!B25,"") -> 0 | M74: =IFERROR(H74/'Income Statement'!C25,"") -> 0 | N74: =IFERROR(I74/'Income Statement'!D25,"") -> 0 | O74: =IFERROR(J74/'Income Statement'!E25,"") -> 0 | P74: =IFERROR(K74/'Income Statement'!F25,"") -> 0 | Q74: =IFERROR(AVERAGE(L74:P74),"") -> 0 | R74: Adjusted to $0 (goodwill/DTA removed) | S74: 0 (adjusted) | T74: 0 | U74: 0 | V74: 0 | W74: 0 | X74: 0
A75: Inventories - Long-Term | B75: 15 | G75: =B75 -> 15 | L75: =IFERROR(G75/'Income Statement'!B25,"") -> 0.00032822757 | M75: =IFERROR(H75/'Income Statement'!C25,"") -> 0 | N75: =IFERROR(I75/'Income Statement'!D25,"") -> 0 | O75: =IFERROR(J75/'Income Statement'!E25,"") -> 0 | P75: =IFERROR(K75/'Income Statement'!F25,"") -> 0 | Q75: =IFERROR(AVERAGE(L75:P75),"") -> 6.5645514e-05 | R75: Avg % of adjusted revenue | S75: ROUND(Q75*IS_rev,0) | T75: =ROUND(Q75*'Income Statement'!K25,0) -> 3 | U75: =ROUND(Q75*'Income Statement'!L25,0) -> 3 | V75: =ROUND(Q75*'Income Statement'!M25,0) -> 4 | W75: =ROUND(Q75*'Income Statement'!N25,0) -> 4 | X75: =ROUND(Q75*'Income Statement'!O25,0) -> 4
A76: Other Non-Current Assets | B76: 196 | C76: 93 | D76: 50 | E76: 39 | F76: 25 | G76: =B76 -> 196 | H76: =C76 -> 93 | I76: =D76 -> 50 | J76: =E76 -> 39 | K76: =F76 -> 25 | L76: =IFERROR(G76/'Income Statement'!B25,"") -> 0.0042888403 | M76: =IFERROR(H76/'Income Statement'!C25,"") -> 0.0021045962 | N76: =IFERROR(I76/'Income Statement'!D25,"") -> 0.0011481056 | O76: =IFERROR(J76/'Income Statement'!E25,"") -> 0.0010586894 | P76: =IFERROR(K76/'Income Statement'!F25,"") -> 0.00073657229 | Q76: =IFERROR(AVERAGE(L76:P76),"") -> 0.0018673607 | R76: Avg % of adjusted revenue | S76: ROUND(Q76*IS_rev,0) | T76: =ROUND(Q76*'Income Statement'!K25,0) -> 94 | U76: =ROUND(Q76*'Income Statement'!L25,0) -> 99 | V76: =ROUND(Q76*'Income Statement'!M25,0) -> 105 | W76: =ROUND(Q76*'Income Statement'!N25,0) -> 111 | X76: =ROUND(Q76*'Income Statement'!O25,0) -> 117
A77: Intangible Assets - Total - Net | B77: 4957 | C77: 5051 | D77: 4692 | E77: 4684 | F77: 3902 | G77: =G78+G79 -> 1469 | H77: =H78+H79 -> 1463 | I77: =I78+I79 -> 1340 | J77: =J78+J79 -> 1347 | K77: =K78+K79 -> 935 | L77: =IFERROR(G77/'Income Statement'!B25,"") -> 0.03214442 | M77: =IFERROR(H77/'Income Statement'!C25,"") -> 0.033107787 | N77: =IFERROR(I77/'Income Statement'!D25,"") -> 0.030769231 | O77: =IFERROR(J77/'Income Statement'!E25,"") -> 0.036565503 | P77: =IFERROR(K77/'Income Statement'!F25,"") -> 0.027547804 | Q77: =IFERROR(AVERAGE(L77:P77),"") -> 0.032026949 | R77: SUM: Goodwill(0) + Intangibles excl GW | S77: T78+T79 | T77: =T78+T79 -> 1605 | U77: =U78+U79 -> 1704 | V77: =V78+V79 -> 1802 | W77: =W78+W79 -> 1901 | X77: =X78+X79 -> 2000
A78: Goodwill/Cost in Excess of Assets Purchased - Net | B78: 3488 | C78: 3588 | D78: 3352 | E78: 3337 | F78: 2967 | G78: 0 | H78: 0 | I78: 0 | J78: 0 | K78: 0 | L78: =IFERROR(G78/'Income Statement'!B25,"") -> 0 | M78: =IFERROR(H78/'Income Statement'!C25,"") -> 0 | N78: =IFERROR(I78/'Income Statement'!D25,"") -> 0 | O78: =IFERROR(J78/'Income Statement'!E25,"") -> 0 | P78: =IFERROR(K78/'Income Statement'!F25,"") -> 0 | Q78: =IFERROR(AVERAGE(L78:P78),"") -> 0 | R78: Adjusted to $0 (goodwill removed) | S78: 0 (adjusted) | T78: 0 | U78: 0 | V78: 0 | W78: 0 | X78: 0
A79: Intangible Assets - excluding Goodwill - Net - Total | B79: 1469 | C79: 1463 | D79: 1340 | E79: 1347 | F79: 935 | G79: =B79 -> 1469 | H79: =C79 -> 1463 | I79: =D79 -> 1340 | J79: =E79 -> 1347 | K79: =F79 -> 935 | L79: =IFERROR(G79/'Income Statement'!B25,"") -> 0.03214442 | M79: =IFERROR(H79/'Income Statement'!C25,"") -> 0.033107787 | N79: =IFERROR(I79/'Income Statement'!D25,"") -> 0.030769231 | O79: =IFERROR(J79/'Income Statement'!E25,"") -> 0.036565503 | P79: =IFERROR(K79/'Income Statement'!F25,"") -> 0.027547804 | Q79: =IFERROR(AVERAGE(L79:P79),"") -> 0.032026949 | R79: Avg % of adjusted revenue | S79: ROUND(Q79*IS_rev,0) | T79: =ROUND(Q79*'Income Statement'!K25,0) -> 1605 | U79: =ROUND(Q79*'Income Statement'!L25,0) -> 1704 | V79: =ROUND(Q79*'Income Statement'!M25,0) -> 1802 | W79: =ROUND(Q79*'Income Statement'!N25,0) -> 1901 | X79: =ROUND(Q79*'Income Statement'!O25,0) -> 2000
A80: Computer Software - Intangible Assets - Net | B80: 532 | C80: 499 | D80: 441 | E80: 439 | F80: 289 | G80: =B80 -> 532 | H80: =C80 -> 499 | I80: =D80 -> 441 | J80: =E80 -> 439 | K80: =F80 -> 289 | L80: =IFERROR(G80/'Income Statement'!B25,"") -> 0.011641138 | M80: =IFERROR(H80/'Income Statement'!C25,"") -> 0.011292403 | N80: =IFERROR(I80/'Income Statement'!D25,"") -> 0.010126292 | O80: =IFERROR(J80/'Income Statement'!E25,"") -> 0.011917042 | P80: =IFERROR(K80/'Income Statement'!F25,"") -> 0.0085147756 | Q80: =IFERROR(AVERAGE(L80:P80),"") -> 0.01069833 | R80: Avg % of adjusted revenue | S80: ROUND(Q80*IS_rev,0) | T80: =ROUND(Q80*'Income Statement'!K25,0) -> 536 | U80: =ROUND(Q80*'Income Statement'!L25,0) -> 569 | V80: =ROUND(Q80*'Income Statement'!M25,0) -> 602 | W80: =ROUND(Q80*'Income Statement'!N25,0) -> 635 | X80: =ROUND(Q80*'Income Statement'!O25,0) -> 668
A81: Brands, Patents, Trademarks, Marketing & Artistic Intangibles - Net | B81: 839 | C81: 839 | D81: 824 | E81: 824 | F81: 617 | G81: =B81 -> 839 | H81: =C81 -> 839 | I81: =D81 -> 824 | J81: =E81 -> 824 | K81: =F81 -> 617 | L81: =IFERROR(G81/'Income Statement'!B25,"") -> 0.018358862 | M81: =IFERROR(H81/'Income Statement'!C25,"") -> 0.018986626 | N81: =IFERROR(I81/'Income Statement'!D25,"") -> 0.018920781 | O81: =IFERROR(J81/'Income Statement'!E25,"") -> 0.022368207 | P81: =IFERROR(K81/'Income Statement'!F25,"") -> 0.018178604 | Q81: =IFERROR(AVERAGE(L81:P81),"") -> 0.019362616 | R81: Avg % of adjusted revenue | S81: ROUND(Q81*IS_rev,0) | T81: =ROUND(Q81*'Income Statement'!K25,0) -> 970 | U81: =ROUND(Q81*'Income Statement'!L25,0) -> 1030 | V81: =ROUND(Q81*'Income Statement'!M25,0) -> 1090 | W81: =ROUND(Q81*'Income Statement'!N25,0) -> 1149 | X81: =ROUND(Q81*'Income Statement'!O25,0) -> 1209
A82: Licenses, Franchises, Copyrights, Property Rights, Prototypes, Contract Based, Models & Designs - Net | B82: 98 | C82: 125 | D82: 76 | E82: 84 | F82: 29 | G82: =B82 -> 98 | H82: =C82 -> 125 | I82: =D82 -> 76 | J82: =E82 -> 84 | K82: =F82 -> 29 | L82: =IFERROR(G82/'Income Statement'!B25,"") -> 0.0021444201 | M82: =IFERROR(H82/'Income Statement'!C25,"") -> 0.0028287583 | N82: =IFERROR(I82/'Income Statement'!D25,"") -> 0.0017451206 | O82: =IFERROR(J82/'Income Statement'!E25,"") -> 0.0022802541 | P82: =IFERROR(K82/'Income Statement'!F25,"") -> 0.00085442385 | Q82: =IFERROR(AVERAGE(L82:P82),"") -> 0.0019705954 | R82: Avg % of adjusted revenue | S82: ROUND(Q82*IS_rev,0) | T82: =ROUND(Q82*'Income Statement'!K25,0) -> 99 | U82: =ROUND(Q82*'Income Statement'!L25,0) -> 105 | V82: =ROUND(Q82*'Income Statement'!M25,0) -> 111 | W82: =ROUND(Q82*'Income Statement'!N25,0) -> 117 | X82: =ROUND(Q82*'Income Statement'!O25,0) -> 123
A83: Intangible Assets - Other - Net | D83: -1 | I83: =D83 -> -1 | L83: =IFERROR(G83/'Income Statement'!B25,"") -> 0 | M83: =IFERROR(H83/'Income Statement'!C25,"") -> 0 | N83: =IFERROR(I83/'Income Statement'!D25,"") -> -2.2962113e-05 | O83: =IFERROR(J83/'Income Statement'!E25,"") -> 0 | P83: =IFERROR(K83/'Income Statement'!F25,"") -> 0 | Q83: =IFERROR(AVERAGE(L83:P83),"") -> -4.5924225e-06 | R83: Immaterial/zero balance – not forecast
A84: Intangible Assets - Gross - Total | B84: 6581 | C84: 6796 | D84: 6311 | E84: 6179 | F84: 5011 | G84: =B84 -> 6581 | H84: =C84 -> 6796 | I84: =D84 -> 6311 | J84: =E84 -> 6179 | K84: =F84 -> 5011 | L84: =IFERROR(G84/'Income Statement'!B25,"") -> 0.14400438 | M84: =IFERROR(H84/'Income Statement'!C25,"") -> 0.15379393 | N84: =IFERROR(I84/'Income Statement'!D25,"") -> 0.14491389 | O84: =IFERROR(J84/'Income Statement'!E25,"") -> 0.1677344 | P84: =IFERROR(K84/'Income Statement'!F25,"") -> 0.14763855 | Q84: =IFERROR(AVERAGE(L84:P84),"") -> 0.15161703 | R84: Avg % of adjusted revenue | S84: ROUND(Q84*IS_rev,0) | T84: =ROUND(Q84*'Income Statement'!K25,0) -> 7597 | U84: =ROUND(Q84*'Income Statement'!L25,0) -> 8065 | V84: =ROUND(Q84*'Income Statement'!M25,0) -> 8533 | W84: =ROUND(Q84*'Income Statement'!N25,0) -> 9001 | X84: =ROUND(Q84*'Income Statement'!O25,0) -> 9469
A85: Goodwill/Cost in Excess of Assets Purchased - Gross | B85: 3790 | C85: 4082 | D85: 3846 | E85: 3831 | F85: 3461 | G85: =B85 -> 3790 | H85: =C85 -> 4082 | I85: =D85 -> 3846 | J85: =E85 -> 3831 | K85: =F85 -> 3461 | L85: =IFERROR(G85/'Income Statement'!B25,"") -> 0.082932166 | M85: =IFERROR(H85/'Income Statement'!C25,"") -> 0.092375931 | N85: =IFERROR(I85/'Income Statement'!D25,"") -> 0.088312285 | O85: =IFERROR(J85/'Income Statement'!E25,"") -> 0.10399587 | P85: =IFERROR(K85/'Income Statement'!F25,"") -> 0.10197107 | Q85: =IFERROR(AVERAGE(L85:P85),"") -> 0.093917465 | R85: Avg % of adjusted revenue | S85: ROUND(Q85*IS_rev,0) | T85: =ROUND(Q85*'Income Statement'!K25,0) -> 4706 | U85: =ROUND(Q85*'Income Statement'!L25,0) -> 4996 | V85: =ROUND(Q85*'Income Statement'!M25,0) -> 5285 | W85: =ROUND(Q85*'Income Statement'!N25,0) -> 5575 | X85: =ROUND(Q85*'Income Statement'!O25,0) -> 5865
A86: Intangible Assets - excluding Goodwill - Gross | B86: 2791 | C86: 2714 | D86: 2465 | E86: 2348 | F86: 1550 | G86: =B86 -> 2791 | H86: =C86 -> 2714 | I86: =D86 -> 2465 | J86: =E86 -> 2348 | K86: =F86 -> 1550 | L86: =IFERROR(G86/'Income Statement'!B25,"") -> 0.06107221 | M86: =IFERROR(H86/'Income Statement'!C25,"") -> 0.061418 | N86: =IFERROR(I86/'Income Statement'!D25,"") -> 0.056601607 | O86: =IFERROR(J86/'Income Statement'!E25,"") -> 0.063738531 | P86: =IFERROR(K86/'Income Statement'!F25,"") -> 0.045667482 | Q86: =IFERROR(AVERAGE(L86:P86),"") -> 0.057699566 | R86: Avg % of adjusted revenue | S86: ROUND(Q86*IS_rev,0) | T86: =ROUND(Q86*'Income Statement'!K25,0) -> 2891 | U86: =ROUND(Q86*'Income Statement'!L25,0) -> 3069 | V86: =ROUND(Q86*'Income Statement'!M25,0) -> 3247 | W86: =ROUND(Q86*'Income Statement'!N25,0) -> 3425 | X86: =ROUND(Q86*'Income Statement'!O25,0) -> 3603
A87: Computer Software - Intangible Assets - Gross | B87: 1310 | C87: 1185 | D87: 1013 | E87: 896 | F87: 609 | G87: =B87 -> 1310 | H87: =C87 -> 1185 | I87: =D87 -> 1013 | J87: =E87 -> 896 | K87: =F87 -> 609 | L87: =IFERROR(G87/'Income Statement'!B25,"") -> 0.028665208 | M87: =IFERROR(H87/'Income Statement'!C25,"") -> 0.026816629 | N87: =IFERROR(I87/'Income Statement'!D25,"") -> 0.02326062 | O87: =IFERROR(J87/'Income Statement'!E25,"") -> 0.02432271 | P87: =IFERROR(K87/'Income Statement'!F25,"") -> 0.017942901 | Q87: =IFERROR(AVERAGE(L87:P87),"") -> 0.024201614 | R87: Avg % of adjusted revenue | S87: ROUND(Q87*IS_rev,0) | T87: =ROUND(Q87*'Income Statement'!K25,0) -> 1213 | U87: =ROUND(Q87*'Income Statement'!L25,0) -> 1287 | V87: =ROUND(Q87*'Income Statement'!M25,0) -> 1362 | W87: =ROUND(Q87*'Income Statement'!N25,0) -> 1437 | X87: =ROUND(Q87*'Income Statement'!O25,0) -> 1511
A88: Brands, Patents, Trademarks, Marketing & Artistic Intangibles - Gross | B88: 1355 | C88: 1355 | D88: 1322 | E88: 1321 | F88: 875 | G88: =B88 -> 1355 | H88: =C88 -> 1355 | I88: =D88 -> 1322 | J88: =E88 -> 1321 | K88: =F88 -> 875 | L88: =IFERROR(G88/'Income Statement'!B25,"") -> 0.029649891 | M88: =IFERROR(H88/'Income Statement'!C25,"") -> 0.03066374 | N88: =IFERROR(I88/'Income Statement'!D25,"") -> 0.030355913 | O88: =IFERROR(J88/'Income Statement'!E25,"") -> 0.03585971 | P88: =IFERROR(K88/'Income Statement'!F25,"") -> 0.02578003 | Q88: =IFERROR(AVERAGE(L88:P88),"") -> 0.030461857 | R88: Avg % of adjusted revenue | S88: ROUND(Q88*IS_rev,0) | T88: =ROUND(Q88*'Income Statement'!K25,0) -> 1526 | U88: =ROUND(Q88*'Income Statement'!L25,0) -> 1620 | V88: =ROUND(Q88*'Income Statement'!M25,0) -> 1714 | W88: =ROUND(Q88*'Income Statement'!N25,0) -> 1808 | X88: =ROUND(Q88*'Income Statement'!O25,0) -> 1902
A89: Licenses, Franchises, Copyrights, Property Rights, Prototypes, Contract Based, Models & Designs - Gross | B89: 126 | C89: 174 | D89: 131 | E89: 131 | F89: 66 | G89: =B89 -> 126 | H89: =C89 -> 174 | I89: =D89 -> 131 | J89: =E89 -> 131 | K89: =F89 -> 66 | L89: =IFERROR(G89/'Income Statement'!B25,"") -> 0.0027571116 | M89: =IFERROR(H89/'Income Statement'!C25,"") -> 0.0039376315 | N89: =IFERROR(I89/'Income Statement'!D25,"") -> 0.0030080367 | O89: =IFERROR(J89/'Income Statement'!E25,"") -> 0.0035561105 | P89: =IFERROR(K89/'Income Statement'!F25,"") -> 0.0019445508 | Q89: =IFERROR(AVERAGE(L89:P89),"") -> 0.0030406883 | R89: Avg % of adjusted revenue | S89: ROUND(Q89*IS_rev,0) | T89: =ROUND(Q89*'Income Statement'!K25,0) -> 152 | U89: =ROUND(Q89*'Income Statement'!L25,0) -> 162 | V89: =ROUND(Q89*'Income Statement'!M25,0) -> 171 | W89: =ROUND(Q89*'Income Statement'!N25,0) -> 181 | X89: =ROUND(Q89*'Income Statement'!O25,0) -> 190
A90: Intangible Assets - Other - Gross - Total | D90: -1 | I90: =D90 -> -1 | L90: =IFERROR(G90/'Income Statement'!B25,"") -> 0 | M90: =IFERROR(H90/'Income Statement'!C25,"") -> 0 | N90: =IFERROR(I90/'Income Statement'!D25,"") -> -2.2962113e-05 | O90: =IFERROR(J90/'Income Statement'!E25,"") -> 0 | P90: =IFERROR(K90/'Income Statement'!F25,"") -> 0 | Q90: =IFERROR(AVERAGE(L90:P90),"") -> -4.5924225e-06 | R90: Zero/nil – not forecast
A91: Intangible Assets - Accumulated Amortization & Impairment - Total | B91: 1624 | C91: 1745 | D91: 1619 | E91: 1495 | F91: 1109 | G91: =B91 -> 1624 | H91: =C91 -> 1745 | I91: =D91 -> 1619 | J91: =E91 -> 1495 | K91: =F91 -> 1109 | L91: =IFERROR(G91/'Income Statement'!B25,"") -> 0.035536105 | M91: =IFERROR(H91/'Income Statement'!C25,"") -> 0.039489466 | N91: =IFERROR(I91/'Income Statement'!D25,"") -> 0.03717566 | O91: =IFERROR(J91/'Income Statement'!E25,"") -> 0.040583094 | P91: =IFERROR(K91/'Income Statement'!F25,"") -> 0.032674347 | Q91: =IFERROR(AVERAGE(L91:P91),"") -> 0.037091734 | R91: Avg % of adjusted revenue | S91: ROUND(Q91*IS_rev,0) | T91: =ROUND(Q91*'Income Statement'!K25,0) -> 1858 | U91: =ROUND(Q91*'Income Statement'!L25,0) -> 1973 | V91: =ROUND(Q91*'Income Statement'!M25,0) -> 2087 | W91: =ROUND(Q91*'Income Statement'!N25,0) -> 2202 | X91: =ROUND(Q91*'Income Statement'!O25,0) -> 2316
A92: Goodwill - Accumulated Amortization & Impairment | B92: 302 | C92: 494 | D92: 494 | E92: 494 | F92: 494 | G92: =B92 -> 302 | H92: =C92 -> 494 | I92: =D92 -> 494 | J92: =E92 -> 494 | K92: =F92 -> 494 | L92: =IFERROR(G92/'Income Statement'!B25,"") -> 0.0066083151 | M92: =IFERROR(H92/'Income Statement'!C25,"") -> 0.011179253 | N92: =IFERROR(I92/'Income Statement'!D25,"") -> 0.011343284 | O92: =IFERROR(J92/'Income Statement'!E25,"") -> 0.013410066 | P92: =IFERROR(K92/'Income Statement'!F25,"") -> 0.014554668 | Q92: =IFERROR(AVERAGE(L92:P92),"") -> 0.011419117 | R92: Avg % of adjusted revenue | S92: ROUND(Q92*IS_rev,0) | T92: =ROUND(Q92*'Income Statement'!K25,0) -> 572 | U92: =ROUND(Q92*'Income Statement'!L25,0) -> 607 | V92: =ROUND(Q92*'Income Statement'!M25,0) -> 643 | W92: =ROUND(Q92*'Income Statement'!N25,0) -> 678 | X92: =ROUND(Q92*'Income Statement'!O25,0) -> 713
A93: Intangible Assets - excluding Goodwill - Accumulated Amortization & Impairment - Total | B93: 1322 | C93: 1251 | D93: 1125 | E93: 1001 | F93: 615 | G93: =B93 -> 1322 | H93: =C93 -> 1251 | I93: =D93 -> 1125 | J93: =E93 -> 1001 | K93: =F93 -> 615 | L93: =IFERROR(G93/'Income Statement'!B25,"") -> 0.02892779 | M93: =IFERROR(H93/'Income Statement'!C25,"") -> 0.028310213 | N93: =IFERROR(I93/'Income Statement'!D25,"") -> 0.025832377 | O93: =IFERROR(J93/'Income Statement'!E25,"") -> 0.027173028 | P93: =IFERROR(K93/'Income Statement'!F25,"") -> 0.018119678 | Q93: =IFERROR(AVERAGE(L93:P93),"") -> 0.025672617 | R93: Avg % of adjusted revenue | S93: ROUND(Q93*IS_rev,0) | T93: =ROUND(Q93*'Income Statement'!K25,0) -> 1286 | U93: =ROUND(Q93*'Income Statement'!L25,0) -> 1366 | V93: =ROUND(Q93*'Income Statement'!M25,0) -> 1445 | W93: =ROUND(Q93*'Income Statement'!N25,0) -> 1524 | X93: =ROUND(Q93*'Income Statement'!O25,0) -> 1603
A94: Computer Software - Intangible Assets - Accumulated Amortization & Impairment | B94: 778 | C94: 686 | D94: 572 | E94: 457 | F94: 320 | G94: =B94 -> 778 | H94: =C94 -> 686 | I94: =D94 -> 572 | J94: =E94 -> 457 | K94: =F94 -> 320 | L94: =IFERROR(G94/'Income Statement'!B25,"") -> 0.01702407 | M94: =IFERROR(H94/'Income Statement'!C25,"") -> 0.015524225 | N94: =IFERROR(I94/'Income Statement'!D25,"") -> 0.013134328 | O94: =IFERROR(J94/'Income Statement'!E25,"") -> 0.012405668 | P94: =IFERROR(K94/'Income Statement'!F25,"") -> 0.0094281253 | Q94: =IFERROR(AVERAGE(L94:P94),"") -> 0.013503283 | R94: Avg % of adjusted revenue | S94: ROUND(Q94*IS_rev,0) | T94: =ROUND(Q94*'Income Statement'!K25,0) -> 677 | U94: =ROUND(Q94*'Income Statement'!L25,0) -> 718 | V94: =ROUND(Q94*'Income Statement'!M25,0) -> 760 | W94: =ROUND(Q94*'Income Statement'!N25,0) -> 802 | X94: =ROUND(Q94*'Income Statement'!O25,0) -> 843
A95: Brands, Patents, Trademarks, Marketing & Artistic Intangibles - Accumulated Amortization & Impairment | B95: 516 | C95: 516 | D95: 498 | E95: 497 | F95: 258 | G95: =B95 -> 516 | H95: =C95 -> 516 | I95: =D95 -> 498 | J95: =E95 -> 497 | K95: =F95 -> 258 | L95: =IFERROR(G95/'Income Statement'!B25,"") -> 0.011291028 | M95: =IFERROR(H95/'Income Statement'!C25,"") -> 0.011677114 | N95: =IFERROR(I95/'Income Statement'!D25,"") -> 0.011435132 | O95: =IFERROR(J95/'Income Statement'!E25,"") -> 0.013491503 | P95: =IFERROR(K95/'Income Statement'!F25,"") -> 0.007601426 | Q95: =IFERROR(AVERAGE(L95:P95),"") -> 0.011099241 | R95: Avg % of adjusted revenue | S95: ROUND(Q95*IS_rev,0) | T95: =ROUND(Q95*'Income Statement'!K25,0) -> 556 | U95: =ROUND(Q95*'Income Statement'!L25,0) -> 590 | V95: =ROUND(Q95*'Income Statement'!M25,0) -> 625 | W95: =ROUND(Q95*'Income Statement'!N25,0) -> 659 | X95: =ROUND(Q95*'Income Statement'!O25,0) -> 693
A96: Licenses, Franchises, Copy/Property Rights, Prototypes, Contract Based, Models & Designs - Accumulated Amortization & Impairment | B96: 28 | C96: 49 | D96: 55 | E96: 47 | F96: 37 | G96: =B96 -> 28 | H96: =C96 -> 49 | I96: =D96 -> 55 | J96: =E96 -> 47 | K96: =F96 -> 37 | L96: =IFERROR(G96/'Income Statement'!B25,"") -> 0.00061269147 | M96: =IFERROR(H96/'Income Statement'!C25,"") -> 0.0011088732 | N96: =IFERROR(I96/'Income Statement'!D25,"") -> 0.0012629162 | O96: =IFERROR(J96/'Income Statement'!E25,"") -> 0.0012758565 | P96: =IFERROR(K96/'Income Statement'!F25,"") -> 0.001090127 | Q96: =IFERROR(AVERAGE(L96:P96),"") -> 0.0010700929 | R96: Avg % of adjusted revenue | S96: ROUND(Q96*IS_rev,0) | T96: =ROUND(Q96*'Income Statement'!K25,0) -> 54 | U96: =ROUND(Q96*'Income Statement'!L25,0) -> 57 | V96: =ROUND(Q96*'Income Statement'!M25,0) -> 60 | W96: =ROUND(Q96*'Income Statement'!N25,0) -> 64 | X96: =ROUND(Q96*'Income Statement'!O25,0) -> 67
A97: Total Non-Current Assets | B97: =B37+B39+B40+B41+B73+B77 -> 18048 | C97: =C37+C39+C40+C41+C73+C77 -> 17895 | D97: =D37+D39+D40+D41+D73+D77 -> 17392 | E97: =E37+E39+E40+E41+E73+E77 -> 17687 | F97: =F37+F39+F40+F41+F73+F77 -> 17118 | G97: =G37+G39+G40+G41+G73+G77 -> 13929 | H97: =H37+H39+H40+H41+H73+H77 -> 13666 | I97: =I37+I39+I40+I41+I73+I77 -> 13416 | ... K97: =K37+K39+K40+K41+K73+K77 -> 13538 | L97: =IFERROR(G97/'Income Statement'!B25,"") -> 0.30479212 | M97: =IFERROR(H97/'Income Statement'!C25,"") -> 0.30926249 | N97: =IFERROR(I97/'Income Statement'!D25,"") -> 0.3080597 | O97: =IFERROR(J97/'Income Statement'!E25,"") -> 0.37377165 | P97: =IFERROR(K97/'Income Statement'!F25,"") -> 0.39886862 | Q97: =IFERROR(AVERAGE(L97:P97),"") -> 0.33895092 | R97: SUM: Investments + Derivatives + PPE + Other NCA + Intangibles | S97: T37+T39+T40+T41+T73+T77 | T97: =T37+T39+T40+T41+T73+T77 -> 14477 | U97: =U37+U39+U40+U41+U73+U77 -> 15179 | V97: =V37+V39+V40+V41+V73+V77 -> 15934 | W97: =W37+W39+W40+W41+W73+W77 -> 16733 | X97: =X37+X39+X40+X41+X73+X77 -> 17572
A98: Total Assets
A99: Total Assets | B99: =B35+B97 -> 27981 | C99: =C35+C97 -> 27309 | D99: =D35+D97 -> 26546 | E99: =E35+E97 -> 27286 | F99: =F35+F97 -> 26214 | G99: =G35+G97 -> 23862 | H99: =H35+H97 -> 23080 | I99: =I35+I97 -> 22570 | ... K99: =K35+K97 -> 22634 | L99: =IFERROR(G99/'Income Statement'!B25,"") -> 0.52214442 | M99: =IFERROR(H99/'Income Statement'!C25,"") -> 0.52230193 | N99: =IFERROR(I99/'Income Statement'!D25,"") -> 0.51825488 | O99: =IFERROR(J99/'Income Statement'!E25,"") -> 0.63434497 | P99: =IFERROR(K99/'Income Statement'!F25,"") -> 0.66686309 | Q99: =IFERROR(AVERAGE(L99:P99),"") -> 0.57278186 | R99: Total Current Assets + Total Non-Current Assets | S99: T35+T97 | T99: =T35+T97 -> 27227 | U99: =U35+U97 -> 28725 | V99: =V35+V97 -> 30249 | W99: =W35+W97 -> 31798 | X99: =X35+X97 -> 33371
A100: Current Liabilities
A101: Trade Accounts Payable & Accruals - Short-Term | B101: 6364 | C101: 6317 | D101: 6137 | E101: 6262 | F101: 5123 | G101: =B101 -> 6364 | H101: =C101 -> 6317 | I101: =D101 -> 6137 | J101: =E101 -> 6262 | K101: =F101 -> 5123 | L101: =IFERROR(G101/'Income Statement'!B25,"") -> 0.13925602 | M101: =IFERROR(H101/'Income Statement'!C25,"") -> 0.14295413 | N101: =IFERROR(I101/'Income Statement'!D25,"") -> 0.14091848 | O101: =IFERROR(J101/'Income Statement'!E25,"") -> 0.16998751 | P101: =IFERROR(K101/'Income Statement'!F25,"") -> 0.15093839 | Q101: =IFERROR(AVERAGE(L101:P101),"") -> 0.14881091 | R101: Avg % of adjusted revenue | S101: ROUND(Q101*IS_rev,0) | T101: =ROUND(Q101*'Income Statement'!K25,0) -> 7456 | U101: =ROUND(Q101*'Income Statement'!L25,0) -> 7915 | V101: =ROUND(Q101*'Income Statement'!M25,0) -> 8375 | W101: =ROUND(Q101*'Income Statement'!N25,0) -> 8834 | X101: =ROUND(Q101*'Income Statement'!O25,0) -> 9294
...

Sheet Dividend Analysis
A2: Year | B2: Earnings/Net Income | C2: Retained Earnings(t-1) | D2: Retained Earnings(t) | E2: Dividend Distribution | F2: Dividend Payout Ratio | G2: Retention Ratio
A3: 2021 | B3: ='Income Statement'!F79 -> 2380 | C3: -10085 | D3: ='Balance Sheet'!K137 -> -9724 | E3: =B3+C3-D3 -> 2019 | F3: =E3/B3 -> 0.84831933 | G3: =1-F3 -> 0.15168067
A4: 2022 | B4: ='Income Statement'!E79 -> 2352 | C4: ='Balance Sheet'!K137 -> -9724 | D4: ='Balance Sheet'!J137 -> -9637 | E4: =B4+C4-D4 -> 2265 | F4: =E4/B4 -> 0.9630102 | G4: =1-F4 -> 0.036989796
A5: 2023 | B5: ='Income Statement'!D79 -> 2465 | C5: ='Balance Sheet'!J137 -> -9637 | D5: ='Balance Sheet'!I137 -> -9369 | E5: =B5+C5-D5 -> 2197 | F5: =E5/B5 -> 0.89127789 | G5: =1-F5 -> 0.10872211
A6: 2024 | B6: ='Income Statement'!C79 -> 2557 | C6: ='Balance Sheet'!I137 -> -9369 | D6: ='Balance Sheet'!H137 -> -9267 | E6: =B6+C6-D6 -> 2455 | F6: =E6/B6 -> 0.9601095 | G6: =1-F6 -> 0.039890497
A7: 2025 | B7: ='Income Statement'!B79 -> 2926 | C7: ='Balance Sheet'!H137 -> -9267 | D7: ='Balance Sheet'!G137 -> -8522 | E7: =B7+C7-D7 -> 2181 | F7: =E7/B7 -> 0.74538619 | G7: =1-F7 -> 0.25461381
E8: Average | F8: =AVERAGE(F3:F7) -> 0.88162062 | G8: =1-F8 -> 0.11837938
A10: 2026 | B10: ='Income Statement'!K79 -> 3098 | C10: ='Balance Sheet'!G137 -> -8522 | D10: =B10+C10-E10 -> -8155.2607 | E10: =B10*F10 -> 2731.2607 | F10: =$F$8 -> 0.88162062 | G10: =1-F10 -> 0.11837938
A11: 2027 | B11: ='Income Statement'!L79 -> 3365 | C11: ='Balance Sheet'!T137 -> -8155 | D11: =B11+C11-E11 -> -7756.6534 | E11: =B11*F11 -> 2966.6534 | F11: =$F$8 -> 0.88162062 | G11: =1-F11 -> 0.11837938
A12: 2028 | B12: ='Income Statement'!M79 -> 3577 | C12: ='Balance Sheet'!U137 -> -7757 | D12: =B12+C12-E12 -> -7333.557 | E12: =B12*F12 -> 3153.557 | F12: =$F$8 -> 0.88162062 | G12: =1-F12 -> 0.11837938
A13: 2029 | B13: ='Income Statement'!N79 -> 3786 | C13: ='Balance Sheet'!V137 -> -7333 | D13: =B13+C13-E13 -> -6884.8157 | E13: =B13*F13 -> 3337.8157 | F13: =$F$8 -> 0.88162062 | G13: =1-F13 -> 0.11837938
A14: 2030 | B14: ='Income Statement'!O79 -> 3998 | C14: ='Balance Sheet'!W137 -> -6885 | D14: =B14+C14-E14 -> -6411.7193 | E14: =B14*F14 -> 3524.7193 | F14: =$F$8 -> 0.88162062 | G14: =1-F14 -> 0.11837938
B17: Note: The dividend payout ratio is calculated as total dividends paid divided by adjusted NPAT each year. Payout ratios are capped at a maximum of 100% and floored at a minimum of 0% per assignment instructions. The average historical payout ratio of 88.16% is applied uniformly to all forecast years 2026–2030.

Sheet Revenue Forecast
A1: Year | B1: Nominal Operating Revenue | C1: CPI | D1: Real Operating Revenue | E1: Real GDP (in $ millions) | F1: Population Growth Rate (%)
A2: 1995 | B2: 2512.7 | C2: 66 | D2: =(B2*$C$32)/C2 -> 5482.2545 | E2: 281218 | F2: 1.11
A3: 1996 | B3: 2513.03 | C3: 67 | D3: =(B3*$C$32)/C3 -> 5401.1391 | E3: 292390 | F3: 1.21 | H3: SUMMARY OUTPUT
A4: 1997 | B4: 2709.52 | C4: 66.8 | D4: =(B4*$C$32)/C4 -> 5840.8814 | E4: 306170 | F4: 1.08
A5: 1998 | B5: 2822.77 | C5: 67.8 | D5: =(B5*$C$32)/C5 -> 5995.2637 | E5: 320472 | F5: 1 | H5: Regression Statistics
A6: 1999 | B6: 3119.46 | C6: 69.1 | D6: =(B6*$C$32)/C6 -> 6500.756 | E6: 334691 | F6: 1.09 | H6: Multiple R | I6: 0.65626381
A7: 2000 | B7: 3480.16 | C7: 73.1 | D7: =(B7*$C$32)/C7 -> 6855.5819 | E7: 345063 | F7: 1.14 | H7: R Square | I7: 0.43068219
A8: 2001 | B8: 4388.65 | C8: 75.4 | D8: =(B8*$C$32)/C8 -> 8381.5066 | E8: 354037 | F8: 1.28 | H8: Adjusted R Square | I8: 0.39001663
A9: 2002 | B9: 7385.66 | C9: 77.6 | D9: =(B9*$C$32)/C9 -> 13705.348 | E9: 368762 | F9: 1.14 | H9: Standard Error | I9: 23599.078
A10: 2003 | B10: 7753.37 | C10: 79.5 | D10: =(B10*$C$32)/C10 -> 14043.84 | E10: 379882 | F10: 1.15 | H10: Observations | I10: 31
A11: 2004 | B11: 8407.49 | C11: 81.5 | D11: =(B11*$C$32)/C11 -> 14854.952 | E11: 395507 | F11: 1.07
A12: 2005 | B12: 8158.63 | C12: 83.8 | D12: =(B12*$C$32)/C12 -> 14019.603 | E12: 407488 | F12: 1.22 | H12: ANOVA
A13: 2006 | B13: 8858.8 | C13: 86.6 | D13: =(B13*$C$32)/C13 -> 14730.568 | E13: 418165 | F13: 1.35 | I13: df | J13: SS | K13: MS | L13: F | M13: Significance F
A14: 2007 | B14: 9754 | C14: 89.1 | D14: =(B14*$C$32)/C14 -> 15764.04 | E14: 436310 | F14: 1.82 | H14: Regression | I14: 2 | J14: 1.1796421e+10 | K14: 5.8982103e+09 | L14: 10.590834 | M14: 0.00037580866
A15: 2008 | B15: 33584 | C15: 92.4 | D15: =(B15*$C$32)/C15 -> 52338.701 | E15: 447630 | F15: 2 | H15: Residual | I15: 28 | J15: 1.5593662e+10 | K15: 5.5691649e+08
A16: 2009 | B16: 50982 | C16: 94.3 | D16: =(B16*$C$32)/C16 -> 77851.622 | E16: 456424 | F16: 2.06 | H16: Total | I16: 30 | J16: 2.7390082e+10
A17: 2010 | B17: 51827 | C17: 96.9 | D17: =(B17*$C$32)/C17 -> 77018.452 | E17: 467465 | F17: 1.56
A18: 2011 | B18: 54875 | C18: 99.8 | D18: =(B18*$C$32)/C18 -> 79178.357 | E18: 480487 | F18: 1.39 | I18: Coefficients | J18: Standard Error | K18: t Stat | L18: P-value | M18: Lower 95% | N18: Upper 95% | O18: Lower 95.0% | P18: Upper 95.0%
A19: 2012 | B19: 58080 | C19: 102 | D19: =(B19*$C$32)/C19 -> 81995.294 | E19: 498692 | F19: 1.75 | H19: Intercept | I19: -49767.912 | J19: 19958.437 | K19: -2.4935776 | L19: 0.018826301 | M19: -90650.918 | N19: -8884.9063 | O19: -90650.918 | P19: -8884.9063
A20: 2013 | B20: 57749 | C20: 104.8 | D20: =(B20*$C$32)/C20 -> 79349.771 | E20: 509758 | F20: 1.72 | H20: Real GDP (in $ millions) | I20: 0.12763112 | J20: 0.039992641 | K20: 3.1913651 | L20: 0.0034803171 | M20: 0.045709909 | N20: 0.20955233 | O20: 0.045709909 | P20: 0.20955233
A21: 2014 | B21: 60181 | C21: 106.6 | D21: =(B21*$C$32)/C21 -> 81295.159 | E21: 522882 | F21: 1.49 | H21: Population Growth Rate (%) | I21: 20807.11 | J21: 11055.7 | K21: 1.8820255 | L21: 0.070264748 | M21: -1839.4659 | N21: 43453.685 | O21: -1839.4659 | P21: 43453.685
A22: 2015 | B22: 62447 | C22: 108.4 | D22: =(B22*$C$32)/C22 -> 82955.424 | E22: 535118 | F22: 1.44
A23: 2016 | B23: 65981 | C23: 110 | D23: =(B23*$C$32)/C23 -> 86375.127 | E23: 549536 | F23: 1.56
A24: 2017 | B24: 64913 | C24: 112.1 | D24: =(B24*$C$32)/C24 -> 83385.12 | E24: 562614 | F24: 1.65
A25: 2018 | B25: 26763 | C25: 114.1 | D25: =(B25*$C$32)/C25 -> 33776.266 | E25: 578318 | F25: 1.5
A26: 2019 | B26: 27920 | C26: 116.2 | D26: =(B26*$C$32)/C26 -> 34599.656 | E26: 589512 | F26: 1.48
A27: 2020 | B27: 30846 | C27: 117.2 | D27: =(B27*$C$32)/C27 -> 37899.522 | E27: 577992 | F27: 1.23
A28: 2021 | B28: 33941 | C28: 121.3 | D28: =(B28*$C$32)/C28 -> 40292.696 | E28: 609318 | F28: 0.14
A29: 2022 | B29: 36838 | C29: 130.8 | D29: =(B29*$C$32)/C29 -> 40555.596 | E29: 634519 | F29: 1.27
A30: 2023 | B30: 43550 | C30: 136.1 | D30: =(B30*$C$32)/C30 -> 46077.884 | E30: 647548 | F30: 2.42
A31: 2024 | B31: 44189 | C31: 139.4 | D31: =(B31*$C$32)/C31 -> 45647.174 | E31: 654212 | F31: 2.05
A32: 2025 | B32: 45700 | C32: 144 | D32: =(B32*$C$32)/C32 -> 45700 | E32: 656388 | F32: 1.6
H34: Macroeconomic Assumptions
H35: Year | I35: Growth % | J35: Population Growth Rate (%)
A36: Year | B36: Real GDP (in $ millions) | C36: Population Growth Rate (%) | D36: Real Operating Revenue | E36: Inflation (%) | F36: Nominal Operating Revenue | H36: 2021 | I36: 5.42 | J36: 0.14
A37: 2026 | B37: =E32*I43 -> 673414.7 | C37: =J$41 -> 1.496 | D37: =I19+(I20*B37)+(I21*C37) -> 67308.198 | E37: 2.5 | F37: =D37*E43 -> 68990.903 | H37: 2022 | I37: 4.14 | J37: 1.27
A38: 2027 | B38: =B37*I43 -> 690883.08 | C38: =J$41 -> 1.496 | D38: =I19+(I20*B38)+(I21*C38) -> 69537.706 | E38: 2.5 | F38: =D38*E43 -> 71276.149 | H38: 2023 | I38: 2.05 | J38: 2.42
A39: 2028 | B39: =B38*I43 -> 708804.59 | C39: =J$41 -> 1.496 | D39: =I19+(I20*B39)+(I21*C39) -> 71825.048 | E39: 2.5 | F39: =D39*E43 -> 73620.674 | H39: 2024 | I39: 1.03 | J39: 2.05
A40: 2029 | B40: =B39*I43 -> 727190.98 | C40: =J$41 -> 1.496 | D40: =I19+(I20*B40)+(I21*C40) -> 74171.724 | E40: 2.5 | F40: =D40*E43 -> 76026.017 | H40: 2025 | I40: 0.33 | J40: 1.6
A41: 2030 | B41: =B40*I43 -> 746054.31 | C41: =J$41 -> 1.496 | D41: =I19+(I20*B41)+(I21*C41) -> 76579.272 | E41: 2.5 | F41: =D41*E43 -> 78493.754 | H41: Average | I41: =AVERAGE(I36:I40) -> 2.594 | J41: =AVERAGE(J36:J40) -> 1.496
D42: ke | E42: 0.025 | H42: g | I42: 0.02594
D43: 1+ke | E43: 1.025 | H43: 1+g | I43: 1.02594
B47: Note
B48: 1: Nominal revenues were deflated using the CPI values provided by the RBA to obtain real revenues.
B49: 2: We forecasted revenues using a regression model with two macroeconomic drivers — Real GDP and Population Growth Rate — obtained from the RBA. The model was estimated using data from 1995 to 2025 and used to project revenues for FY2026–2030.
B50: 3: Macroeconomic assumptions: Real GDP growth of 2.594% per annum and population growth of 1.496% per annum, based on the past five-year average. Inflation of 2.5% per annum, consistent with the RBA's medium-term target band of 2–3%.
B51: 4: The R² of 0.431 is moderate. Real GDP is statistically significant (p-value = 0.0035) confirming a meaningful relationship with Wesfarmers' revenues. Population Growth is marginally significant (p-value = 0.070) but was retained given its economic relevance as a key driver of retail demand. Overall we consider the regression results reliable enough to use for forecasting purposes.

Sheet FCFE & FCFF
A1: Valuation of FCFE | B1: 2026 | C1: 2027 | D1: 2028 | E1: 2029 | F1: 2030 | H1: Valuation of FCFE | I1: 2026 | J1: 2027 | K1: 2028 | L1: 2029 | M1: 2030
A2: Earnings | B2: ='Income Statement'!K79 -> 3098 | C2: ='Income Statement'!L79 -> 3365 | D2: ='Income Statement'!M79 -> 3577 | E2: ='Income Statement'!N79 -> 3786 | F2: ='Income Statement'!O79 -> 3998 | H2: FCFE | I2: =B8 -> 3153 | J2: =C8 -> 3079 | K2: =D8 -> 3250 | L2: =E8 -> 3427 | M2: =F8 -> 3613
A3: NCC | B3: ='Income Statement'!K29+'Income Statement'!K30 -> 1790 | C3: ='Income Statement'!L29+'Income Statement'!L30 -> 1868 | D3: ='Income Statement'!M29+'Income Statement'!M30 -> 1956 | E3: ='Income Statement'!N29+'Income Statement'!N30 -> 2050 | F3: ='Income Statement'!O29+'Income Statement'!O30 -> 2151 | H3: D/E | I3: =('Balance Sheet'!T116+'Balance Sheet'!T104)/'Balance Sheet'!T142 -> 1.0746735 | J3: =('Balance Sheet'!U116+'Balance Sheet'!U104)/'Balance Sheet'!U142 -> 1.0215938 | K3: =('Balance Sheet'!V116+'Balance Sheet'!V104)/'Balance Sheet'!V142 -> 0.97108164 | L3: =('Balance Sheet'!W116+'Balance Sheet'!W104)/'Balance Sheet'!W142 -> 0.92381094 | M3: =('Balance Sheet'!X116+'Balance Sheet'!X104)/'Balance Sheet'!X142 -> 0.87938719
A4: WCInv | B4: ='Balance Sheet'!T35-'Balance Sheet'!T20-'Balance Sheet'!T113+'Balance Sheet'!T104-(('Balance Sheet'!G35-'Balance Sheet'!G20-'Balance Sheet'!G113+'Balance Sheet'!G104)) -> -316 | C4: ='Balance Sheet'!U35-'Balance Sheet'!U20-'Balance Sheet'!U113+'Balance Sheet'!U104-(('Balance Sheet'!T35-'Balance Sheet'!T20-'Balance Sheet'!T113+'Balance Sheet'!T104)) -> 110 | D4: ='Balance Sheet'!V35-'Balance Sheet'!V20-'Balance Sheet'!V113+'Balance Sheet'!V104-(('Balance Sheet'!U35-'Balance Sheet'!U20-'Balance Sheet'!U113+'Balance Sheet'!U104)) -> 111 | E4: ='Balance Sheet'!W35-'Balance Sheet'!W20-'Balance Sheet'!W113+'Balance Sheet'!W104-(('Balance Sheet'!V35-'Balance Sheet'!V20-'Balance Sheet'!V113+'Balance Sheet'!V104)) -> 111 | F4: ='Balance Sheet'!X35-'Balance Sheet'!X20-'Balance Sheet'!X113+'Balance Sheet'!X104-(('Balance Sheet'!W35-'Balance Sheet'!W20-'Balance Sheet'!W113+'Balance Sheet'!W104)) -> 110 | H4: Unlevered beta | I4: 0.5007 | J4: 0.5007 | K4: 0.5007 | L4: 0.5007 | M4: 0.5007
A5: FCInv | B5: ='Balance Sheet'!T41-'Balance Sheet'!G41+'Income Statement'!K30 -> 2064 | C5: ='Balance Sheet'!U41-'Balance Sheet'!T41+'Income Statement'!L30 -> 2191 | D5: ='Balance Sheet'!V41-'Balance Sheet'!U41+'Income Statement'!M30 -> 2319 | E5: ='Balance Sheet'!W41-'Balance Sheet'!V41+'Income Statement'!N30 -> 2446 | F5: ='Balance Sheet'!X41-'Balance Sheet'!W41+'Income Statement'!O30 -> 2573 | H5: Levered Beta | I5: =0.5007*(1+0.7103*('Balance Sheet'!T116+'Balance Sheet'!T104)/'Balance Sheet'!T142) -> 0.88290464 | J5: =0.5007*(1+0.7103*('Balance Sheet'!U116+'Balance Sheet'!U104)/'Balance Sheet'!U142) -> 0.864027 | K5: =0.5007*(1+0.7103*('Balance Sheet'!V116+'Balance Sheet'!V104)/'Balance Sheet'!V142) -> 0.84606248 | L5: =0.5007*(1+0.7103*('Balance Sheet'!W116+'Balance Sheet'!W104)/'Balance Sheet'!W142) -> 0.82925078 | M5: =0.5007*(1+0.7103*('Balance Sheet'!X116+'Balance Sheet'!X104)/'Balance Sheet'!X142) -> 0.8134516
A6: Net Borrowing | B6: =('Balance Sheet'!T116+'Balance Sheet'!T104)-('Balance Sheet'!G116+'Balance Sheet'!G104) -> -25 | C6: =('Balance Sheet'!U116+'Balance Sheet'!U104)-('Balance Sheet'!T116+'Balance Sheet'!T104) -> 118 | D6: =('Balance Sheet'!V116+'Balance Sheet'!V104)-('Balance Sheet'!U116+'Balance Sheet'!U104) -> 117 | E6: =('Balance Sheet'!W116+'Balance Sheet'!W104)-('Balance Sheet'!V116+'Balance Sheet'!V104) -> 118 | F6: =('Balance Sheet'!X116+'Balance Sheet'!X104)-('Balance Sheet'!W116+'Balance Sheet'!W104) -> 118 | H6: Risk-free rate | I6: 0.02709 | J6: 0.02709 | K6: 0.02709 | L6: 0.02709 | M6: 0.02709
A7: Other NCL | B7: ='Balance Sheet'!T120-'Balance Sheet'!G120 -> 38 | C7: ='Balance Sheet'!U120-'Balance Sheet'!T120 -> 29 | D7: ='Balance Sheet'!V120-'Balance Sheet'!U120 -> 30 | E7: ='Balance Sheet'!W120-'Balance Sheet'!V120 -> 30 | F7: ='Balance Sheet'!X120-'Balance Sheet'!W120 -> 29 | H7: Risk premium | I7: 0.07733 | J7: 0.07733 | K7: 0.07733 | L7: 0.07733 | M7: 0.07733
A8: FCFE | B8: =B2+B3-B4-B5+B6+B7 -> 3153 | C8: =C2+C3-C4-C5+C6+C7 -> 3079 | D8: =D2+D3-D4-D5+D6+D7 -> 3250 | E8: =E2+E3-E4-E5+E6+E7 -> 3427 | F8: =F2+F3-F4-F5+F6+F7 -> 3613 | H8: Cost of equity | I8: =I6+I5*I7 -> 0.095365016 | J8: =J6+J5*J7 -> 0.093905208 | K8: =K6+K5*K7 -> 0.092516011 | L8: =L6+L5*L7 -> 0.091215963 | M8: =M6+M5*M7 -> 0.089994212
A9: Duality of FCFE | B9: ='Balance Sheet'!G142+'Income Statement'!K79-'Balance Sheet'!T142 -> 2731 | C9: ='Balance Sheet'!T142+'Income Statement'!L79-'Balance Sheet'!U142 -> 2967 | D9: ='Balance Sheet'!U142+'Income Statement'!M79-'Balance Sheet'!V142 -> 3153 | E9: ='Balance Sheet'!V142+'Income Statement'!N79-'Balance Sheet'!W142 -> 3338 | F9: ='Balance Sheet'!W142+'Income Statement'!O79-'Balance Sheet'!X142 -> 3525 | H9: Present value | I9: =I2/(1+I8)^1 -> 2878.4925 | J9: =J2/(1+J8)^2 -> 2573.0623 | K9: =K2/(1+K8)^3 -> 2492.2978 | L9: =L2/(1+L8)^4 -> 2416.97 | M9: =M2/(1+M8)^5 -> 2348.2644
H10: Long-term growth rate | I10: 0.0125 | J10: 0.0125 | K10: 0.0125 | L10: 0.0125 | M10: 0.0125
H11: Terminal value | N11: =M2*(1+M10)/(M8-M10) -> 47205.622
A12: Valuation of FCFF | B12: 2026 | C12: 2027 | D12: 2028 | E12: 2029 | F12: 2030 | H12: PVTV | N12: =N11/(1+M8)^5 -> 30681.23
A13: Earnings | B13: ='Income Statement'!K79 -> 3098 | C13: ='Income Statement'!L79 -> 3365 | D13: ='Income Statement'!M79 -> 3577 | E13: ='Income Statement'!N79 -> 3786 | F13: ='Income Statement'!O79 -> 3998 | H13: Total Present Value of Equity | N13: =SUM(I9:M9)+N12 -> 43390.317
A14: NCC | B14: ='Income Statement'!K29+'Income Statement'!K30 -> 1790 | C14: ='Income Statement'!L29+'Income Statement'!L30 -> 1868 | D14: ='Income Statement'!M29+'Income Statement'!M30 -> 1956 | E14: ='Income Statement'!N29+'Income Statement'!N30 -> 2050 | F14: ='Income Statement'!O29+'Income Statement'!O30 -> 2151 | H14: Number of Shares (m) | N14: 1140
A15: WCInv | B15: ='Balance Sheet'!T35-'Balance Sheet'!T20-'Balance Sheet'!T113+'Balance Sheet'!T104-(('Balance Sheet'!G35-'Balance Sheet'!G20-'Balance Sheet'!G113+'Balance Sheet'!G104)) -> -316 | C15: ='Balance Sheet'!U35-'Balance Sheet'!U20-'Balance Sheet'!U113+'Balance Sheet'!U104-(('Balance Sheet'!T35-'Balance Sheet'!T20-'Balance Sheet'!T113+'Balance Sheet'!T104)) -> 110 | D15: ='Balance Sheet'!V35-'Balance Sheet'!V20-'Balance Sheet'!V113+'Balance Sheet'!V104-(('Balance Sheet'!U35-'Balance Sheet'!U20-'Balance Sheet'!U113+'Balance Sheet'!U104)) -> 111 | E15: ='Balance Sheet'!W35-'Balance Sheet'!W20-'Balance Sheet'!W113+'Balance Sheet'!W104-(('Balance Sheet'!V35-'Balance Sheet'!V20-'Balance Sheet'!V113+'Balance Sheet'!V104)) -> 111 | F15: ='Balance Sheet'!X35-'Balance Sheet'!X20-'Balance Sheet'!X113+'Balance Sheet'!X104-(('Balance Sheet'!W35-'Balance Sheet'!W20-'Balance Sheet'!W113+'Balance Sheet'!W104)) -> 110 | H15: Price per Share ($) | N15: =N13/N14 -> 38.061682
A16: FCInv | B16: ='Balance Sheet'!T41-'Balance Sheet'!G41+'Income Statement'!K30 -> 2064 | C16: ='Balance Sheet'!U41-'Balance Sheet'!T41+'Income Statement'!L30 -> 2191 | D16: ='Balance Sheet'!V41-'Balance Sheet'!U41+'Income Statement'!M30 -> 2319 | E16: ='Balance Sheet'!W41-'Balance Sheet'!V41+'Income Statement'!N30 -> 2446 | F16: ='Balance Sheet'!X41-'Balance Sheet'!W41+'Income Statement'!O30 -> 2573 | H16: Market price as at 01/07/25 | N16: 73.47
A17: Interest (1-T) | B17: =ROUND('Income Statement'!K50*0.7103,0) -> 329 | C17: =ROUND('Income Statement'!L50*0.7103,0) -> 274 | D17: =ROUND('Income Statement'!M50*0.7103,0) -> 274 | E17: =ROUND('Income Statement'!N50*0.7103,0) -> 274 | F17: =ROUND('Income Statement'!O50*0.7103,0) -> 274 | H17: Recommendation buy/ sell/ hold | N17: =IF(N15>N16,"BUY","SELL") -> SELL
A18: Other NCL | B18: ='Balance Sheet'!T120-'Balance Sheet'!G120 -> 38 | C18: ='Balance Sheet'!U120-'Balance Sheet'!T120 -> 29 | D18: ='Balance Sheet'!V120-'Balance Sheet'!U120 -> 30 | E18: ='Balance Sheet'!W120-'Balance Sheet'!V120 -> 30 | F18: ='Balance Sheet'!X120-'Balance Sheet'!W120 -> 29 | H18: Cost of equity | I18: =I8 -> 0.095365016 | J18: =J8 -> 0.093905208 | K18: =K8 -> 0.092516011 | L18: =L8 -> 0.091215963 | M18: =M8 -> 0.089994212
A19: FCFF | B19: =B13+B14-B15-B16+B17+B18 -> 3507 | C19: =C13+C14-C15-C16+C17+C18 -> 3235 | D19: =D13+D14-D15-D16+D17+D18 -> 3407 | E19: =E13+E14-E15-E16+E17+E18 -> 3583 | F19: =F13+F14-F15-F16+F17+F18 -> 3769 | H19: E(Equity) | I19: 5437 | J19: 5835 | K19: 6259 | L19: 6707 | M19: 7180
A20: Duality of FCFF | B20: ='Balance Sheet'!G142+'Balance Sheet'!G116+'Balance Sheet'!G104+'Income Statement'!K79+ROUND('Income Statement'!K50*0.7103,0)-('Balance Sheet'!T142+'Balance Sheet'!T116+'Balance Sheet'!T104) -> 3085 | C20: ='Balance Sheet'!T142+'Balance Sheet'!T116+'Balance Sheet'!T104+'Income Statement'!L79+ROUND('Income Statement'!L50*0.7103,0)-('Balance Sheet'!U142+'Balance Sheet'!U116+'Balance Sheet'!U104) -> 3123 | D20: ='Balance Sheet'!U142+'Balance Sheet'!U116+'Balance Sheet'!U104+'Income Statement'!M79+ROUND('Income Statement'!M50*0.7103,0)-('Balance Sheet'!V142+'Balance Sheet'!V116+'Balance Sheet'!V104) -> 3310 | E20: ='Balance Sheet'!V142+'Balance Sheet'!V116+'Balance Sheet'!V104+'Income Statement'!N79+ROUND('Income Statement'!N50*0.7103,0)-('Balance Sheet'!W142+'Balance Sheet'!W116+'Balance Sheet'!W104) -> 3494 | F20: ='Balance Sheet'!W142+'Balance Sheet'!W116+'Balance Sheet'!W104+'Income Statement'!O79+ROUND('Income Statement'!O50*0.7103,0)-('Balance Sheet'!X142+'Balance Sheet'!X116+'Balance Sheet'!X104) -> 3681 | H20: D (Total Debt) | I20: 5843 | J20: 5961 | K20: 6708 | L20: 6196 | M20: 6314
H21: V = E + D | I21: =I19+I20 -> 11280 | J21: =J19+J20 -> 11796 | K21: =K19+K20 -> 12967 | L21: =L19+L20 -> 12903 | M21: =M19+M20 -> 13494
H22: E/V | I22: =I19/I21 -> 0.48200355 | J22: =J19/J21 -> 0.49465921 | K22: =K19/K21 -> 0.48268682 | L22: =L19/L21 -> 0.5198016 | M22: =M19/M21 -> 0.53208834
H23: D/V | I23: =I20/I21 -> 0.51799645 | J23: =J20/J21 -> 0.50534079 | K23: =K20/K21 -> 0.51731318 | L23: =L20/L21 -> 0.4801984 | M23: =M20/M21 -> 0.46791166
H24: Cost of Debt(Kd) | I24: 0.0335 | J24: 0.0335 | K24: 0.0335 | L24: 0.0335 | M24: 0.0335
H25: Tax Rate | I25: 0.2908 | J25: 0.2931 | K25: 0.2954 | L25: 0.2977 | M25: 0.3
H26: WACC | I26: =(I22*I18)+(I23*I24*(1-I25)) -> 0.058272939 | J26: =(J22*J18)+(J23*J24*(1-J25)) -> 0.058418127 | K26: =(K22*K18)+(K23*K24*(1-K25)) -> 0.056866971 | L26: =(L22*L18)+(L23*L24*(1-L25)) -> 0.058711855 | M26: =(M22*M18)+(M23*M24*(1-M25)) -> 0.058857399
H27: Long-term growth rate | I27: 0.0125 | J27: 0.0125 | K27: 0.0125 | L27: 0.0125 | M27: 0.0125
H28: YEAR | I28: t | J28: FCFF | K28: PV of Each years FCFF
H29: 2026 | I29: 1 | J29: =B19 -> 3507 | K29: =J29/(1+I26)^1 -> 3313.8899
H30: 2027 | I30: 2 | J30: =C19 -> 3235 | K30: =J30/(1+J26)^2 -> 2887.751
H31: 2028 | I31: 3 | J31: =D19 -> 3407 | K31: =J31/(1+K26)^3 -> 2886.0985
H32: 2029 | I32: 4 | J32: =E19 -> 3583 | K32: =J32/(1+L26)^4 -> 2851.9093
H33: 2030 | I33: 5 | J33: =F19 -> 3769 | K33: =J33/(1+M26)^5 -> 2831.6447
H34: Terminal Value | K34: =J33*(1+0.0125)/(M26-0.0125) -> 82319.383
H35: PVTV | K35: =K34/(1+M26)^5 -> 61846.443
H36: Total Present Value of Firm | K36: =K29+K30+K31+K32+K33+K35 -> 76617.737
H37: Value of debt | K37: ='Balance Sheet'!G116+'Balance Sheet'!G104 -> 5868
H38: Value of equity | K38: =K36-K37 -> 70749.737
H39: Number of shares (m) | K39: 1140
H40: Price per share | K40: =K38/K39 -> 62.061173
H41: Market price as at 01/07/25 | K41: 73.47
H42: Recommendation buy/ sell/ hold | K42: =IF(K40>K41,"BUY","SELL") -> SELL
H43: NOTE: Risk-free rate = 2.709% | See Beta Analysis sheet for full beta summary table

Sheet FCFF
A1: Free Cash Flow to the Firm (FCFF) — Wesfarmers Ltd (WES.AX)
A2: AUD $m | FY2026–FY2030 | All components formula-linked to pro-forma IS and BS | Duality checks for both FCFE and FCFF
A4: SECTION 1 — FCFF FORMULA & RELATIONSHIP TO FCFE
A5: FCFF = E + NCC − ΔWCAP − FCInv + Interest×(1−T) + Δ Other NCL
A6: FCFF = FCFE + Interest×(1−T) − Net Borrowing (key relationship)
A7: Where:
A8: E = Net Income | B8: IS row 79 — same as FCFE
A9: NCC = Non-Cash Charges (Dep + Amort) | B9: IS rows 30+29 — same as FCFE
A10: ΔWCAP = Change in Net Working Capital | B10: BS rows 35,20,113,104 — same as FCFE
A11: FCInv = Net Capital Expenditure | B11: BS row 41 + IS row 30 — same as FCFE
A12: Interest×(1−T) = After-tax interest expense | B12: IS row 50 × (1−avg tax rate) = IS row 50 × 0.7103
A13: Δ Other NCL = Change in other non-current liabilities | B13: BS row 120 — same as FCFE
A14: Note: Net Borrowing is EXCLUDED — FCFF is pre-financing (available to ALL capital providers) | B14: Net Borrowing is a financing decision, not part of the firm's operating free cash flow
A16: SECTION 2 — FCFF CALCULATION (FY2026–FY2030)
A17: Component | B17: 2026 | C17: 2027 | D17: 2028 | E17: 2029 | F17: 2030 | H17: Formula / Source Reference
A18: E — Net Income | B18: ='Income Statement'!K79 -> 3098 | C18: ='Income Statement'!L79 -> 3365 | D18: ='Income Statement'!M79 -> 3577 | E18: ='Income Statement'!N79 -> 3786 | F18: ='Income Statement'!O79 -> 3998 | H18: IS row 79: Net Income after Tax (same as FCFE)
A19: NCC — Depreciation | B19: ='Income Statement'!K30 -> 1604 | C19: ='Income Statement'!L30 -> 1671 | D19: ='Income Statement'!M30 -> 1747 | E19: ='Income Statement'!N30 -> 1830 | F19: ='Income Statement'!O30 -> 1919 | H19: IS row 30: Depreciation (same as FCFE)
A20: NCC — Amortisation | B20: ='Income Statement'!K29 -> 186 | C20: ='Income Statement'!L29 -> 197 | D20: ='Income Statement'!M29 -> 209 | E20: ='Income Statement'!N29 -> 220 | F20: ='Income Statement'!O29 -> 232 | H20: IS row 29: Amortisation (same as FCFE)
A21: NCC Total (Dep + Amort) | B21: =B19+B20 -> 1790 | C21: =C19+C20 -> 1868 | D21: =D19+D20 -> 1956 | E21: =E19+E20 -> 2050 | F21: =F19+F20 -> 2151 | H21: Sum of IS rows 30 and 29 (same as FCFE)
A22: Less: ΔWCAP — Change in Net Working Capital | B22: =('Balance Sheet'!T35-'Balance Sheet'!T20-'Balance Sheet'!T113+'Balance Sheet'!T104)-('Balance Sheet'!G35-'Balance Sheet'!G20-'Balance Sheet'!G113+'Balance Sheet'!G104) -> -316 | C22: =('Balance Sheet'!U35-'Balance Sheet'!U20-'Balance Sheet'!U113+'Balance Sheet'!U104)-('Balance Sheet'!T35-'Balance Sheet'!T20-'Balance Sheet'!T113+'Balance Sheet'!T104) -> 110 | D22: =('Balance Sheet'!V35-'Balance Sheet'!V20-'Balance Sheet'!V113+'Balance Sheet'!V104)-('Balance Sheet'!U35-'Balance Sheet'!U20-'Balance Sheet'!U113+'Balance Sheet'!U104) -> 111 | E22: =('Balance Sheet'!W35-'Balance Sheet'!W20-'Balance Sheet'!W113+'Balance Sheet'!W104)-('Balance Sheet'!V35-'Balance Sheet'!V20-'Balance Sheet'!V113+'Balance Sheet'!V104) -> 111 | F22: =('Balance Sheet'!X35-'Balance Sheet'!X20-'Balance Sheet'!X113+'Balance Sheet'!X104)-('Balance Sheet'!W35-'Balance Sheet'!W20-'Balance Sheet'!W113+'Balance Sheet'!W104) -> 110 | H22: (TCA−Cash−TCL+STD)_t − prior year | BS rows 35,20,113,104 (same as FCFE)
A23: Less: FCInv — Net Capital Expenditure | B23: ='Balance Sheet'!T41-'Balance Sheet'!G41+'Income Statement'!K30 -> 2064 | C23: ='Balance Sheet'!U41-'Balance Sheet'!T41+'Income Statement'!L30 -> 2191 | D23: ='Balance Sheet'!V41-'Balance Sheet'!U41+'Income Statement'!M30 -> 2319 | E23: ='Balance Sheet'!W41-'Balance Sheet'!V41+'Income Statement'!N30 -> 2446 | F23: ='Balance Sheet'!X41-'Balance Sheet'!W41+'Income Statement'!O30 -> 2573 | H23: PPE_t − PPE_{t-1} + Dep_t | BS row 41 + IS row 30 (same as FCFE)
A24: Add: Interest × (1−T) [avg T = 0.2897] | B24: =ROUND('Income Statement'!K50*0.7103,0) -> 329 | C24: =ROUND('Income Statement'!L50*0.7103,0) -> 274 | D24: =ROUND('Income Statement'!M50*0.7103,0) -> 274 | E24: =ROUND('Income Statement'!N50*0.7103,0) -> 274 | F24: =ROUND('Income Statement'!O50*0.7103,0) -> 274 | H24: IS row 50 (Interest Expense) × (1−0.2897) = × 0.7103 | After-tax cost of debt
A25: Add: Δ Other Non-Current Liabilities | B25: ='Balance Sheet'!T120-'Balance Sheet'!G120 -> 38 | C25: ='Balance Sheet'!U120-'Balance Sheet'!T120 -> 29 | D25: ='Balance Sheet'!V120-'Balance Sheet'!U120 -> 30 | E25: ='Balance Sheet'!W120-'Balance Sheet'!V120 -> 30 | F25: ='Balance Sheet'!X120-'Balance Sheet'!W120 -> 29 | H25: BS row 120: Other NCL Total vs prior year (same as FCFE)
A26: FCFF = E + NCC − ΔWCAP − FCInv + Interest×(1−T) + Δ Other NCL | B26: =B18+B21-B22-B23+B24+B25 -> 3507 | C26: =C18+C21-C22-C23+C24+C25 -> 3235 | D26: =D18+D21-D22-D23+D24+D25 -> 3407 | E26: =E18+E21-E22-E23+E24+E25 -> 3583 | F26: =F18+F21-F22-F23+F24+F25 -> 3769 | H26: e + ncc − ΔWCAP − FCInv + Interest×(1−T) + Δ Other NCL
A27: Duality of FCFF = Inv.Capital_{t-1} + NI + Int×(1−T) − Inv.Capital_t | B27: =('Balance Sheet'!G142+'Balance Sheet'!G116+'Balance Sheet'!G104)+'Income Statement'!K79+ROUND('Income Statement'!K50*0.7103,0)-('Balance Sheet'!T142+'Balance Sheet'!T116+'Balance Sheet'!T104) -> 3085 | C27: =('Balance Sheet'!T142+'Balance Sheet'!T116+'Balance Sheet'!T104)+'Income Statement'!L79+ROUND('Income Statement'!L50*0.7103,0)-('Balance Sheet'!U142+'Balance Sheet'!U116+'Balance Sheet'!U104) -> 3123 | D27: =('Balance Sheet'!U142+'Balance Sheet'!U116+'Balance Sheet'!U104)+'Income Statement'!M79+ROUND('Income Statement'!M50*0.7103,0)-('Balance Sheet'!V142+'Balance Sheet'!V116+'Balance Sheet'!V104) -> 3310 | E27: =('Balance Sheet'!V142+'Balance Sheet'!V116+'Balance Sheet'!V104)+'Income Statement'!N79+ROUND('Income Statement'!N50*0.7103,0)-('Balance Sheet'!W142+'Balance Sheet'!W116+'Balance Sheet'!W104) -> 3494 | F27: =('Balance Sheet'!W142+'Balance Sheet'!W116+'Balance Sheet'!W104)+'Income Statement'!O79+ROUND('Income Statement'!O50*0.7103,0)-('Balance Sheet'!X142+'Balance Sheet'!X116+'Balance Sheet'!X104) -> 3681 | H27: (Equity+LTD+STD)_{t-1} + NI + Int×(1-T) − (Equity+LTD+STD)_t | Invested Capital approach
A29: SECTION 3 — FCFE vs FCFF RECONCILIATION
A30: Item | B30: 2026 | C30: 2027 | D30: 2028 | E30: 2029 | F30: 2030 | H30: Note
A31: FCFE (from FCFE sheet) | B31: =FCFE!B25 -> 3153 | C31: =FCFE!C25 -> 3079 | D31: =FCFE!D25 -> 3250 | E31: =FCFE!E25 -> 3427 | F31: =FCFE!F25 -> 3613 | H31: FCFE row 25 on FCFE sheet
A32: Add: Interest × (1−T) | B32: =B24 -> 329 | C32: =C24 -> 274 | D32: =D24 -> 274 | E32: =E24 -> 274 | F32: =F24 -> 274 | H32: Row 24 above: IS row 50 × 0.7103
A33: Less: Net Borrowing Δ(LTD + STD) | B33: =('Balance Sheet'!T116+'Balance Sheet'!T104)-('Balance Sheet'!G116+'Balance Sheet'!G104) -> -25 | C33: =('Balance Sheet'!U116+'Balance Sheet'!U104)-('Balance Sheet'!T116+'Balance Sheet'!T104) -> 118 | D33: =('Balance Sheet'!V116+'Balance Sheet'!V104)-('Balance Sheet'!U116+'Balance Sheet'!U104) -> 117 | E33: =('Balance Sheet'!W116+'Balance Sheet'!W104)-('Balance Sheet'!V116+'Balance Sheet'!V104) -> 118 | F33: =('Balance Sheet'!X116+'Balance Sheet'!X104)-('Balance Sheet'!W116+'Balance Sheet'!W104) -> 118 | H33: Same Net Borrowing as FCFE sheet | BS rows 116+104
A34: FCFF = FCFE + Int×(1−T) − Net Borrowing | B34: =B31+B32-B33 -> 3507 | C34: =C31+C32-C33 -> 3235 | D34: =D31+D32-D33 -> 3407 | E34: =E31+E32-E33 -> 3583 | F34: =F31+F32-F33 -> 3769 | H34: Should equal FCFF row 26 above
A35: FCFF check (row 26) | B35: =B26 -> 3507 | C35: =C26 -> 3235 | D35: =D26 -> 3407 | E35: =E26 -> 3583 | F35: =F26 -> 3769 | H35: Cross-check: must equal row 34
A36: Difference (should be 0) | B36: =B34-B35 -> 0 | C36: =C34-C35 -> 0 | D36: =D34-D35 -> 0 | E36: =E34-E35 -> 0 | F36: =F34-F35 -> 0 | H36: Any non-zero value indicates a formula error
A38: SECTION 4 — DUALITY CHECK SUMMARY (FCFE and FCFF)
A39: Check | B39: 2026 | C39: 2027 | D39: 2028 | E39: 2029 | F39: 2030 | H39: Definition
A40: FCFE (built up) | B40: =FCFE!B25 -> 3153 | C40: =FCFE!C25 -> 3079 | D40: =FCFE!D25 -> 3250 | E40: =FCFE!E25 -> 3427 | F40: =FCFE!F25 -> 3613 | H40: E + NCC − ΔWCAP − FCInv + Net Borrowing + Δ Other NCL
A41: Duality of FCFE | B41: =FCFE!B26 -> 2731 | C41: =FCFE!C26 -> 2967 | D41: =FCFE!D26 -> 3153 | E41: =FCFE!E26 -> 3338 | F41: =FCFE!F26 -> 3525 | H41: Equity_{t-1} + NI − Equity_t | From FCFE sheet row 26
A42: Residual (FCFE gap) | B42: =B40-B41 -> 422 | C42: =C40-C41 -> 112 | D42: =D40-D41 -> 97 | E42: =E40-E41 -> 89 | F42: =F40-F41 -> 88 | H42: Small residual = OCI non-cash movements in equity
A44: FCFF (built up) | B44: =B26 -> 3507 | C44: =C26 -> 3235 | D44: =D26 -> 3407 | E44: =E26 -> 3583 | F44: =F26 -> 3769 | H44: E + NCC − ΔWCAP − FCInv + Int×(1−T) + Δ Other NCL
A45: Duality of FCFF | B45: =B27 -> 3085 | C45: =C27 -> 3123 | D45: =D27 -> 3310 | E45: =E27 -> 3494 | F45: =F27 -> 3681 | H45: Inv.Capital_{t-1} + NI + Int×(1−T) − Inv.Capital_t
A46: Residual (FCFF gap) | B46: =B44-B45 -> 422 | C46: =C44-C45 -> 112 | D46: =D44-D45 -> 97 | E46: =E44-E45 -> 89 | F46: =F44-F45 -> 88 | H46: Small residual = OCI non-cash movements in equity
A48: SECTION 5 — METHODOLOGY NOTES
A49: 1. FCFF represents cash flow available to ALL capital providers (debt + equity). FCFE is available to equity holders only.
A50: 2. The relationship FCFF = FCFE + Interest×(1−T) − Net Borrowing holds exactly in every forecast year (verified in Section 3).
A51: 3. Interest×(1−T) uses the average effective tax rate of 28.974% → multiplier = 0.7103. Interest from IS row 50.
A52: 4. Components E, NCC, ΔWCAP, FCInv, and Δ Other NCL are identical to FCFE. Only the financing adjustment differs.
A53: 5. FCFF Duality: Invested Capital = Equity (BS r142) + LT Debt excl. leases (r116) + ST Debt (r104). Cap. lease obligations excluded (non-cash AASB 16).
A54: 6. FCFE Duality: Equity_{t-1} + NI − Equity_t (following last year's methodology). Residuals reflect OCI reserve movements.
A55: 7. FCFF is positive in all forecast years, confirming Wesfarmers generates sufficient operating cash flow above reinvestment needs for all providers of capital.

Sheet WES.AX Price History
A1: Exchange Date | B1: Close | C1: Net | D1: %Chg | E1: Open | F1: Low | G1: High | H1: Volume | I1: Turnover - AUD | J1: Flow
A2: 46203 | B2: 79.15 | C2: -0.64 | D2: -0.00802 | E2: 80 | F2: 77.83 | G2: 80.42 | H2: 4354172 | I2: 3.4599508e+08 | J2: 4.0528377e+10
A3: 46173 | B3: 79.79 | C3: 6.87 | D3: 0.09421 | E3: 73.2 | F3: 70.8 | G3: 79.79 | H3: 35327949 | I3: 2.6466004e+09 | J3: 4.0874372e+10
A4: 46142 | B4: 72.92 | C4: 0.01 | D4: 0.00014 | E4: 73.57 | F4: 71.88 | G4: 77.51 | H4: 26033657 | I4: 1.9384291e+09 | J4: 3.8227772e+10
A5: 46112 | B5: 72.91 | C5: -6.71 | D5: -0.08428 | E5: 79 | F5: 71.5 | G5: 80.44 | H5: 35196800 | I5: 2.6401612e+09 | J5: 3.6289343e+10
A6: 46081 | B6: 79.62 | C6: -3.74 | D6: -0.04487 | E6: 83.32 | F6: 78.91 | G6: 89.47 | H6: 29038999 | I6: 2.4515594e+09 | J6: 3.8929504e+10
A7: 46053 | B7: 83.36 | C7: 2.27 | D7: 0.02799 | E7: 81.05 | F7: 79.49 | G7: 85.16 | H7: 21662800 | I7: 1.7860366e+09 | J7: 4.1381063e+10
A8: 46022 | B8: 81.09 | C8: -0.79 | D8: -0.00965 | E8: 81.97 | F8: 79.73 | G8: 82.85 | H8: 25890504 | I8: 2.1006217e+09 | J8: 3.9595027e+10
A9: 45991 | B9: 81.88 | C9: -0.614 | D9: -0.00745 | E9: 81.424 | F9: 78.8 | G9: 83.369 | H9: 32332415 | I9: 2.6324226e+09 | J9: 4.1695648e+10
A10: 45961 | B10: 82.494 | C10: -7.876 | D10: -0.08715 | E10: 90.646 | F10: 82.494 | G10: 93.003 | H10: 32226965 | I10: 2.8874217e+09 | J10: 4.4328071e+10
A11: 45930 | B11: 90.371 | C11: 0.206 | D11: 0.00229 | E11: 89.546 | F11: 86.158 | G11: 92.708 | H11: 31923770 | I11: 2.9283112e+09 | J11: 4.7215493e+10
A12: 45900 | B12: 90.165 | C12: 5.951 | D12: 0.07067 | E12: 82.868 | F12: 82.809 | G12: 93.469 | H12: 39080238 | I12: 3.5277132e+09 | J12: 4.4287182e+10
A13: 45869 | B13: 84.213 | C13: 0.982 | D13: 0.0118 | E13: 83.28 | F13: 80.079 | G13: 84.252 | H13: 26476048 | I13: 2.2139882e+09 | J13: 4.0759468e+10
... A79: 43861 | B79: 42.774 | C79: 3.605 | D79: 0.09203 | E79: 38.743 | F79: 38.743 | G79: 43.077 | H79: 36375409 | I79: 1577696031 | J79: 16822839952

Sheet ASX200 Price History
A1: Exchange Date | B1: Close | C1: Net | D1: %Chg | E1: Open | F1: Low | G1: High | H1: Volume | I1: Turnover - AUD | J1: Flow
A2: 46203 | B2: 8724.4 | C2: -7.3 | D2: -0.00083603422 | E2: 8731.7 | F2: 8625.8 | G2: 8736.5 | H2: 1438363523 | I2: 14536138656 | J2: 3176765991313
A3: 46173 | B3: 8731.7 | C3: 65.9 | D3: 0.0076046066 | E3: 8665.8 | F3: 8485.2 | G3: 8887.9 | H3: 15078197442 | I3: 158667804785 | J3: 3191302129969
A4: 46142 | B4: 8665.8 | C4: 184 | D4: 0.021693508 | E4: 8481.8 | F4: 8481.8 | G4: 9021.5 | H4: 14586715624 | I4: 142325273944 | J4: 3032634325184
A5: 46112 | B5: 8481.8 | C5: -716.8 | D5: -0.077924902 | E5: 9198.6 | F5: 8262.4 | G5: 9200.9 | H5: 19831072574 | I5: 195551273969 | J5: 2890309051240
A6: 46081 | B6: 9198.6 | C6: 329.5 | D6: 0.037151458 | E6: 8869.1 | F6: 8683.7 | G6: 9202.9 | H6: 15226198926 | I6: 161240002910 | J6: 3085860325209
A7: 46053 | B7: 8869.1 | C7: 154.8 | D7: 0.017763905 | E7: 8714.3 | F7: 8675.6 | G7: 8978.5 | H7: 12187342793 | I7: 126727079007 | J7: 2924620322299
A8: 46022 | B8: 8714.3 | C8: 100.2 | D8: 0.011632092 | E8: 8614.1 | F8: 8547.1 | G8: 8805.5 | H8: 13136543247 | I8: 131090869543 | J8: 2797893243292
A9: 45991 | B9: 8614.1 | C9: -267.8 | D9: -0.030151206 | E9: 8881.9 | F9: 8383.2 | G9: 8894.8 | H9: 13453553009 | I9: 140051823222 | J9: 2666802373749
A10: 45961 | B10: 8881.9 | C10: 33.1 | D10: 0.0037406202 | E10: 8848.8 | F10: 8809 | G10: 9115.2 | H10: 15555119470 | I10: 152824628369 | J10: 2806854196971
A11: 45930 | B11: 8848.8 | C11: -124.3 | D11: -0.013852515 | E11: 8973.1 | F11: 8731.3 | G11: 8973.1 | H11: 17242693679 | I11: 158744767714 | J11: 2654029568602
A12: 45900 | B12: 8973.1 | C12: 230.3 | D12: 0.026341675 | E12: 8742.8 | F12: 8630.9 | G12: 9054.5 | H12: 15145750500 | I12: 150497828195 | J12: 2812774336316
A13: 45869 | B13: 8742.8 | C13: 200.5 | D13: 0.02347143 | E13: 8542.3 | F13: 8531.4 | G13: 8776.4 | H13: 14678876386 | I13: 133270468526 | J13: 2662276508121
... A79: 43861 | B79: 7017.2 | C79: 333.1 | D79: 0.049834682 | E79: 6684.1 | F79: 6669.2 | G79: 7144.9 | H79: 10881213885 | I79: 96670369200 | J79: 711486564400

Sheet Beta Analysis
A1: DATE | B1: WES Price | C1: ASX200 | D1: WES Return | E1: Market Research | G1: SUMMARY OUTPUT
A2: 46203 | B2: 79.15 | C2: 8724.4
A3: 46173 | B3: 79.79 | C3: 8731.7 | D3: =(B3-B2)/B2 -> 0.0080859128 | E3: =(C3-C2)/C2 -> 0.00083673376 | G3: Regression Statistics
A4: 46142 | B4: 72.92 | C4: 8665.8 | D4: =(B4-B3)/B3 -> -0.086101015 | E4: =(C4-C3)/C3 -> -0.007547213 | G4: Multiple R | H4: 0.7500471
A5: 46112 | B5: 72.91 | C5: 8481.8 | D5: =(B5-B4)/B4 -> -0.00013713659 | E5: =(C5-C4)/C4 -> -0.021232893 | G5: R Square | H5: 0.56257065
A6: 46081 | B6: 79.62 | C6: 9198.6 | D6: =(B6-B5)/B5 -> 0.092031271 | E6: =(C6-C5)/C5 -> 0.084510363 | G6: Adjusted R Square | H6: 0.55665944
A7: 46053 | B7: 83.36 | C7: 8869.1 | D7: =(B7-B6)/B6 -> 0.046973122 | E7: =(C7-C6)/C6 -> -0.035820668 | G7: Standard Error | H7: 0.04329824
A8: 46022 | B8: 81.09 | C8: 8714.3 | D8: =(B8-B7)/B7 -> -0.027231286 | E8: =(C8-C7)/C7 -> -0.017453857 | G8: Observations | H8: 76
A9: 45991 | B9: 81.88 | C9: 8614.1 | D9: =(B9-B8)/B8 -> 0.0097422617 | E9: =(C9-C8)/C8 -> -0.011498342
A10: 45961 | B10: 82.494 | C10: 8881.9 | D10: =(B10-B9)/B9 -> 0.0074987787 | E10: =(C10-C9)/C9 -> 0.031088564 | G10: ANOVA
A11: 45930 | B11: 90.371 | C11: 8848.8 | D11: =(B11-B10)/B10 -> 0.095485732 | E11: =(C11-C10)/C10 -> -0.0037266801 | H11: df | I11: SS | J11: MS | K11: F | L11: Significance F
A12: 45900 | B12: 90.165 | C12: 8973.1 | D12: =(B12-B11)/B11 -> -0.0022794923 | E12: =(C12-C11)/C11 -> 0.014047102 | G12: Regression | H12: 1 | I12: 0.1784191 | J12: 0.1784191 | K12: 95.170176 | L12: 6.3099148e-15
A13: 45869 | B13: 84.213 | C13: 8742.8 | D13: =(B13-B12)/B12 -> -0.066012311 | E13: =(C13-C12)/C12 -> -0.025665601 | G13: Residual | H13: 74 | I13: 0.13873058 | J13: 0.0018747376
A14: 45838 | B14: 83.231 | C14: 8542.3 | D14: =(B14-B13)/B13 -> -0.011660907 | E14: =(C14-C13)/C13 -> -0.022933156 | G14: Total | H14: 75 | I14: 0.31714968
A15: 45808 | B15: 81.532 | C15: 8434.7 | D15: =(B15-B14)/B14 -> -0.020413067 | E15: =(C15-C14)/C14 -> -0.012596139
A16: 45777 | B16: 76.916 | C16: 8126.2 | D16: =(B16-B15)/B15 -> -0.056615807 | E16: =(C16-C15)/C15 -> -0.0365751 | H16: Coefficients | I16: Standard Error | J16: t Stat | K16: P-value | L16: Lower 95% | M16: Upper 95% | N16: Lower 95.0% | O16: Upper 95.0%
A17: 45747 | B17: 70.719 | C17: 7843.4 | D17: =(B17-B16)/B16 -> -0.080568412 | E17: =(C17-C16)/C16 -> -0.034801014 | G17: Intercept | H17: -0.0043870955 | I17: 0.0049698039 | J17: -0.88275022 | K17: 0.38022993 | L17: -0.014289646 | M17: 0.0055154549 | N17: -0.014289646 | O17: 0.0055154549
A18: 45716 | B18: 72.831 | C18: 8172.4 | D18: =(B18-B17)/B17 -> 0.029864676 | E18: =(C18-C17)/C17 -> 0.041946095 | G18: 0.00083673376 | H18: 0.98911442 | I18: 0.10139023 | J18: 9.7555203 | K18: 6.3099148e-15 | L18: 0.78708998 | M18: 1.1911389 | N18: 0.78708998 | O18: 1.1911389
A19: 45688 | B19: 75.227 | C19: 8532.3 | D19: =(B19-B18)/B18 -> 0.032898079 | E19: =(C19-C18)/C18 -> 0.044038471
A20: 45657 | B20: 70.248 | C20: 8159.1 | D20: =(B20-B19)/B19 -> -0.066186343 | E20: =(C20-C19)/C19 -> -0.043739672
A21: 45626 | B21: 70.543 | C21: 8436.2 | D21: =(B21-B20)/B20 -> 0.0041994078 | E21: =(C21-C20)/C20 -> 0.033962079
A22: 45596 | B22: 66.074 | C22: 8160 | D22: =(B22-B21)/B21 -> -0.063351431 | E22: =(C22-C21)/C21 -> -0.032739859 | G22: SUMMARY TABLE | H22: VALUES
A23: 45565 | B23: 69.168 | C23: 8269.8 | D23: =(B23-B22)/B22 -> 0.046826286 | E23: =(C23-C22)/C22 -> 0.013455882
A24: 45535 | B24: 71.299 | C24: 8091.9 | D24: =(B24-B23)/B23 -> 0.030809045 | E24: =(C24-C23)/C23 -> -0.021512008 | G24: Regression Period | H24: 31 Jan 2020 - Jun 2026
A25: 45504 | B25: 72.33 | C25: 8092.3 | D25: =(B25-B24)/B24 -> 0.014460231 | E25: =(C25-C24)/C24 -> 4.9432148e-05 | G25: Observations | H25: 76
A26: 45473 | B26: 64.012 | C26: 7767.5 | D26: =(B26-B25)/B25 -> -0.11500069 | E26: =(C26-C25)/C25 -> -0.04013692 | G26: R Square | H26: 0.5626
A27: 45443 | B27: 63.727 | C27: 7701.7 | D27: =(B27-B26)/B26 -> -0.0044522902 | E27: =(C27-C26)/C26 -> -0.0084711941 | G27: Raw levered Beta | H27: 0.98911
A28: 45412 | B28: 65.593 | C28: 7664.1 | D28: =(B28-B27)/B27 -> 0.029281152 | E28: =(C28-C27)/C27 -> -0.004882039 | G28: Standard Error | H28: 0.1014
A29: 45382 | B29: 67.174 | C29: 7896.9 | D29: =(B29-B28)/B28 -> 0.024103182 | E29: =(C29-C28)/C28 -> 0.030375387 | G29: t-Statistic | H29: 9.756
A30: 45351 | B30: 65.446 | C30: 7698.7 | D30: =(B30-B29)/B29 -> -0.025724239 | E30: =(C30-C29)/C29 -> -0.025098456 | G30: p-value | H30: 6.3099148e-15
A31: 45322 | B31: 57.127 | C31: 7680.7 | D31: =(B31-B30)/B30 -> -0.12711243 | E31: =(C31-C30)/C30 -> -0.0023380571 | G31: Tax Rate | H31: 0.2908
A32: 45291 | B32: 56.018 | C32: 7590.8 | D32: =(B32-B31)/B31 -> -0.019412887 | E32: =(C32-C31)/C31 -> -0.011704662 | G32: Avereage D/E | H32: 2.4015
A33: 45260 | B33: 51.716 | C33: 7087.3 | D33: =(B33-B32)/B32 -> -0.076796744 | E33: =(C33-C32)/C32 -> -0.066330295 | G33: Unlevered Beta | H33: =H27/(1+(1-0.2908)*H32) -> 0.36591098
A34: 45230 | B34: 49.615 | C34: 6780.7 | D34: =(B34-B33)/B33 -> -0.040625725 | E34: =(C34-C33)/C33 -> -0.04326048
A35: 45199 | B35: 51.913 | C35: 7048.6 | D35: =(B35-B34)/B34 -> 0.046316638 | E35: =(C35-C34)/C34 -> 0.039509195 | G35: Risk-Free Rate | H35: 0.02709
A36: 45169 | B36: 52.904 | C36: 7305.3 | D36: =(B36-B35)/B35 -> 0.019089631 | E36: =(C36-C35)/C35 -> 0.03641858 | G36: Market Risk Premium | H36: 0.07733
A37: 45138 | B37: 48.76 | C37: 7410.4 | D37: =(B37-B36)/B36 -> -0.078330561 | E37: =(C37-C36)/C36 -> 0.014386815 | G37: Re-levered Beta 2026 | H37: =H33*(1+(1-H31)*1.0747) -> 0.6448
A38: 45107 | B38: 48.456 | C38: 7203.3 | D38: =(B38-B37)/B37 -> -0.0062346185 | E38: =(C38-C37)/C37 -> -0.027947209 | G38: Re-levered Beta 2027 | H38: =H33*(1+(1-H31)*1.0216) -> 0.63102034
A39: 45077 | B39: 46.816 | C39: 7091.3 | D39: =(B39-B38)/B38 -> -0.033845138 | E39: =(C39-C38)/C38 -> -0.015548429 | G39: Re-levered Beta 2028 | H39: =H33*(1+(1-H31)*0.9711) -> 0.61791538
A40: 45046 | B40: 51.039 | C40: 7309.2 | D40: =(B40-B39)/B39 -> 0.090204204 | E40: =(C40-C39)/C39 -> 0.030727793 | G40: Re-levered Beta 2029 | H40: =H33*(1+(1-H31)*0.9238) -> 0.60564084
A41: 45016 | B41: 49.349 | C41: 7177.8 | D41: =(B41-B40)/B40 -> -0.033111934 | E41: =(C41-C40)/C40 -> -0.017977344 | G41: Re-levered Beta 2030 | H41: =H33*(1+(1-H31)*0.8794) -> 0.59411886
A42: 44985 | B42: 47.375 | C42: 7258.4 | D42: =(B42-B41)/B41 -> -0.040000811 | E42: =(C42-C41)/C41 -> 0.011229067
A43: 44957 | B43: 48.76 | C43: 7476.7 | D43: =(B43-B42)/B42 -> 0.029234828 | E43: =(C43-C42)/C42 -> 0.030075499
A44: 44926 | B44: 45.087 | C44: 7038.7 | D44: =(B44-B43)/B43 -> -0.075328138 | E44: =(C44-C43)/C43 -> -0.058581995
A45: 44895 | B45: 47.699 | C45: 7284.2 | D45: =(B45-B44)/B44 -> 0.057932442 | E45: =(C45-C44)/C44 -> 0.0348786
A46: 44865 | B46: 44.645 | C46: 6863.5 | D46: =(B46-B45)/B45 -> -0.0640265 | E46: =(C46-C45)/C45 -> -0.057755141
A47: 44834 | B47: 41.954 | C47: 6474.2 | D47: =(B47-B46)/B46 -> -0.060275507 | E47: =(C47-C46)/C46 -> -0.056720332
A48: 44804 | B48: 46.167 | C48: 6986.8 | D48: =(B48-B47)/B47 -> 0.10041951 | E48: =(C48-C47)/C47 -> 0.079175806
A49: 44773 | B49: 45.794 | C49: 6945.2 | D49: =(B49-B48)/B48 -> -0.008079364 | E49: =(C49-C48)/C48 -> -0.0059540848
A50: 44742 | B50: 41.159 | C50: 6568.1 | D50: =(B50-B49)/B49 -> -0.10121413 | E50: =(C50-C49)/C49 -> -0.054296493
A51: 44712 | B51: 46.344 | C51: 7211.2 | D51: =(B51-B50)/B50 -> 0.12597488 | E51: =(C51-C50)/C50 -> 0.097912638
A52: 44681 | B52: 48.524 | C52: 7435 | D52: =(B52-B51)/B51 -> 0.04703953 | E52: =(C52-C51)/C51 -> 0.031035057
A53: 44651 | B53: 49.507 | C53: 7499.6 | D53: =(B53-B52)/B52 -> 0.020258017 | E53: =(C53-C52)/C52 -> 0.0086886348
... A79: 43861 | B79: 42.774 | C79: 7017.2 | D79: =(B79-B78)/B78 -> 0.11219741 | E79: =(C79-C78)/C78 -> 0.089424331
